Workbook

Sheet Carnes
A1: Carnes | F1: 1 | I1: 2 | L1: 3 | O1: 4 | R1: 5 | U1: 6 | X1: 7 | AA1: 8 | AD1: 9 | AG1: 10 | AJ1: 11 | AM1: 12 | AP1: 13 | AS1: 14 | AV1: 15 | AY1: 16 | BB1: 17 | BE1: 18 | BH1: 19 | BK1: 20 | BN1: 21 | BQ1: 22 | BT1: 23 | BW1: 24 | BZ1: 25 | CC1: 26 | CF1: 27 | CI1: 28 | CL1: 29 | CO1: 30 | CR1: 31 | CU1: Total mes
A2: Producto | B2: Medidas | C2: Cantidad | D2: Valor | E2: Total | F2: Cantid | G2: Costo unit | H2: Vr. compra | I2: Cantid | J2: Costo unit | K2: Vr. compra | L2: Cantid | M2: Costo unit | N2: Vr. compra | O2: Cantid | P2: Costo unit | Q2: Vr. compra | R2: Cantid | S2: Costo | T2: Vr. compra | U2: Cantid | V2: Costo unit | W2: Vr. compra | X2: Cantid | Y2: Costo unit | Z2: Vr. compra | AA2: Cantid | AB2: Costo unit | AC2: Vr. compra | AD2: Cantid | AE2: Costo unit | AF2: Vr. compra | AG2: Cantid | AH2: Costo unit | AI2: Vr. compra | AJ2: Cantid | AK2: Costo unit | AL2: Vr. compra | AM2: Cantid | AN2: Costo unit | AO2: Vr. compra | AP2: Cantid | AQ2: Costo | AR2: Vr. compra | AS2: Cantid | AT2: Costo unit | AU2: Vr. compra | AV2: Cantid | AW2: Costo unit | AX2: Vr. compra | AY2: Cantid | AZ2: Costo unit | BA2: Vr. compra | BB2: Cantid | BC2: Costo unit | BD2: Vr. compra | BE2: Cantid | BF2: Costo unit | BG2: Vr. compra | BH2: Cantid | BI2: Costo unit | BJ2: Vr. compra | BK2: Cantid | BL2: Costo unit | BM2: Vr. compra | BN2: Cantid | BO2: Costo | BP2: Vr. compra | BQ2: Cantid | BR2: Costo unit | BS2: Vr. compra | BT2: Cantid | BU2: Costo unit | BV2: Vr. compra | BW2: Cantid | BX2: Costo unit | BY2: Vr. compra | BZ2: Cantid | CA2: Costo unit | CB2: Vr. compra | CC2: Cantid | CD2: Costo unit | CE2: Vr. compra | CF2: Cantid | CG2: Costo unit | CH2: Vr. compra | CI2: Cantid | CJ2: Costo unit | CK2: Vr. compra | CL2: Cantid | CM2: Costo unit | CN2: Vr. compra | CO2: Cantid | CP2: Costo unit | CQ2: Vr. compra | CR2: Cantid | CS2: Costo unit | CT2: Vr. compra | CU2: Cantid | CV2: Costo unit | CW2: Vr. compra
A3: Alas de pollo | B3: Kg | E3: 0 | H3: =IFERROR(F3*G3, 0) | K3: =IFERROR(I3*J3, 0) | N3: =IFERROR(L3*M3, 0) | Q3: =IFERROR(O3*P3, 0) | T3: =IFERROR(R3*S3, 0) | W3: =IFERROR(U3*V3, 0) | X3: 3.176 | Y3: 14500 | Z3: 46052 | AA3: 3.145 | AB3: 14500 | AC3: 45603 | AF3: =IFERROR(AD3*AE3, 0) | AI3: =IFERROR(AG3*AH3, 0) | AL3: =IFERROR(AJ3*AK3, 0) | AO3: =IFERROR(AM3*AN3, 0) | AR3: =IFERROR(AP3*AQ3, 0) | AU3: =IFERROR(AS3*AT3, 0) | AX3: =IFERROR(AV3*AW3, 0) | BA3: =IFERROR(AY3*AZ3, 0) | BD3: =IFERROR(BB3*BC3, 0) | BG3: =IFERROR(BE3*BF3, 0) | BJ3: =IFERROR(BH3*BI3, 0) | BM3: =IFERROR(BK3*BL3, 0) | BP3: =IFERROR(BN3*BO3, 0) | BS3: =IFERROR(BQ3*BR3, 0) | BV3: =IFERROR(BT3*BU3, 0) | BW3: 10 | BX3: 5000 | BY3: 50000 | CB3: =IFERROR(BZ3*CA3, 0) | CE3: =IFERROR(CC3*CD3, 0) | CH3: =IFERROR(CF3*CG3, 0) | CK3: =IFERROR(CI3*CJ3, 0) | CN3: =IFERROR(CL3*CM3, 0) | CQ3: =IFERROR(CO3*CP3, 0) | CT3: =IFERROR(CR3*CS3, 0) | CU3: =IFERROR(SUM(F3,I3,L3,O3,R3,U3,X3,AA3,AD3,AG3,AJ3,AM3,AP3,AS3,AV3,AY3,BB3,BE3,BH3,BK3,BN3,BQ3,BT3,BW3,BZ3,CC3,CF3,CI3,CL3,CO3,CR3), 0) | CV3: =IFERROR(AVERAGE(G3,J3,M3,P3,S3,V3,Y3,AB3,AE3,AH3,AK3,AN3,AQ3,AT3,AW3,AZ3,BC3,BF3,BI3,BL3,BO3,BR3,BU3,BX3,CA3,CD3,CG3,CJ3,CM3,CP3,CS3), 0) | CW3: =CU3*CV3
A4: Bagre de mar | B4: Kg | E4: 0 | H4: =IFERROR(F4*G4, 0) | I4: 20 | J4: 16500 | K4: 330000 | N4: =IFERROR(L4*M4, 0) | Q4: =IFERROR(O4*P4, 0) | T4: =IFERROR(R4*S4, 0) | W4: =IFERROR(U4*V4, 0) | Z4: =IFERROR(X4*Y4, 0) | AA4: 21 | AB4: 16500 | AC4: 759000 | AF4: =IFERROR(AD4*AE4, 0) | AI4: =IFERROR(AG4*AH4, 0) | AL4: =IFERROR(AJ4*AK4, 0) | AO4: =IFERROR(AM4*AN4, 0) | AR4: =IFERROR(AP4*AQ4, 0) | AU4: =IFERROR(AS4*AT4, 0) | AV4: 26 | AW4: 16500 | AX4: 429000 | BA4: =IFERROR(AY4*AZ4, 0) | BD4: =IFERROR(BB4*BC4, 0) | BG4: =IFERROR(BE4*BF4, 0) | BJ4: =IFERROR(BH4*BI4, 0) | BM4: =IFERROR(BK4*BL4, 0) | BP4: =IFERROR(BN4*BO4, 0) | BS4: =IFERROR(BQ4*BR4, 0) | BT4: 22.12 | BU4: 17000 | BV4: 376040 | BY4: =IFERROR(BW4*BX4, 0) | CB4: =IFERROR(BZ4*CA4, 0) | CE4: =IFERROR(CC4*CD4, 0) | CH4: =IFERROR(CF4*CG4, 0) | CK4: =IFERROR(CI4*CJ4, 0) | CN4: =IFERROR(CL4*CM4, 0) | CQ4: =IFERROR(CO4*CP4, 0) | CT4: =IFERROR(CR4*CS4, 0) | CU4: =IFERROR(SUM(F4,I4,L4,O4,R4,U4,X4,AA4,AD4,AG4,AJ4,AM4,AP4,AS4,AV4,AY4,BB4,BE4,BH4,BK4,BN4,BQ4,BT4,BW4,BZ4,CC4,CF4,CI4,CL4,CO4,CR4), 0) | CV4: =IFERROR(AVERAGE(G4,J4,M4,P4,S4,V4,Y4,AB4,AE4,AH4,AK4,AN4,AQ4,AT4,AW4,AZ4,BC4,BF4,BI4,BL4,BO4,BR4,BU4,BX4,CA4,CD4,CG4,CJ4,CM4,CP4,CS4), 0) | CW4: =CU4*CV4
A5: Barcino de res | B5: Kg | E5: 0 | H5: =IFERROR(F5*G5, 0) | K5: =IFERROR(I5*J5, 0) | N5: =IFERROR(L5*M5, 0) | Q5: =IFERROR(O5*P5, 0) | T5: =IFERROR(R5*S5, 0) | W5: =IFERROR(U5*V5, 0) | X5: 19.55 | Y5: 26900 | Z5: 525895 | AC5: =IFERROR(AA5*AB5, 0) | AF5: =IFERROR(AD5*AE5, 0) | AG5: 27.1 | AH5: 26900 | AI5: 728990 | AL5: =IFERROR(AJ5*AK5, 0) | AO5: =IFERROR(AM5*AN5, 0) | AR5: =IFERROR(AP5*AQ5, 0) | AU5: =IFERROR(AS5*AT5, 0) | AV5: 23.2 | AW5: 26900 | AX5: 624080 | BA5: =IFERROR(AY5*AZ5, 0) | BB5: 24.2 | BC5: 26900 | BD5: 650980 | BG5: =IFERROR(BE5*BF5, 0) | BJ5: =IFERROR(BH5*BI5, 0) | BM5: =IFERROR(BK5*BL5, 0) | BP5: =IFERROR(BN5*BO5, 0) | BS5: =IFERROR(BQ5*BR5, 0) | BT5: 21.5 | BU5: 26900 | BV5: 578350 | BY5: =IFERROR(BW5*BX5, 0) | CB5: =IFERROR(BZ5*CA5, 0) | CE5: =IFERROR(CC5*CD5, 0) | CH5: =IFERROR(CF5*CG5, 0) | CK5: =IFERROR(CI5*CJ5, 0) | CN5: =IFERROR(CL5*CM5, 0) | CQ5: =IFERROR(CO5*CP5, 0) | CT5: =IFERROR(CR5*CS5, 0) | CU5: =IFERROR(SUM(F5,I5,L5,O5,R5,U5,X5,AA5,AD5,AG5,AJ5,AM5,AP5,AS5,AV5,AY5,BB5,BE5,BH5,BK5,BN5,BQ5,BT5,BW5,BZ5,CC5,CF5,CI5,CL5,CO5,CR5), 0) | CV5: =IFERROR(AVERAGE(G5,J5,M5,P5,S5,V5,Y5,AB5,AE5,AH5,AK5,AN5,AQ5,AT5,AW5,AZ5,BC5,BF5,BI5,BL5,BO5,BR5,BU5,BX5,CA5,CD5,CG5,CJ5,CM5,CP5,CS5), 0) | CW5: =CU5*CV5
A6: Bola negra | B6: Kg | E6: 0 | H6: =IFERROR(F6*G6, 0) | K6: =IFERROR(I6*J6, 0) | N6: =IFERROR(L6*M6, 0) | Q6: =IFERROR(O6*P6, 0) | T6: =IFERROR(R6*S6, 0) | W6: =IFERROR(U6*V6, 0) | Z6: =IFERROR(X6*Y6, 0) | AC6: =IFERROR(AA6*AB6, 0) | AF6: =IFERROR(AD6*AE6, 0) | AI6: =IFERROR(AG6*AH6, 0) | AJ6: 8.07 | AK6: 34000 | AL6: 274380 | AO6: =IFERROR(AM6*AN6, 0) | AR6: =IFERROR(AP6*AQ6, 0) | AU6: =IFERROR(AS6*AT6, 0) | AX6: =IFERROR(AV6*AW6, 0) | BA6: =IFERROR(AY6*AZ6, 0) | BD6: =IFERROR(BB6*BC6, 0) | BG6: =IFERROR(BE6*BF6, 0) | BJ6: =IFERROR(BH6*BI6, 0) | BM6: =IFERROR(BK6*BL6, 0) | BP6: =IFERROR(BN6*BO6, 0) | BS6: =IFERROR(BQ6*BR6, 0) | BV6: =IFERROR(BT6*BU6, 0) | BY6: =IFERROR(BW6*BX6, 0) | CB6: =IFERROR(BZ6*CA6, 0) | CE6: =IFERROR(CC6*CD6, 0) | CH6: =IFERROR(CF6*CG6, 0) | CK6: =IFERROR(CI6*CJ6, 0) | CN6: =IFERROR(CL6*CM6, 0) | CQ6: =IFERROR(CO6*CP6, 0) | CT6: =IFERROR(CR6*CS6, 0) | CU6: =IFERROR(SUM(F6,I6,L6,O6,R6,U6,X6,AA6,AD6,AG6,AJ6,AM6,AP6,AS6,AV6,AY6,BB6,BE6,BH6,BK6,BN6,BQ6,BT6,BW6,BZ6,CC6,CF6,CI6,CL6,CO6,CR6), 0) | CV6: =IFERROR(AVERAGE(G6,J6,M6,P6,S6,V6,Y6,AB6,AE6,AH6,AK6,AN6,AQ6,AT6,AW6,AZ6,BC6,BF6,BI6,BL6,BO6,BR6,BU6,BX6,CA6,CD6,CG6,CJ6,CM6,CP6,CS6), 0) | CW6: =CU6*CV6
A7: Bondiola importada | B7: Kg | E7: 0 | H7: =IFERROR(F7*G7, 0) | K7: =IFERROR(I7*J7, 0) | N7: =IFERROR(L7*M7, 0) | Q7: =IFERROR(O7*P7, 0) | T7: =IFERROR(R7*S7, 0) | W7: =IFERROR(U7*V7, 0) | Z7: =IFERROR(X7*Y7, 0) | AC7: =IFERROR(AA7*AB7, 0) | AF7: =IFERROR(AD7*AE7, 0) | AI7: =IFERROR(AG7*AH7, 0) | AL7: =IFERROR(AJ7*AK7, 0) | AO7: =IFERROR(AM7*AN7, 0) | AR7: =IFERROR(AP7*AQ7, 0) | AU7: =IFERROR(AS7*AT7, 0) | AX7: =IFERROR(AV7*AW7, 0) | BA7: =IFERROR(AY7*AZ7, 0) | BD7: =IFERROR(BB7*BC7, 0) | BG7: =IFERROR(BE7*BF7, 0) | BJ7: =IFERROR(BH7*BI7, 0) | BM7: =IFERROR(BK7*BL7, 0) | BP7: =IFERROR(BN7*BO7, 0) | BS7: =IFERROR(BQ7*BR7, 0) | BV7: =IFERROR(BT7*BU7, 0) | BY7: =IFERROR(BW7*BX7, 0) | CB7: =IFERROR(BZ7*CA7, 0) | CE7: =IFERROR(CC7*CD7, 0) | CH7: =IFERROR(CF7*CG7, 0) | CK7: =IFERROR(CI7*CJ7, 0) | CN7: =IFERROR(CL7*CM7, 0) | CQ7: =IFERROR(CO7*CP7, 0) | CT7: =IFERROR(CR7*CS7, 0) | CU7: =IFERROR(SUM(F7,I7,L7,O7,R7,U7,X7,AA7,AD7,AG7,AJ7,AM7,AP7,AS7,AV7,AY7,BB7,BE7,BH7,BK7,BN7,BQ7,BT7,BW7,BZ7,CC7,CF7,CI7,CL7,CO7,CR7), 0) | CV7: =IFERROR(AVERAGE(G7,J7,M7,P7,S7,V7,Y7,AB7,AE7,AH7,AK7,AN7,AQ7,AT7,AW7,AZ7,BC7,BF7,BI7,BL7,BO7,BR7,BU7,BX7,CA7,CD7,CG7,CJ7,CM7,CP7,CS7), 0) | CW7: =CU7*CV7
A8: Cabeza de lomo | B8: Kg | E8: 0 | H8: =IFERROR(F8*G8, 0) | K8: =IFERROR(I8*J8, 0) | N8: =IFERROR(L8*M8, 0) | Q8: =IFERROR(O8*P8, 0) | T8: =IFERROR(R8*S8, 0) | W8: =IFERROR(U8*V8, 0) | Z8: =IFERROR(X8*Y8, 0) | AC8: =IFERROR(AA8*AB8, 0) | AF8: =IFERROR(AD8*AE8, 0) | AI8: =IFERROR(AG8*AH8, 0) | AL8: =IFERROR(AJ8*AK8, 0) | AO8: =IFERROR(AM8*AN8, 0) | AR8: =IFERROR(AP8*AQ8, 0) | AU8: =IFERROR(AS8*AT8, 0) | AX8: =IFERROR(AV8*AW8, 0) | BA8: =IFERROR(AY8*AZ8, 0) | BD8: =IFERROR(BB8*BC8, 0) | BG8: =IFERROR(BE8*BF8, 0) | BJ8: =IFERROR(BH8*BI8, 0) | BM8: =IFERROR(BK8*BL8, 0) | BP8: =IFERROR(BN8*BO8, 0) | BS8: =IFERROR(BQ8*BR8, 0) | BV8: =IFERROR(BT8*BU8, 0) | BY8: =IFERROR(BW8*BX8, 0) | CB8: =IFERROR(BZ8*CA8, 0) | CE8: =IFERROR(CC8*CD8, 0) | CH8: =IFERROR(CF8*CG8, 0) | CK8: =IFERROR(CI8*CJ8, 0) | CN8: =IFERROR(CL8*CM8, 0) | CQ8: =IFERROR(CO8*CP8, 0) | CT8: =IFERROR(CR8*CS8, 0) | CU8: =IFERROR(SUM(F8,I8,L8,O8,R8,U8,X8,AA8,AD8,AG8,AJ8,AM8,AP8,AS8,AV8,AY8,BB8,BE8,BH8,BK8,BN8,BQ8,BT8,BW8,BZ8,CC8,CF8,CI8,CL8,CO8,CR8), 0) | CV8: =IFERROR(AVERAGE(G8,J8,M8,P8,S8,V8,Y8,AB8,AE8,AH8,AK8,AN8,AQ8,AT8,AW8,AZ8,BC8,BF8,BI8,BL8,BO8,BR8,BU8,BX8,CA8,CD8,CG8,CJ8,CM8,CP8,CS8), 0) | CW8: =CU8*CV8
A9: Caderita | B9: Kg | E9: 0 | H9: =IFERROR(F9*G9, 0) | K9: =IFERROR(I9*J9, 0) | N9: =IFERROR(L9*M9, 0) | Q9: =IFERROR(O9*P9, 0) | T9: =IFERROR(R9*S9, 0) | W9: =IFERROR(U9*V9, 0) | Z9: =IFERROR(X9*Y9, 0) | AC9: =IFERROR(AA9*AB9, 0) | AD9: 6.04 | AE9: 34000 | AF9: 205360 | AI9: =IFERROR(AG9*AH9, 0) | AL9: =IFERROR(AJ9*AK9, 0) | AO9: =IFERROR(AM9*AN9, 0) | AR9: =IFERROR(AP9*AQ9, 0) | AU9: =IFERROR(AS9*AT9, 0) | AV9: 10.1 | AW9: 33000 | AX9: 333300 | BA9: =IFERROR(AY9*AZ9, 0) | BD9: =IFERROR(BB9*BC9, 0) | BG9: =IFERROR(BE9*BF9, 0) | BJ9: =IFERROR(BH9*BI9, 0) | BM9: =IFERROR(BK9*BL9, 0) | BP9: =IFERROR(BN9*BO9, 0) | BS9: =IFERROR(BQ9*BR9, 0) | BV9: =IFERROR(BT9*BU9, 0) | BY9: =IFERROR(BW9*BX9, 0) | CB9: =IFERROR(BZ9*CA9, 0) | CE9: =IFERROR(CC9*CD9, 0) | CH9: =IFERROR(CF9*CG9, 0) | CK9: =IFERROR(CI9*CJ9, 0) | CN9: =IFERROR(CL9*CM9, 0) | CQ9: =IFERROR(CO9*CP9, 0) | CT9: =IFERROR(CR9*CS9, 0) | CU9: =IFERROR(SUM(F9,I9,L9,O9,R9,U9,X9,AA9,AD9,AG9,AJ9,AM9,AP9,AS9,AV9,AY9,BB9,BE9,BH9,BK9,BN9,BQ9,BT9,BW9,BZ9,CC9,CF9,CI9,CL9,CO9,CR9), 0) | CV9: =IFERROR(AVERAGE(G9,J9,M9,P9,S9,V9,Y9,AB9,AE9,AH9,AK9,AN9,AQ9,AT9,AW9,AZ9,BC9,BF9,BI9,BL9,BO9,BR9,BU9,BX9,CA9,CD9,CG9,CJ9,CM9,CP9,CS9), 0) | CW9: =CU9*CV9
A10: Callo | B10: Kg | E10: 0 | H10: =IFERROR(F10*G10, 0) | K10: =IFERROR(I10*J10, 0) | N10: =IFERROR(L10*M10, 0) | Q10: =IFERROR(O10*P10, 0) | R10: 7.65 | S10: 18000 | T10: 137700 | W10: =IFERROR(U10*V10, 0) | Z10: =IFERROR(X10*Y10, 0) | AC10: =IFERROR(AA10*AB10, 0) | AF10: =IFERROR(AD10*AE10, 0) | AI10: =IFERROR(AG10*AH10, 0) | AL10: =IFERROR(AJ10*AK10, 0) | AO10: =IFERROR(AM10*AN10, 0) | AR10: =IFERROR(AP10*AQ10, 0) | AU10: =IFERROR(AS10*AT10, 0) | AX10: =IFERROR(AV10*AW10, 0) | BA10: =IFERROR(AY10*AZ10, 0) | BD10: =IFERROR(BB10*BC10, 0) | BG10: =IFERROR(BE10*BF10, 0) | BJ10: =IFERROR(BH10*BI10, 0) | BM10: =IFERROR(BK10*BL10, 0) | BP10: =IFERROR(BN10*BO10, 0) | BS10: =IFERROR(BQ10*BR10, 0) | BV10: =IFERROR(BT10*BU10, 0) | BY10: =IFERROR(BW10*BX10, 0) | CB10: =IFERROR(BZ10*CA10, 0) | CE10: =IFERROR(CC10*CD10, 0) | CH10: =IFERROR(CF10*CG10, 0) | CK10: =IFERROR(CI10*CJ10, 0) | CN10: =IFERROR(CL10*CM10, 0) | CQ10: =IFERROR(CO10*CP10, 0) | CT10: =IFERROR(CR10*CS10, 0) | CU10: =IFERROR(SUM(F10,I10,L10,O10,R10,U10,X10,AA10,AD10,AG10,AJ10,AM10,AP10,AS10,AV10,AY10,BB10,BE10,BH10,BK10,BN10,BQ10,BT10,BW10,BZ10,CC10,CF10,CI10,CL10,CO10,CR10), 0) | CV10: =IFERROR(AVERAGE(G10,J10,M10,P10,S10,V10,Y10,AB10,AE10,AH10,AK10,AN10,AQ10,AT10,AW10,AZ10,BC10,BF10,BI10,BL10,BO10,BR10,BU10,BX10,CA10,CD10,CG10,CJ10,CM10,CP10,CS10), 0) | CW10: =CU10*CV10
A11: Callo distribuidora myc sas | B11: Kg | E11: 0 | H11: =IFERROR(F11*G11, 0) | K11: =IFERROR(I11*J11, 0) | N11: =IFERROR(L11*M11, 0) | Q11: =IFERROR(O11*P11, 0) | T11: =IFERROR(R11*S11, 0) | W11: =IFERROR(U11*V11, 0) | Z11: =IFERROR(X11*Y11, 0) | AC11: =IFERROR(AA11*AB11, 0) | AF11: =IFERROR(AD11*AE11, 0) | AI11: =IFERROR(AG11*AH11, 0) | AL11: =IFERROR(AJ11*AK11, 0) | AO11: =IFERROR(AM11*AN11, 0) | AR11: =IFERROR(AP11*AQ11, 0) | AU11: =IFERROR(AS11*AT11, 0) | AX11: =IFERROR(AV11*AW11, 0) | BA11: =IFERROR(AY11*AZ11, 0) | BD11: =IFERROR(BB11*BC11, 0) | BG11: =IFERROR(BE11*BF11, 0) | BJ11: =IFERROR(BH11*BI11, 0) | BM11: =IFERROR(BK11*BL11, 0) | BP11: =IFERROR(BN11*BO11, 0) | BS11: =IFERROR(BQ11*BR11, 0) | BV11: =IFERROR(BT11*BU11, 0) | BY11: =IFERROR(BW11*BX11, 0) | CB11: =IFERROR(BZ11*CA11, 0) | CE11: =IFERROR(CC11*CD11, 0) | CH11: =IFERROR(CF11*CG11, 0) | CK11: =IFERROR(CI11*CJ11, 0) | CN11: =IFERROR(CL11*CM11, 0) | CQ11: =IFERROR(CO11*CP11, 0) | CT11: =IFERROR(CR11*CS11, 0) | CU11: =IFERROR(SUM(F11,I11,L11,O11,R11,U11,X11,AA11,AD11,AG11,AJ11,AM11,AP11,AS11,AV11,AY11,BB11,BE11,BH11,BK11,BN11,BQ11,BT11,BW11,BZ11,CC11,CF11,CI11,CL11,CO11,CR11), 0) | CV11: =IFERROR(AVERAGE(G11,J11,M11,P11,S11,V11,Y11,AB11,AE11,AH11,AK11,AN11,AQ11,AT11,AW11,AZ11,BC11,BF11,BI11,BL11,BO11,BR11,BU11,BX11,CA11,CD11,CG11,CJ11,CM11,CP11,CS11), 0) | CW11: =CU11*CV11
A12: Camaron precocido | B12: Kg | E12: 0 | H12: =IFERROR(F12*G12, 0) | I12: 30.7 | J12: 22900 | K12: 703030 | N12: =IFERROR(L12*M12, 0) | Q12: =IFERROR(O12*P12, 0) | T12: =IFERROR(R12*S12, 0) | W12: =IFERROR(U12*V12, 0) | Z12: =IFERROR(X12*Y12, 0) | AC12: =IFERROR(AA12*AB12, 0) | AF12: =IFERROR(AD12*AE12, 0) | AG12: 20.2 | AH12: 22900 | AI12: 462580 | AL12: =IFERROR(AJ12*AK12, 0) | AO12: =IFERROR(AM12*AN12, 0) | AR12: =IFERROR(AP12*AQ12, 0) | AU12: =IFERROR(AS12*AT12, 0) | AX12: =IFERROR(AV12*AW12, 0) | BA12: =IFERROR(AY12*AZ12, 0) | BB12: 20.2 | BC12: 22900 | BD12: 462580 | BG12: =IFERROR(BE12*BF12, 0) | BJ12: =IFERROR(BH12*BI12, 0) | BM12: =IFERROR(BK12*BL12, 0) | BP12: =IFERROR(BN12*BO12, 0) | BS12: =IFERROR(BQ12*BR12, 0) | BV12: =IFERROR(BT12*BU12, 0) | BY12: =IFERROR(BW12*BX12, 0) | CB12: =IFERROR(BZ12*CA12, 0) | CE12: =IFERROR(CC12*CD12, 0) | CH12: =IFERROR(CF12*CG12, 0) | CK12: =IFERROR(CI12*CJ12, 0) | CN12: =IFERROR(CL12*CM12, 0) | CQ12: =IFERROR(CO12*CP12, 0) | CT12: =IFERROR(CR12*CS12, 0) | CU12: =IFERROR(SUM(F12,I12,L12,O12,R12,U12,X12,AA12,AD12,AG12,AJ12,AM12,AP12,AS12,AV12,AY12,BB12,BE12,BH12,BK12,BN12,BQ12,BT12,BW12,BZ12,CC12,CF12,CI12,CL12,CO12,CR12), 0) | CV12: =IFERROR(AVERAGE(G12,J12,M12,P12,S12,V12,Y12,AB12,AE12,AH12,AK12,AN12,AQ12,AT12,AW12,AZ12,BC12,BF12,BI12,BL12,BO12,BR12,BU12,BX12,CA12,CD12,CG12,CJ12,CM12,CP12,CS12), 0) | CW12: =CU12*CV12
A13: Carne molida | B13: Kg | E13: 0 | H13: =IFERROR(F13*G13, 0) | K13: =IFERROR(I13*J13, 0) | N13: =IFERROR(L13*M13, 0) | Q13: =IFERROR(O13*P13, 0) | T13: =IFERROR(R13*S13, 0) | W13: =IFERROR(U13*V13, 0) | Z13: =IFERROR(X13*Y13, 0) | AC13: =IFERROR(AA13*AB13, 0) | AF13: =IFERROR(AD13*AE13, 0) | AI13: =IFERROR(AG13*AH13, 0) | AL13: =IFERROR(AJ13*AK13, 0) | AO13: =IFERROR(AM13*AN13, 0) | AR13: =IFERROR(AP13*AQ13, 0) | AU13: =IFERROR(AS13*AT13, 0) | AX13: =IFERROR(AV13*AW13, 0) | BA13: =IFERROR(AY13*AZ13, 0) | BD13: =IFERROR(BB13*BC13, 0) | BG13: =IFERROR(BE13*BF13, 0) | BJ13: =IFERROR(BH13*BI13, 0) | BM13: =IFERROR(BK13*BL13, 0) | BP13: =IFERROR(BN13*BO13, 0) | BS13: =IFERROR(BQ13*BR13, 0) | BV13: =IFERROR(BT13*BU13, 0) | BY13: =IFERROR(BW13*BX13, 0) | CB13: =IFERROR(BZ13*CA13, 0) | CE13: =IFERROR(CC13*CD13, 0) | CH13: =IFERROR(CF13*CG13, 0) | CK13: =IFERROR(CI13*CJ13, 0) | CN13: =IFERROR(CL13*CM13, 0) | CQ13: =IFERROR(CO13*CP13, 0) | CT13: =IFERROR(CR13*CS13, 0) | CU13: =IFERROR(SUM(F13,I13,L13,O13,R13,U13,X13,AA13,AD13,AG13,AJ13,AM13,AP13,AS13,AV13,AY13,BB13,BE13,BH13,BK13,BN13,BQ13,BT13,BW13,BZ13,CC13,CF13,CI13,CL13,CO13,CR13), 0) | CV13: =IFERROR(AVERAGE(G13,J13,M13,P13,S13,V13,Y13,AB13,AE13,AH13,AK13,AN13,AQ13,AT13,AW13,AZ13,BC13,BF13,BI13,BL13,BO13,BR13,BU13,BX13,CA13,CD13,CG13,CJ13,CM13,CP13,CS13), 0) | CW13: =CU13*CV13
A14: Pecho | B14: Kg | E14: 0 | H14: =IFERROR(F14*G14, 0) | K14: =IFERROR(I14*J14, 0) | N14: =IFERROR(L14*M14, 0) | Q14: =IFERROR(O14*P14, 0) | T14: =IFERROR(R14*S14, 0) | W14: =IFERROR(U14*V14, 0) | Z14: =IFERROR(X14*Y14, 0) | AC14: =IFERROR(AA14*AB14, 0) | AF14: =IFERROR(AD14*AE14, 0) | AI14: =IFERROR(AG14*AH14, 0) | AL14: =IFERROR(AJ14*AK14, 0) | AO14: =IFERROR(AM14*AN14, 0) | AR14: =IFERROR(AP14*AQ14, 0) | AU14: =IFERROR(AS14*AT14, 0) | AX14: =IFERROR(AV14*AW14, 0) | BA14: =IFERROR(AY14*AZ14, 0) | BD14: =IFERROR(BB14*BC14, 0) | BG14: =IFERROR(BE14*BF14, 0) | BJ14: =IFERROR(BH14*BI14, 0) | BM14: =IFERROR(BK14*BL14, 0) | BP14: =IFERROR(BN14*BO14, 0) | BS14: =IFERROR(BQ14*BR14, 0) | BV14: =IFERROR(BT14*BU14, 0) | BY14: =IFERROR(BW14*BX14, 0) | CB14: =IFERROR(BZ14*CA14, 0) | CE14: =IFERROR(CC14*CD14, 0) | CH14: =IFERROR(CF14*CG14, 0) | CK14: =IFERROR(CI14*CJ14, 0) | CN14: =IFERROR(CL14*CM14, 0) | CQ14: =IFERROR(CO14*CP14, 0) | CT14: =IFERROR(CR14*CS14, 0) | CU14: =IFERROR(SUM(F14,I14,L14,O14,R14,U14,X14,AA14,AD14,AG14,AJ14,AM14,AP14,AS14,AV14,AY14,BB14,BE14,BH14,BK14,BN14,BQ14,BT14,BW14,BZ14,CC14,CF14,CI14,CL14,CO14,CR14), 0) | CV14: =IFERROR(AVERAGE(G14,J14,M14,P14,S14,V14,Y14,AB14,AE14,AH14,AK14,AN14,AQ14,AT14,AW14,AZ14,BC14,BF14,BI14,BL14,BO14,BR14,BU14,BX14,CA14,CD14,CG14,CJ14,CM14,CP14,CS14), 0) | CW14: =CU14*CV14
A15: Muchacho res | B15: Kg | E15: 0 | H15: =IFERROR(F15*G15, 0) | K15: =IFERROR(I15*J15, 0) | N15: =IFERROR(L15*M15, 0) | Q15: =IFERROR(O15*P15, 0) | T15: =IFERROR(R15*S15, 0) | W15: =IFERROR(U15*V15, 0) | Z15: =IFERROR(X15*Y15, 0) | AC15: =IFERROR(AA15*AB15, 0) | AF15: =IFERROR(AD15*AE15, 0) | AI15: =IFERROR(AG15*AH15, 0) | AL15: =IFERROR(AJ15*AK15, 0) | AO15: =IFERROR(AM15*AN15, 0) | AR15: =IFERROR(AP15*AQ15, 0) | AU15: =IFERROR(AS15*AT15, 0) | AX15: =IFERROR(AV15*AW15, 0) | BA15: =IFERROR(AY15*AZ15, 0) | BD15: =IFERROR(BB15*BC15, 0) | BG15: =IFERROR(BE15*BF15, 0) | BJ15: =IFERROR(BH15*BI15, 0) | BM15: =IFERROR(BK15*BL15, 0) | BP15: =IFERROR(BN15*BO15, 0) | BS15: =IFERROR(BQ15*BR15, 0) | BV15: =IFERROR(BT15*BU15, 0) | BY15: =IFERROR(BW15*BX15, 0) | CB15: =IFERROR(BZ15*CA15, 0) | CE15: =IFERROR(CC15*CD15, 0) | CH15: =IFERROR(CF15*CG15, 0) | CK15: =IFERROR(CI15*CJ15, 0) | CN15: =IFERROR(CL15*CM15, 0) | CQ15: =IFERROR(CO15*CP15, 0) | CT15: =IFERROR(CR15*CS15, 0) | CU15: =IFERROR(SUM(F15,I15,L15,O15,R15,U15,X15,AA15,AD15,AG15,AJ15,AM15,AP15,AS15,AV15,AY15,BB15,BE15,BH15,BK15,BN15,BQ15,BT15,BW15,BZ15,CC15,CF15,CI15,CL15,CO15,CR15), 0) | CV15: =IFERROR(AVERAGE(G15,J15,M15,P15,S15,V15,Y15,AB15,AE15,AH15,AK15,AN15,AQ15,AT15,AW15,AZ15,BC15,BF15,BI15,BL15,BO15,BR15,BU15,BX15,CA15,CD15,CG15,CJ15,CM15,CP15,CS15), 0) | CW15: =CU15*CV15
A16: Morcilla | B16: Kg | E16: 0 | H16: =IFERROR(F16*G16, 0) | K16: =IFERROR(I16*J16, 0) | N16: =IFERROR(L16*M16, 0) | Q16: =IFERROR(O16*P16, 0) | T16: =IFERROR(R16*S16, 0) | W16: =IFERROR(U16*V16, 0) | Z16: =IFERROR(X16*Y16, 0) | AC16: =IFERROR(AA16*AB16, 0) | AF16: =IFERROR(AD16*AE16, 0) | AI16: =IFERROR(AG16*AH16, 0) | AJ16: 5 | AK16: 20000 | AL16: 100000 | AO16: =IFERROR(AM16*AN16, 0) | AR16: =IFERROR(AP16*AQ16, 0) | AU16: =IFERROR(AS16*AT16, 0) | AX16: =IFERROR(AV16*AW16, 0) | BA16: =IFERROR(AY16*AZ16, 0) | BD16: =IFERROR(BB16*BC16, 0) | BG16: =IFERROR(BE16*BF16, 0) | BJ16: =IFERROR(BH16*BI16, 0) | BM16: =BL16*BK16 | BP16: =IFERROR(BN16*BO16, 0) | BS16: =IFERROR(BQ16*BR16, 0) | BV16: =IFERROR(BT16*BU16, 0) | BY16: =IFERROR(BW16*BX16, 0) | CB16: =IFERROR(BZ16*CA16, 0) | CE16: =IFERROR(CC16*CD16, 0) | CH16: =IFERROR(CF16*CG16, 0) | CK16: =IFERROR(CI16*CJ16, 0) | CN16: =IFERROR(CL16*CM16, 0) | CQ16: =IFERROR(CO16*CP16, 0) | CT16: =IFERROR(CR16*CS16, 0) | CU16: =IFERROR(SUM(F16,I16,L16,O16,R16,U16,X16,AA16,AD16,AG16,AJ16,AM16,AP16,AS16,AV16,AY16,BB16,BE16,BH16,BK16,BN16,BQ16,BT16,BW16,BZ16,CC16,CF16,CI16,CL16,CO16,CR16), 0) | CV16: =IFERROR(AVERAGE(G16,J16,M16,P16,S16,V16,Y16,AB16,AE16,AH16,AK16,AN16,AQ16,AT16,AW16,AZ16,BC16,BF16,BI16,BL16,BO16,BR16,BU16,BX16,CA16,CD16,CG16,CJ16,CM16,CP16,CS16), 0) | CW16: =CU16*CV16
A17: Lomo de caracho | B17: Kg | E17: 0 | H17: =IFERROR(F17*G17, 0) | K17: =IFERROR(I17*J17, 0) | N17: =IFERROR(L17*M17, 0) | Q17: =IFERROR(O17*P17, 0) | T17: =IFERROR(R17*S17, 0) | W17: =IFERROR(U17*V17, 0) | Z17: =IFERROR(X17*Y17, 0) | AC17: =IFERROR(AA17*AB17, 0) | AF17: =IFERROR(AD17*AE17, 0) | AG17: 14.5 | AH17: 44000 | AI17: 638000 | AL17: =IFERROR(AJ17*AK17, 0) | AO17: =IFERROR(AM17*AN17, 0) | AR17: =IFERROR(AP17*AQ17, 0) | AU17: =IFERROR(AS17*AT17, 0) | AX17: =IFERROR(AV17*AW17, 0) | BA17: =IFERROR(AY17*AZ17, 0) | BD17: =IFERROR(BB17*BC17, 0) | BG17: =IFERROR(BE17*BF17, 0) | BJ17: =IFERROR(BH17*BI17, 0) | BM17: =IFERROR(BK17*BL17, 0) | BP17: =IFERROR(BN17*BO17, 0) | BS17: =IFERROR(BQ17*BR17, 0) | BT17: 6.71 | BU17: 50900 | BV17: 341539 | BY17: =IFERROR(BW17*BX17, 0) | CB17: =IFERROR(BZ17*CA17, 0) | CE17: =IFERROR(CC17*CD17, 0) | CH17: =IFERROR(CF17*CG17, 0) | CK17: =IFERROR(CI17*CJ17, 0) | CN17: =IFERROR(CL17*CM17, 0) | CQ17: =IFERROR(CO17*CP17, 0) | CT17: =IFERROR(CR17*CS17, 0) | CU17: =IFERROR(SUM(F17,I17,L17,O17,R17,U17,X17,AA17,AD17,AG17,AJ17,AM17,AP17,AS17,AV17,AY17,BB17,BE17,BH17,BK17,BN17,BQ17,BT17,BW17,BZ17,CC17,CF17,CI17,CL17,CO17,CR17), 0) | CV17: =IFERROR(AVERAGE(G17,J17,M17,P17,S17,V17,Y17,AB17,AE17,AH17,AK17,AN17,AQ17,AT17,AW17,AZ17,BC17,BF17,BI17,BL17,BO17,BR17,BU17,BX17,CA17,CD17,CG17,CJ17,CM17,CP17,CS17), 0) | CW17: =CU17*CV17
A18: Chorizo Premium | B18: Kg | E18: 0 | H18: =IFERROR(F18*G18, 0) | K18: =IFERROR(I18*J18, 0) | N18: =IFERROR(L18*M18, 0) | O18: 2 | P18: 46000 | Q18: 92000 | T18: =IFERROR(R18*S18, 0) | W18: =IFERROR(U18*V18, 0) | Z18: =IFERROR(X18*Y18, 0) | AC18: =IFERROR(AA18*AB18, 0) | AF18: =IFERROR(AD18*AE18, 0) | AG18: 2 | AH18: 46000 | AI18: 92000 | AL18: =IFERROR(AJ18*AK18, 0) | AO18: =IFERROR(AM18*AN18, 0) | AR18: =IFERROR(AP18*AQ18, 0) | AU18: =IFERROR(AS18*AT18, 0) | AV18: 2 | AW18: 46000 | AX18: 92000 | BA18: =IFERROR(AY18*AZ18, 0) | BD18: =IFERROR(BB18*BC18, 0) | BG18: =IFERROR(BE18*BF18, 0) | BJ18: =IFERROR(BH18*BI18, 0) | BK18: 5 | BL18: 46000 | BM18: 230000 | BP18: =IFERROR(BN18*BO18, 0) | BS18: =IFERROR(BQ18*BR18, 0) | BV18: =IFERROR(BT18*BU18, 0) | BY18: =IFERROR(BW18*BX18, 0) | CB18: =IFERROR(BZ18*CA18, 0) | CE18: =IFERROR(CC18*CD18, 0) | CH18: =IFERROR(CF18*CG18, 0) | CK18: =IFERROR(CI18*CJ18, 0) | CN18: =IFERROR(CL18*CM18, 0) | CQ18: =IFERROR(CO18*CP18, 0) | CT18: =IFERROR(CR18*CS18, 0) | CU18: =IFERROR(SUM(F18,I18,L18,O18,R18,U18,X18,AA18,AD18,AG18,AJ18,AM18,AP18,AS18,AV18,AY18,BB18,BE18,BH18,BK18,BN18,BQ18,BT18,BW18,BZ18,CC18,CF18,CI18,CL18,CO18,CR18), 0) | CV18: =IFERROR(AVERAGE(G18,J18,M18,P18,S18,V18,Y18,AB18,AE18,AH18,AK18,AN18,AQ18,AT18,AW18,AZ18,BC18,BF18,BI18,BL18,BO18,BR18,BU18,BX18,CA18,CD18,CG18,CJ18,CM18,CP18,CS18), 0) | CW18: =CU18*CV18
A19: Churrasco | B19: Kg | E19: 0 | H19: =IFERROR(F19*G19, 0) | K19: =IFERROR(I19*J19, 0) | N19: =IFERROR(L19*M19, 0) | Q19: =IFERROR(O19*P19, 0) | T19: =IFERROR(R19*S19, 0) | W19: =IFERROR(U19*V19, 0) | Z19: =IFERROR(X19*Y19, 0) | AC19: =IFERROR(AA19*AB19, 0) | AF19: =IFERROR(AD19*AE19, 0) | AI19: =IFERROR(AG19*AH19, 0) | AL19: =IFERROR(AJ19*AK19, 0) | AO19: =IFERROR(AM19*AN19, 0) | AR19: =IFERROR(AP19*AQ19, 0) | AU19: =IFERROR(AS19*AT19, 0) | AX19: =IFERROR(AV19*AW19, 0) | BA19: =IFERROR(AY19*AZ19, 0) | BD19: =IFERROR(BB19*BC19, 0) | BG19: =IFERROR(BE19*BF19, 0) | BJ19: =IFERROR(BH19*BI19, 0) | BM19: =IFERROR(BK19*BL19, 0) | BP19: =IFERROR(BN19*BO19, 0) | BS19: =IFERROR(BQ19*BR19, 0) | BV19: =IFERROR(BT19*BU19, 0) | BY19: =IFERROR(BW19*BX19, 0) | CB19: =IFERROR(BZ19*CA19, 0) | CE19: =IFERROR(CC19*CD19, 0) | CH19: =IFERROR(CF19*CG19, 0) | CK19: =IFERROR(CI19*CJ19, 0) | CN19: =IFERROR(CL19*CM19, 0) | CQ19: =IFERROR(CO19*CP19, 0) | CT19: =IFERROR(CR19*CS19, 0) | CU19: =IFERROR(SUM(F19,I19,L19,O19,R19,U19,X19,AA19,AD19,AG19,AJ19,AM19,AP19,AS19,AV19,AY19,BB19,BE19,BH19,BK19,BN19,BQ19,BT19,BW19,BZ19,CC19,CF19,CI19,CL19,CO19,CR19), 0) | CV19: =IFERROR(AVERAGE(G19,J19,M19,P19,S19,V19,Y19,AB19,AE19,AH19,AK19,AN19,AQ19,AT19,AW19,AZ19,BC19,BF19,BI19,BL19,BO19,BR19,BU19,BX19,CA19,CD19,CG19,CJ19,CM19,CP19,CS19), 0) | CW19: =CU19*CV19
A20: Costilla ahumada | B20: Kg | E20: 0 | H20: =IFERROR(F20*G20, 0) | K20: =IFERROR(I20*J20, 0) | N20: =IFERROR(L20*M20, 0) | Q20: =IFERROR(O20*P20, 0) | R20: 8 | S20: 22900 | T20: 183200 | W20: =IFERROR(U20*V20, 0) | Z20: =IFERROR(X20*Y20, 0) | AC20: =IFERROR(AA20*AB20, 0) | AF20: =IFERROR(AD20*AE20, 0) | AI20: =IFERROR(AG20*AH20, 0) | AL20: =IFERROR(AJ20*AK20, 0) | AO20: =IFERROR(AM20*AN20, 0) | AR20: =IFERROR(AP20*AQ20, 0) | AU20: =IFERROR(AS20*AT20, 0) | AX20: =IFERROR(AV20*AW20, 0) | BA20: =IFERROR(AY20*AZ20, 0) | BD20: =IFERROR(BB20*BC20, 0) | BG20: =IFERROR(BE20*BF20, 0) | BJ20: =IFERROR(BH20*BI20, 0) | BM20: =IFERROR(BK20*BL20, 0) | BP20: =IFERROR(BN20*BO20, 0) | BS20: =IFERROR(BQ20*BR20, 0) | BV20: =IFERROR(BT20*BU20, 0) | BY20: =IFERROR(BW20*BX20, 0) | CB20: =IFERROR(BZ20*CA20, 0) | CE20: =IFERROR(CC20*CD20, 0) | CH20: =IFERROR(CF20*CG20, 0) | CK20: =IFERROR(CI20*CJ20, 0) | CN20: =IFERROR(CL20*CM20, 0) | CQ20: =IFERROR(CO20*CP20, 0) | CT20: =IFERROR(CR20*CS20, 0) | CU20: =IFERROR(SUM(F20,I20,L20,O20,R20,U20,X20,AA20,AD20,AG20,AJ20,AM20,AP20,AS20,AV20,AY20,BB20,BE20,BH20,BK20,BN20,BQ20,BT20,BW20,BZ20,CC20,CF20,CI20,CL20,CO20,CR20), 0) | CV20: =IFERROR(AVERAGE(G20,J20,M20,P20,S20,V20,Y20,AB20,AE20,AH20,AK20,AN20,AQ20,AT20,AW20,AZ20,BC20,BF20,BI20,BL20,BO20,BR20,BU20,BX20,CA20,CD20,CG20,CJ20,CM20,CP20,CS20), 0) | CW20: =CU20*CV20
A21: Costilla corte americano | B21: Kg | E21: 0 | H21: =IFERROR(F21*G21, 0) | K21: =IFERROR(I21*J21, 0) | N21: =IFERROR(L21*M21, 0) | Q21: =IFERROR(O21*P21, 0) | T21: =IFERROR(R21*S21, 0) | W21: =IFERROR(U21*V21, 0) | Z21: =IFERROR(X21*Y21, 0) | AC21: =IFERROR(AA21*AB21, 0) | AF21: =IFERROR(AD21*AE21, 0) | AI21: =IFERROR(AG21*AH21, 0) | AL21: =IFERROR(AJ21*AK21, 0) | AO21: =IFERROR(AM21*AN21, 0) | AR21: =IFERROR(AP21*AQ21, 0) | AU21: =IFERROR(AS21*AT21, 0) | AX21: =IFERROR(AV21*AW21, 0) | BA21: =IFERROR(AY21*AZ21, 0) | BD21: =IFERROR(BB21*BC21, 0) | BG21: =IFERROR(BE21*BF21, 0) | BJ21: =IFERROR(BH21*BI21, 0) | BM21: =IFERROR(BK21*BL21, 0) | BP21: =IFERROR(BN21*BO21, 0) | BS21: =IFERROR(BQ21*BR21, 0) | BV21: =IFERROR(BT21*BU21, 0) | BY21: =IFERROR(BW21*BX21, 0) | CB21: =IFERROR(BZ21*CA21, 0) | CE21: =IFERROR(CC21*CD21, 0) | CH21: =IFERROR(CF21*CG21, 0) | CK21: =IFERROR(CI21*CJ21, 0) | CN21: =IFERROR(CL21*CM21, 0) | CQ21: =IFERROR(CO21*CP21, 0) | CT21: =IFERROR(CR21*CS21, 0) | CU21: =IFERROR(SUM(F21,I21,L21,O21,R21,U21,X21,AA21,AD21,AG21,AJ21,AM21,AP21,AS21,AV21,AY21,BB21,BE21,BH21,BK21,BN21,BQ21,BT21,BW21,BZ21,CC21,CF21,CI21,CL21,CO21,CR21), 0) | CV21: =IFERROR(AVERAGE(G21,J21,M21,P21,S21,V21,Y21,AB21,AE21,AH21,AK21,AN21,AQ21,AT21,AW21,AZ21,BC21,BF21,BI21,BL21,BO21,BR21,BU21,BX21,CA21,CD21,CG21,CJ21,CM21,CP21,CS21), 0) | CW21: =CU21*CV21
A22: Costilla de cerdo especial | B22: Kg | E22: 0 | H22: =IFERROR(F22*G22, 0) | K22: =IFERROR(I22*J22, 0) | N22: =IFERROR(L22*M22, 0) | Q22: =IFERROR(O22*P22, 0) | T22: =IFERROR(R22*S22, 0) | W22: =IFERROR(U22*V22, 0) | X22: 28.1 | Y22: 16700 | Z22: 469270 | AC22: =IFERROR(AA22*AB22, 0) | AF22: =IFERROR(AD22*AE22, 0) | AI22: =IFERROR(AG22*AH22, 0) | AL22: =IFERROR(AJ22*AK22, 0) | AO22: =IFERROR(AM22*AN22, 0) | AR22: =IFERROR(AP22*AQ22, 0) | AU22: =IFERROR(AS22*AT22, 0) | AV22: 28.1 | AW22: 15900 | AX22: 446790 | BA22: =IFERROR(AY22*AZ22, 0) | BD22: =IFERROR(BB22*BC22, 0) | BE22: 20 | BF22: 18200 | BG22: 364000 | BJ22: =IFERROR(BH22*BI22, 0) | BM22: =IFERROR(BK22*BL22, 0) | BP22: =IFERROR(BN22*BO22, 0) | BS22: =IFERROR(BQ22*BR22, 0) | BT22: 26.1 | BU22: 15400 | BV22: 401940 | BY22: =IFERROR(BW22*BX22, 0) | CB22: =IFERROR(BZ22*CA22, 0) | CE22: =IFERROR(CC22*CD22, 0) | CH22: =IFERROR(CF22*CG22, 0) | CK22: =IFERROR(CI22*CJ22, 0) | CN22: =IFERROR(CL22*CM22, 0) | CQ22: =IFERROR(CO22*CP22, 0) | CT22: =IFERROR(CR22*CS22, 0) | CU22: =IFERROR(SUM(F22,I22,L22,O22,R22,U22,X22,AA22,AD22,AG22,AJ22,AM22,AP22,AS22,AV22,AY22,BB22,BE22,BH22,BK22,BN22,BQ22,BT22,BW22,BZ22,CC22,CF22,CI22,CL22,CO22,CR22), 0) | CV22: =IFERROR(AVERAGE(G22,J22,M22,P22,S22,V22,Y22,AB22,AE22,AH22,AK22,AN22,AQ22,AT22,AW22,AZ22,BC22,BF22,BI22,BL22,BO22,BR22,BU22,BX22,CA22,CD22,CG22,CJ22,CM22,CP22,CS22), 0) | CW22: =CU22*CV22
A23: Costilla de res | B23: Kg | E23: 0 | H23: =IFERROR(F23*G23, 0) | K23: =IFERROR(I23*J23, 0) | N23: =IFERROR(L23*M23, 0) | Q23: =IFERROR(O23*P23, 0) | T23: =IFERROR(R23*S23, 0) | W23: =IFERROR(U23*V23, 0) | Z23: =IFERROR(X23*Y23, 0) | AC23: =IFERROR(AA23*AB23, 0) | AF23: =IFERROR(AD23*AE23, 0) | AI23: =IFERROR(AG23*AH23, 0) | AL23: =IFERROR(AJ23*AK23, 0) | AO23: =IFERROR(AM23*AN23, 0) | AR23: =IFERROR(AP23*AQ23, 0) | AU23: =IFERROR(AS23*AT23, 0) | AX23: =IFERROR(AV23*AW23, 0) | BA23: =IFERROR(AY23*AZ23, 0) | BD23: =IFERROR(BB23*BC23, 0) | BG23: =IFERROR(BE23*BF23, 0) | BJ23: =IFERROR(BH23*BI23, 0) | BM23: =IFERROR(BK23*BL23, 0) | BN23: 20.55 | BO23: 22000 | BP23: 452100 | BS23: =IFERROR(BQ23*BR23, 0) | BV23: =IFERROR(BT23*BU23, 0) | BY23: =IFERROR(BW23*BX23, 0) | CB23: =IFERROR(BZ23*CA23, 0) | CE23: =IFERROR(CC23*CD23, 0) | CH23: =IFERROR(CF23*CG23, 0) | CK23: =IFERROR(CI23*CJ23, 0) | CN23: =IFERROR(CL23*CM23, 0) | CQ23: =IFERROR(CO23*CP23, 0) | CT23: =IFERROR(CR23*CS23, 0) | CU23: =IFERROR(SUM(F23,I23,L23,O23,R23,U23,X23,AA23,AD23,AG23,AJ23,AM23,AP23,AS23,AV23,AY23,BB23,BE23,BH23,BK23,BN23,BQ23,BT23,BW23,BZ23,CC23,CF23,CI23,CL23,CO23,CR23), 0) | CV23: =IFERROR(AVERAGE(G23,J23,M23,P23,S23,V23,Y23,AB23,AE23,AH23,AK23,AN23,AQ23,AT23,AW23,AZ23,BC23,BF23,BI23,BL23,BO23,BR23,BU23,BX23,CA23,CD23,CG23,CJ23,CM23,CP23,CS23), 0) | CW23: =CU23*CV23
A24: Costilla san luis | B24: Kg | E24: 0 | H24: =IFERROR(F24*G24, 0) | K24: =IFERROR(I24*J24, 0) | N24: =IFERROR(L24*M24, 0) | Q24: =IFERROR(O24*P24, 0) | T24: =IFERROR(R24*S24, 0) | W24: =IFERROR(U24*V24, 0) | Z24: =IFERROR(X24*Y24, 0) | AC24: =IFERROR(AA24*AB24, 0) | AF24: =IFERROR(AD24*AE24, 0) | AI24: =IFERROR(AG24*AH24, 0) | AL24: =IFERROR(AJ24*AK24, 0) | AO24: =IFERROR(AM24*AN24, 0) | AR24: =IFERROR(AP24*AQ24, 0) | AU24: =IFERROR(AS24*AT24, 0) | AX24: =IFERROR(AV24*AW24, 0) | BA24: =IFERROR(AY24*AZ24, 0) | BD24: =IFERROR(BB24*BC24, 0) | BG24: =IFERROR(BE24*BF24, 0) | BJ24: =IFERROR(BH24*BI24, 0) | BM24: =IFERROR(BK24*BL24, 0) | BP24: =IFERROR(BN24*BO24, 0) | BS24: =IFERROR(BQ24*BR24, 0) | BV24: =IFERROR(BT24*BU24, 0) | BY24: =IFERROR(BW24*BX24, 0) | CB24: =IFERROR(BZ24*CA24, 0) | CE24: =IFERROR(CC24*CD24, 0) | CH24: =IFERROR(CF24*CG24, 0) | CK24: =IFERROR(CI24*CJ24, 0) | CN24: =IFERROR(CL24*CM24, 0) | CQ24: =IFERROR(CO24*CP24, 0) | CT24: =IFERROR(CR24*CS24, 0) | CU24: =IFERROR(SUM(F24,I24,L24,O24,R24,U24,X24,AA24,AD24,AG24,AJ24,AM24,AP24,AS24,AV24,AY24,BB24,BE24,BH24,BK24,BN24,BQ24,BT24,BW24,BZ24,CC24,CF24,CI24,CL24,CO24,CR24), 0) | CV24: =IFERROR(AVERAGE(G24,J24,M24,P24,S24,V24,Y24,AB24,AE24,AH24,AK24,AN24,AQ24,AT24,AW24,AZ24,BC24,BF24,BI24,BL24,BO24,BR24,BU24,BX24,CA24,CD24,CG24,CJ24,CM24,CP24,CS24), 0) | CW24: =CU24*CV24
A25: Costilla san luis jr | B25: Kg | E25: 0 | H25: =IFERROR(F25*G25, 0) | K25: =IFERROR(I25*J25, 0) | N25: =IFERROR(L25*M25, 0) | O25: 20.2 | P25: 22000 | Q25: 444400 | T25: =IFERROR(R25*S25, 0) | W25: =IFERROR(U25*V25, 0) | X25: 48.66 | Y25: 21900 | Z25: 1065654 | AC25: =IFERROR(AA25*AB25, 0) | AF25: =IFERROR(AD25*AE25, 0) | AI25: =IFERROR(AG25*AH25, 0) | AL25: =IFERROR(AJ25*AK25, 0) | AO25: =IFERROR(AM25*AN25, 0) | AR25: =IFERROR(AP25*AQ25, 0) | AU25: =IFERROR(AS25*AT25, 0) | AX25: =IFERROR(AV25*AW25, 0) | BA25: =IFERROR(AY25*AZ25, 0) | BD25: =IFERROR(BB25*BC25, 0) | BG25: =IFERROR(BE25*BF25, 0) | BJ25: =IFERROR(BH25*BI25, 0) | BM25: =IFERROR(BK25*BL25, 0) | BP25: =IFERROR(BN25*BO25, 0) | BS25: =IFERROR(BQ25*BR25, 0) | BV25: =IFERROR(BT25*BU25, 0) | BY25: =IFERROR(BW25*BX25, 0) | CB25: =IFERROR(BZ25*CA25, 0) | CE25: =IFERROR(CC25*CD25, 0) | CH25: =IFERROR(CF25*CG25, 0) | CK25: =IFERROR(CI25*CJ25, 0) | CN25: =IFERROR(CL25*CM25, 0) | CQ25: =IFERROR(CO25*CP25, 0) | CT25: =IFERROR(CR25*CS25, 0) | CU25: =IFERROR(SUM(F25,I25,L25,O25,R25,U25,X25,AA25,AD25,AG25,AJ25,AM25,AP25,AS25,AV25,AY25,BB25,BE25,BH25,BK25,BN25,BQ25,BT25,BW25,BZ25,CC25,CF25,CI25,CL25,CO25,CR25), 0) | CV25: =IFERROR(AVERAGE(G25,J25,M25,P25,S25,V25,Y25,AB25,AE25,AH25,AK25,AN25,AQ25,AT25,AW25,AZ25,BC25,BF25,BI25,BL25,BO25,BR25,BU25,BX25,CA25,CD25,CG25,CJ25,CM25,CP25,CS25), 0) | CW25: =CU25*CV25
A26: Empella | B26: Kg | E26: 0 | H26: =IFERROR(F26*G26, 0) | K26: =IFERROR(I26*J26, 0) | N26: =IFERROR(L26*M26, 0) | Q26: =IFERROR(O26*P26, 0) | T26: =IFERROR(R26*S26, 0) | W26: =IFERROR(U26*V26, 0) | Z26: =IFERROR(X26*Y26, 0) | AC26: =IFERROR(AA26*AB26, 0) | AF26: =IFERROR(AD26*AE26, 0) | AI26: =IFERROR(AG26*AH26, 0) | AL26: =IFERROR(AJ26*AK26, 0) | AO26: =IFERROR(AM26*AN26, 0) | AR26: =IFERROR(AP26*AQ26, 0) | AU26: =IFERROR(AS26*AT26, 0) | AX26: =IFERROR(AV26*AW26, 0) | BA26: =IFERROR(AY26*AZ26, 0) | BD26: =IFERROR(BB26*BC26, 0) | BG26: =IFERROR(BE26*BF26, 0) | BJ26: =IFERROR(BH26*BI26, 0) | BM26: =IFERROR(BK26*BL26, 0) | BP26: =IFERROR(BN26*BO26, 0) | BS26: =IFERROR(BQ26*BR26, 0) | BV26: =IFERROR(BT26*BU26, 0) | BY26: =IFERROR(BW26*BX26, 0) | CB26: =IFERROR(BZ26*CA26, 0) | CE26: =IFERROR(CC26*CD26, 0) | CH26: =IFERROR(CF26*CG26, 0) | CK26: =IFERROR(CI26*CJ26, 0) | CN26: =IFERROR(CL26*CM26, 0) | CQ26: =IFERROR(CO26*CP26, 0) | CT26: =IFERROR(CR26*CS26, 0) | CU26: =IFERROR(SUM(F26,I26,L26,O26,R26,U26,X26,AA26,AD26,AG26,AJ26,AM26,AP26,AS26,AV26,AY26,BB26,BE26,BH26,BK26,BN26,BQ26,BT26,BW26,BZ26,CC26,CF26,CI26,CL26,CO26,CR26), 0) | CV26: =IFERROR(AVERAGE(G26,J26,M26,P26,S26,V26,Y26,AB26,AE26,AH26,AK26,AN26,AQ26,AT26,AW26,AZ26,BC26,BF26,BI26,BL26,BO26,BR26,BU26,BX26,CA26,CD26,CG26,CJ26,CM26,CP26,CS26), 0) | CW26: =CU26*CV26
A27: Espinazo de cerdo | B27: Kg | E27: 0 | H27: =IFERROR(F27*G27, 0) | K27: =IFERROR(I27*J27, 0) | N27: =IFERROR(L27*M27, 0) | Q27: =IFERROR(O27*P27, 0) | T27: =IFERROR(R27*S27, 0) | U27: 3.036 | V27: 7350 | W27: 22315 | Z27: =IFERROR(X27*Y27, 0) | AC27: =IFERROR(AA27*AB27, 0) | AF27: =IFERROR(AD27*AE27, 0) | AI27: =IFERROR(AG27*AH27, 0) | AL27: =IFERROR(AJ27*AK27, 0) | AO27: =IFERROR(AM27*AN27, 0) | AR27: =IFERROR(AP27*AQ27, 0) | AU27: =IFERROR(AS27*AT27, 0) | AX27: =IFERROR(AV27*AW27, 0) | BA27: =IFERROR(AY27*AZ27, 0) | BD27: =IFERROR(BB27*BC27, 0) | BG27: =IFERROR(BE27*BF27, 0) | BJ27: =IFERROR(BH27*BI27, 0) | BM27: =IFERROR(BK27*BL27, 0) | BP27: =IFERROR(BN27*BO27, 0) | BQ27: 3.058 | BR27: 9799 | BS27: 30066 | BV27: =IFERROR(BT27*BU27, 0) | BY27: =IFERROR(BW27*BX27, 0) | CB27: =IFERROR(BZ27*CA27, 0) | CE27: =IFERROR(CC27*CD27, 0) | CH27: =IFERROR(CF27*CG27, 0) | CK27: =IFERROR(CI27*CJ27, 0) | CN27: =IFERROR(CL27*CM27, 0) | CQ27: =IFERROR(CO27*CP27, 0) | CT27: =IFERROR(CR27*CS27, 0) | CU27: =IFERROR(SUM(F27,I27,L27,O27,R27,U27,X27,AA27,AD27,AG27,AJ27,AM27,AP27,AS27,AV27,AY27,BB27,BE27,BH27,BK27,BN27,BQ27,BT27,BW27,BZ27,CC27,CF27,CI27,CL27,CO27,CR27), 0) | CV27: =IFERROR(AVERAGE(G27,J27,M27,P27,S27,V27,Y27,AB27,AE27,AH27,AK27,AN27,AQ27,AT27,AW27,AZ27,BC27,BF27,BI27,BL27,BO27,BR27,BU27,BX27,CA27,CD27,CG27,CJ27,CM27,CP27,CS27), 0) | CW27: =CU27*CV27
A28: Filete de pollo x 120 | B28: Und | E28: 0 | H28: =IFERROR(F28*G28, 0) | K28: =IFERROR(I28*J28, 0) | N28: =IFERROR(L28*M28, 0) | Q28: =IFERROR(O28*P28, 0) | T28: =IFERROR(R28*S28, 0) | W28: =IFERROR(U28*V28, 0) | Z28: =IFERROR(X28*Y28, 0) | AC28: =IFERROR(AA28*AB28, 0) | AF28: =IFERROR(AD28*AE28, 0) | AI28: =IFERROR(AG28*AH28, 0) | AL28: =IFERROR(AJ28*AK28, 0) | AO28: =IFERROR(AM28*AN28, 0) | AR28: =IFERROR(AP28*AQ28, 0) | AU28: =IFERROR(AS28*AT28, 0) | AX28: =IFERROR(AV28*AW28, 0) | BA28: =IFERROR(AY28*AZ28, 0) | BD28: =IFERROR(BB28*BC28, 0) | BG28: =IFERROR(BE28*BF28, 0) | BJ28: =IFERROR(BH28*BI28, 0) | BM28: =IFERROR(BK28*BL28, 0) | BP28: =IFERROR(BN28*BO28, 0) | BS28: =IFERROR(BQ28*BR28, 0) | BV28: =IFERROR(BT28*BU28, 0) | BY28: =IFERROR(BW28*BX28, 0) | CB28: =IFERROR(BZ28*CA28, 0) | CE28: =IFERROR(CC28*CD28, 0) | CH28: =IFERROR(CF28*CG28, 0) | CK28: =IFERROR(CI28*CJ28, 0) | CN28: =IFERROR(CL28*CM28, 0) | CQ28: =IFERROR(CO28*CP28, 0) | CT28: =IFERROR(CR28*CS28, 0) | CU28: =IFERROR(SUM(F28,I28,L28,O28,R28,U28,X28,AA28,AD28,AG28,AJ28,AM28,AP28,AS28,AV28,AY28,BB28,BE28,BH28,BK28,BN28,BQ28,BT28,BW28,BZ28,CC28,CF28,CI28,CL28,CO28,CR28), 0) | CV28: =IFERROR(AVERAGE(G28,J28,M28,P28,S28,V28,Y28,AB28,AE28,AH28,AK28,AN28,AQ28,AT28,AW28,AZ28,BC28,BF28,BI28,BL28,BO28,BR28,BU28,BX28,CA28,CD28,CG28,CJ28,CM28,CP28,CS28), 0) | CW28: =CU28*CV28
A29: Filete de pollo x 350 | B29: Kg | E29: 0 | H29: =IFERROR(F29*G29, 0) | K29: =IFERROR(I29*J29, 0) | L29: 10.36 | M29: 18500 | N29: 191660 | Q29: =IFERROR(O29*P29, 0) | R29: 4 | S29: 40250 | T29: 161000 | U29: 24.9 | V29: 18500 | W29: 460650 | Z29: =IFERROR(X29*Y29, 0) | AC29: =IFERROR(AA29*AB29, 0) | AF29: =IFERROR(AD29*AE29, 0) | AG29: 24.7 | AH29: 18500 | AI29: 456950 | AL29: =IFERROR(AJ29*AK29, 0) | AO29: =IFERROR(AM29*AN29, 0) | AR29: =IFERROR(AP29*AQ29, 0) | AS29: 10.6 | AT29: 18500 | AU29: 196100 | AX29: =IFERROR(AV29*AW29, 0) | BA29: =IFERROR(AY29*AZ29, 0) | BD29: =IFERROR(BB29*BC29, 0) | BE29: 24.3 | BF29: 18500 | BG29: 449550 | BJ29: =IFERROR(BH29*BI29, 0) | BM29: =IFERROR(BK29*BL29, 0) | BP29: =IFERROR(BN29*BO29, 0) | BS29: =IFERROR(BQ29*BR29, 0) | BV29: =IFERROR(BT29*BU29, 0) | BY29: =IFERROR(BW29*BX29, 0) | CB29: =IFERROR(BZ29*CA29, 0) | CE29: =IFERROR(CC29*CD29, 0) | CH29: =IFERROR(CF29*CG29, 0) | CK29: =IFERROR(CI29*CJ29, 0) | CN29: =IFERROR(CL29*CM29, 0) | CQ29: =IFERROR(CO29*CP29, 0) | CT29: =IFERROR(CR29*CS29, 0) | CU29: =IFERROR(SUM(F29,I29,L29,O29,R29,U29,X29,AA29,AD29,AG29,AJ29,AM29,AP29,AS29,AV29,AY29,BB29,BE29,BH29,BK29,BN29,BQ29,BT29,BW29,BZ29,CC29,CF29,CI29,CL29,CO29,CR29), 0) | CV29: =IFERROR(AVERAGE(G29,J29,M29,P29,S29,V29,Y29,AB29,AE29,AH29,AK29,AN29,AQ29,AT29,AW29,AZ29,BC29,BF29,BI29,BL29,BO29,BR29,BU29,BX29,CA29,CD29,CG29,CJ29,CM29,CP29,CS29), 0) | CW29: =CU29*CV29
A30: Filete de pollo x 400 | B30: Kg | E30: 0 | H30: =IFERROR(F30*G30, 0) | K30: =IFERROR(I30*J30, 0) | N30: =IFERROR(L30*M30, 0) | Q30: =IFERROR(O30*P30, 0) | T30: =IFERROR(R30*S30, 0) | W30: =IFERROR(U30*V30, 0) | Z30: =IFERROR(X30*Y30, 0) | AC30: =IFERROR(AA30*AB30, 0) | AF30: =IFERROR(AD30*AE30, 0) | AI30: =IFERROR(AG30*AH30, 0) | AL30: =IFERROR(AJ30*AK30, 0) | AO30: =IFERROR(AM30*AN30, 0) | AR30: =IFERROR(AP30*AQ30, 0) | AU30: =IFERROR(AS30*AT30, 0) | AX30: =IFERROR(AV30*AW30, 0) | BA30: =IFERROR(AY30*AZ30, 0) | BD30: =IFERROR(BB30*BC30, 0) | BG30: =IFERROR(BE30*BF30, 0) | BJ30: =IFERROR(BH30*BI30, 0) | BM30: =IFERROR(BK30*BL30, 0) | BP30: =IFERROR(BN30*BO30, 0) | BS30: =IFERROR(BQ30*BR30, 0) | BV30: =IFERROR(BT30*BU30, 0) | BY30: =IFERROR(BW30*BX30, 0) | CB30: =IFERROR(BZ30*CA30, 0) | CE30: =IFERROR(CC30*CD30, 0) | CH30: =IFERROR(CF30*CG30, 0) | CK30: =IFERROR(CI30*CJ30, 0) | CN30: =IFERROR(CL30*CM30, 0) | CQ30: =IFERROR(CO30*CP30, 0) | CT30: =IFERROR(CR30*CS30, 0) | CU30: =IFERROR(SUM(F30,I30,L30,O30,R30,U30,X30,AA30,AD30,AG30,AJ30,AM30,AP30,AS30,AV30,AY30,BB30,BE30,BH30,BK30,BN30,BQ30,BT30,BW30,BZ30,CC30,CF30,CI30,CL30,CO30,CR30), 0) | CV30: =IFERROR(AVERAGE(G30,J30,M30,P30,S30,V30,Y30,AB30,AE30,AH30,AK30,AN30,AQ30,AT30,AW30,AZ30,BC30,BF30,BI30,BL30,BO30,BR30,BU30,BX30,CA30,CD30,CG30,CJ30,CM30,CP30,CS30), 0) | CW30: =CU30*CV30
A31: Filete de pollox 320 gr | B31: Kg | E31: 0 | H31: =IFERROR(F31*G31, 0) | K31: =IFERROR(I31*J31, 0) | N31: =IFERROR(L31*M31, 0) | Q31: =IFERROR(O31*P31, 0) | T31: =IFERROR(R31*S31, 0) | W31: =IFERROR(U31*V31, 0) | Z31: =IFERROR(X31*Y31, 0) | AC31: =IFERROR(AA31*AB31, 0) | AF31: =IFERROR(AD31*AE31, 0) | AI31: =IFERROR(AG31*AH31, 0) | AL31: =IFERROR(AJ31*AK31, 0) | AO31: =IFERROR(AM31*AN31, 0) | AR31: =IFERROR(AP31*AQ31, 0) | AU31: =IFERROR(AS31*AT31, 0) | AX31: =IFERROR(AV31*AW31, 0) | BA31: =IFERROR(AY31*AZ31, 0) | BD31: =IFERROR(BB31*BC31, 0) | BG31: =IFERROR(BE31*BF31, 0) | BJ31: =IFERROR(BH31*BI31, 0) | BM31: =IFERROR(BK31*BL31, 0) | BP31: =IFERROR(BN31*BO31, 0) | BS31: =IFERROR(BQ31*BR31, 0) | BV31: =IFERROR(BT31*BU31, 0) | BY31: =IFERROR(BW31*BX31, 0) | CB31: =IFERROR(BZ31*CA31, 0) | CE31: =IFERROR(CC31*CD31, 0) | CH31: =IFERROR(CF31*CG31, 0) | CK31: =IFERROR(CI31*CJ31, 0) | CN31: =IFERROR(CL31*CM31, 0) | CQ31: =IFERROR(CO31*CP31, 0) | CT31: =IFERROR(CR31*CS31, 0) | CU31: =IFERROR(SUM(F31,I31,L31,O31,R31,U31,X31,AA31,AD31,AG31,AJ31,AM31,AP31,AS31,AV31,AY31,BB31,BE31,BH31,BK31,BN31,BQ31,BT31,BW31,BZ31,CC31,CF31,CI31,CL31,CO31,CR31), 0) | CV31: =IFERROR(AVERAGE(G31,J31,M31,P31,S31,V31,Y31,AB31,AE31,AH31,AK31,AN31,AQ31,AT31,AW31,AZ31,BC31,BF31,BI31,BL31,BO31,BR31,BU31,BX31,CA31,CD31,CG31,CJ31,CM31,CP31,CS31), 0) | CW31: =CU31*CV31
A32: Francesa | B32: Paq | E32: 0 | H32: =IFERROR(F32*G32, 0) | K32: =IFERROR(I32*J32, 0) | N32: =IFERROR(L32*M32, 0) | Q32: =IFERROR(O32*P32, 0) | T32: =IFERROR(R32*S32, 0) | W32: =IFERROR(U32*V32, 0) | Z32: =IFERROR(X32*Y32, 0) | AC32: =IFERROR(AA32*AB32, 0) | AF32: =IFERROR(AD32*AE32, 0) | AI32: =IFERROR(AG32*AH32, 0) | AL32: =IFERROR(AJ32*AK32, 0) | AO32: =IFERROR(AM32*AN32, 0) | AR32: =IFERROR(AP32*AQ32, 0) | AU32: =IFERROR(AS32*AT32, 0) | AX32: =IFERROR(AV32*AW32, 0) | BA32: =IFERROR(AY32*AZ32, 0) | BD32: =IFERROR(BB32*BC32, 0) | BG32: =IFERROR(BE32*BF32, 0) | BJ32: =IFERROR(BH32*BI32, 0) | BM32: =IFERROR(BK32*BL32, 0) | BP32: =IFERROR(BN32*BO32, 0) | BS32: =IFERROR(BQ32*BR32, 0) | BV32: =IFERROR(BT32*BU32, 0) | BY32: =IFERROR(BW32*BX32, 0) | CB32: =IFERROR(BZ32*CA32, 0) | CE32: =IFERROR(CC32*CD32, 0) | CH32: =IFERROR(CF32*CG32, 0) | CK32: =IFERROR(CI32*CJ32, 0) | CN32: =IFERROR(CL32*CM32, 0) | CQ32: =IFERROR(CO32*CP32, 0) | CT32: =IFERROR(CR32*CS32, 0) | CU32: =IFERROR(SUM(F32,I32,L32,O32,R32,U32,X32,AA32,AD32,AG32,AJ32,AM32,AP32,AS32,AV32,AY32,BB32,BE32,BH32,BK32,BN32,BQ32,BT32,BW32,BZ32,CC32,CF32,CI32,CL32,CO32,CR32), 0) | CV32: =IFERROR(AVERAGE(G32,J32,M32,P32,S32,V32,Y32,AB32,AE32,AH32,AK32,AN32,AQ32,AT32,AW32,AZ32,BC32,BF32,BI32,BL32,BO32,BR32,BU32,BX32,CA32,CD32,CG32,CJ32,CM32,CP32,CS32), 0) | CW32: =CU32*CV32
A33: Gallina | B33: Kg | E33: 0 | H33: =IFERROR(F33*G33, 0) | K33: =IFERROR(I33*J33, 0) | N33: =IFERROR(L33*M33, 0) | Q33: =IFERROR(O33*P33, 0) | T33: =IFERROR(R33*S33, 0) | W33: =IFERROR(U33*V33, 0) | Z33: =IFERROR(X33*Y33, 0) | AC33: =IFERROR(AA33*AB33, 0) | AF33: =IFERROR(AD33*AE33, 0) | AI33: =IFERROR(AG33*AH33, 0) | AL33: =IFERROR(AJ33*AK33, 0) | AO33: =IFERROR(AM33*AN33, 0) | AR33: =IFERROR(AP33*AQ33, 0) | AU33: =IFERROR(AS33*AT33, 0) | AX33: =IFERROR(AV33*AW33, 0) | BA33: =IFERROR(AY33*AZ33, 0) | BD33: =IFERROR(BB33*BC33, 0) | BG33: =IFERROR(BE33*BF33, 0) | BJ33: =IFERROR(BH33*BI33, 0) | BM33: =IFERROR(BK33*BL33, 0) | BP33: =IFERROR(BN33*BO33, 0) | BS33: =IFERROR(BQ33*BR33, 0) | BV33: =IFERROR(BT33*BU33, 0) | BY33: =IFERROR(BW33*BX33, 0) | CB33: =IFERROR(BZ33*CA33, 0) | CE33: =IFERROR(CC33*CD33, 0) | CH33: =IFERROR(CF33*CG33, 0) | CK33: =IFERROR(CI33*CJ33, 0) | CN33: =IFERROR(CL33*CM33, 0) | CQ33: =IFERROR(CO33*CP33, 0) | CT33: =IFERROR(CR33*CS33, 0) | CU33: =IFERROR(SUM(F33,I33,L33,O33,R33,U33,X33,AA33,AD33,AG33,AJ33,AM33,AP33,AS33,AV33,AY33,BB33,BE33,BH33,BK33,BN33,BQ33,BT33,BW33,BZ33,CC33,CF33,CI33,CL33,CO33,CR33), 0) | CV33: =IFERROR(AVERAGE(G33,J33,M33,P33,S33,V33,Y33,AB33,AE33,AH33,AK33,AN33,AQ33,AT33,AW33,AZ33,BC33,BF33,BI33,BL33,BO33,BR33,BU33,BX33,CA33,CD33,CG33,CJ33,CM33,CP33,CS33), 0) | CW33: =CU33*CV33
A34: Higado | B34: Kg | E34: 0 | F34: 2 | G34: 22000 | H34: 44000 | K34: =IFERROR(I34*J34, 0) | N34: =IFERROR(L34*M34, 0) | Q34: =IFERROR(O34*P34, 0) | T34: =IFERROR(R34*S34, 0) | W34: =IFERROR(U34*V34, 0) | Z34: =IFERROR(X34*Y34, 0) | AC34: =IFERROR(AA34*AB34, 0) | AF34: =IFERROR(AD34*AE34, 0) | AI34: =IFERROR(AG34*AH34, 0) | AL34: =IFERROR(AJ34*AK34, 0) | AO34: =IFERROR(AM34*AN34, 0) | AR34: =IFERROR(AP34*AQ34, 0) | AU34: =IFERROR(AS34*AT34, 0) | AV34: 8.2 | AW34: 21500 | AX34: 176300 | BA34: =IFERROR(AY34*AZ34, 0) | BD34: =IFERROR(BB34*BC34, 0) | BG34: =IFERROR(BE34*BF34, 0) | BJ34: =IFERROR(BH34*BI34, 0) | BM34: =IFERROR(BK34*BL34, 0) | BP34: =IFERROR(BN34*BO34, 0) | BS34: =IFERROR(BQ34*BR34, 0) | BV34: =IFERROR(BT34*BU34, 0) | BY34: =IFERROR(BW34*BX34, 0) | CB34: =IFERROR(BZ34*CA34, 0) | CE34: =IFERROR(CC34*CD34, 0) | CH34: =IFERROR(CF34*CG34, 0) | CK34: =IFERROR(CI34*CJ34, 0) | CN34: =IFERROR(CL34*CM34, 0) | CQ34: =IFERROR(CO34*CP34, 0) | CT34: =IFERROR(CR34*CS34, 0) | CU34: =IFERROR(SUM(F34,I34,L34,O34,R34,U34,X34,AA34,AD34,AG34,AJ34,AM34,AP34,AS34,AV34,AY34,BB34,BE34,BH34,BK34,BN34,BQ34,BT34,BW34,BZ34,CC34,CF34,CI34,CL34,CO34,CR34), 0) | CV34: =IFERROR(AVERAGE(G34,J34,M34,P34,S34,V34,Y34,AB34,AE34,AH34,AK34,AN34,AQ34,AT34,AW34,AZ34,BC34,BF34,BI34,BL34,BO34,BR34,BU34,BX34,CA34,CD34,CG34,CJ34,CM34,CP34,CS34), 0) | CW34: =CU34*CV34
A35: Lengua de res | B35: Kg | E35: 0 | F35: 5.91 | G35: 23500 | H35: 138767.5 | K35: =IFERROR(I35*J35, 0) | N35: =IFERROR(L35*M35, 0) | O35: 5.43 | P35: 23500 | Q35: 127605 | T35: =IFERROR(R35*S35, 0) | W35: =IFERROR(U35*V35, 0) | X35: 42.6 | Y35: 22900 | Z35: 975540 | AC35: =IFERROR(AA35*AB35, 0) | AF35: =IFERROR(AD35*AE35, 0) | AI35: =IFERROR(AG35*AH35, 0) | AL35: =IFERROR(AJ35*AK35, 0) | AO35: =IFERROR(AM35*AN35, 0) | AR35: =IFERROR(AP35*AQ35, 0) | AU35: =IFERROR(AS35*AT35, 0) | AX35: =IFERROR(AV35*AW35, 0) | BA35: =IFERROR(AY35*AZ35, 0) | BB35: 40.1 | BC35: 22900 | BD35: 918290 | BG35: =IFERROR(BE35*BF35, 0) | BJ35: =IFERROR(BH35*BI35, 0) | BM35: =IFERROR(BK35*BL35, 0) | BP35: =IFERROR(BN35*BO35, 0) | BS35: =IFERROR(BQ35*BR35, 0) | BV35: =IFERROR(BT35*BU35, 0) | BY35: =IFERROR(BW35*BX35, 0) | CB35: =IFERROR(BZ35*CA35, 0) | CE35: =IFERROR(CC35*CD35, 0) | CH35: =IFERROR(CF35*CG35, 0) | CK35: =IFERROR(CI35*CJ35, 0) | CN35: =IFERROR(CL35*CM35, 0) | CQ35: =IFERROR(CO35*CP35, 0) | CT35: =IFERROR(CR35*CS35, 0) | CU35: =IFERROR(SUM(F35,I35,L35,O35,R35,U35,X35,AA35,AD35,AG35,AJ35,AM35,AP35,AS35,AV35,AY35,BB35,BE35,BH35,BK35,BN35,BQ35,BT35,BW35,BZ35,CC35,CF35,CI35,CL35,CO35,CR35), 0) | CV35: =IFERROR(AVERAGE(G35,J35,M35,P35,S35,V35,Y35,AB35,AE35,AH35,AK35,AN35,AQ35,AT35,AW35,AZ35,BC35,BF35,BI35,BL35,BO35,BR35,BU35,BX35,CA35,CD35,CG35,CJ35,CM35,CP35,CS35), 0) | CW35: =CU35*CV35
A36: Chorizo paisa | B36: Kg | E36: 0 | H36: =IFERROR(F36*G36, 0) | K36: =IFERROR(I36*J36, 0) | N36: =IFERROR(L36*M36, 0) | Q36: =IFERROR(O36*P36, 0) | T36: =IFERROR(R36*S36, 0) | W36: =IFERROR(U36*V36, 0) | Z36: =IFERROR(X36*Y36, 0) | AC36: =IFERROR(AA36*AB36, 0) | AF36: =IFERROR(AD36*AE36, 0) | AI36: =IFERROR(AG36*AH36, 0) | AL36: =IFERROR(AJ36*AK36, 0) | AO36: =IFERROR(AM36*AN36, 0) | AR36: =IFERROR(AP36*AQ36, 0) | AU36: =IFERROR(AS36*AT36, 0) | AX36: =IFERROR(AV36*AW36, 0) | BA36: =IFERROR(AY36*AZ36, 0) | BD36: =IFERROR(BB36*BC36, 0) | BG36: =IFERROR(BE36*BF36, 0) | BJ36: =IFERROR(BH36*BI36, 0) | BM36: =IFERROR(BK36*BL36, 0) | BP36: =IFERROR(BN36*BO36, 0) | BS36: =IFERROR(BQ36*BR36, 0) | BV36: =IFERROR(BT36*BU36, 0) | BY36: =IFERROR(BW36*BX36, 0) | CB36: =IFERROR(BZ36*CA36, 0) | CE36: =IFERROR(CC36*CD36, 0) | CH36: =IFERROR(CF36*CG36, 0) | CK36: =IFERROR(CI36*CJ36, 0) | CN36: =IFERROR(CL36*CM36, 0) | CQ36: =IFERROR(CO36*CP36, 0) | CT36: =IFERROR(CR36*CS36, 0) | CU36: =IFERROR(SUM(F36,I36,L36,O36,R36,U36,X36,AA36,AD36,AG36,AJ36,AM36,AP36,AS36,AV36,AY36,BB36,BE36,BH36,BK36,BN36,BQ36,BT36,BW36,BZ36,CC36,CF36,CI36,CL36,CO36,CR36), 0) | CV36: =IFERROR(AVERAGE(G36,J36,M36,P36,S36,V36,Y36,AB36,AE36,AH36,AK36,AN36,AQ36,AT36,AW36,AZ36,BC36,BF36,BI36,BL36,BO36,BR36,BU36,BX36,CA36,CD36,CG36,CJ36,CM36,CP36,CS36), 0) | CW36: =CU36*CV36
A37: Lomo de cerdo | B37: Kg | E37: 0 | F37: 13.2 | G37: 19800 | H37: 261360 | K37: =IFERROR(I37*J37, 0) | N37: =IFERROR(L37*M37, 0) | O37: 15.9 | P37: 19800 | Q37: 314820 | R37: 20.6 | S37: 19500 | T37: 401700 | U37: 10.57 | V37: 19800 | W37: 328986 | Z37: =IFERROR(X37*Y37, 0) | AC37: =IFERROR(AA37*AB37, 0) | AF37: =IFERROR(AD37*AE37, 0) | AI37: =IFERROR(AG37*AH37, 0) | AL37: =IFERROR(AJ37*AK37, 0) | AO37: =IFERROR(AM37*AN37, 0) | AR37: =IFERROR(AP37*AQ37, 0) | AU37: =IFERROR(AS37*AT37, 0) | AX37: =IFERROR(AV37*AW37, 0) | BA37: =IFERROR(AY37*AZ37, 0) | BD37: =IFERROR(BB37*BC37, 0) | BG37: =IFERROR(BE37*BF37, 0) | BJ37: =IFERROR(BH37*BI37, 0) | BM37: =IFERROR(BK37*BL37, 0) | BN37: 9.15 | BO37: 19500 | BP37: 178425 | BQ37: 18.31 | BR37: 19500 | BS37: 357045 | BV37: =IFERROR(BT37*BU37, 0) | BY37: =IFERROR(BW37*BX37, 0) | CB37: =IFERROR(BZ37*CA37, 0) | CE37: =IFERROR(CC37*CD37, 0) | CH37: =IFERROR(CF37*CG37, 0) | CI37: 9.15 | CJ37: 19500 | CK37: 178425 | CN37: =IFERROR(CL37*CM37, 0) | CQ37: =IFERROR(CO37*CP37, 0) | CT37: =IFERROR(CR37*CS37, 0) | CU37: =IFERROR(SUM(F37,I37,L37,O37,R37,U37,X37,AA37,AD37,AG37,AJ37,AM37,AP37,AS37,AV37,AY37,BB37,BE37,BH37,BK37,BN37,BQ37,BT37,BW37,BZ37,CC37,CF37,CI37,CL37,CO37,CR37), 0) | CV37: =IFERROR(AVERAGE(G37,J37,M37,P37,S37,V37,Y37,AB37,AE37,AH37,AK37,AN37,AQ37,AT37,AW37,AZ37,BC37,BF37,BI37,BL37,BO37,BR37,BU37,BX37,CA37,CD37,CG37,CJ37,CM37,CP37,CS37), 0) | CW37: =CU37*CV37
A38: Lomo viche | B38: Kg | E38: 0 | H38: =IFERROR(F38*G38, 0) | K38: =IFERROR(I38*J38, 0) | N38: =IFERROR(L38*M38, 0) | O38: 8.75 | P38: 45000 | Q38: 393750 | T38: =IFERROR(R38*S38, 0) | W38: =IFERROR(U38*V38, 0) | Z38: =IFERROR(X38*Y38, 0) | AC38: =IFERROR(AA38*AB38, 0) | AF38: =IFERROR(AD38*AE38, 0) | AI38: =IFERROR(AG38*AH38, 0) | AL38: =IFERROR(AJ38*AK38, 0) | AO38: =IFERROR(AM38*AN38, 0) | AP38: 5.75 | AQ38: 46000 | AR38: 264500 | AU38: =IFERROR(AS38*AT38, 0) | AX38: =IFERROR(AV38*AW38, 0) | BA38: =IFERROR(AY38*AZ38, 0) | BD38: =IFERROR(BB38*BC38, 0) | BG38: =IFERROR(BE38*BF38, 0) | BJ38: =IFERROR(BH38*BI38, 0) | BM38: =IFERROR(BK38*BL38, 0) | BP38: =IFERROR(BN38*BO38, 0) | BS38: =IFERROR(BQ38*BR38, 0) | BT38: 4.2 | BU38: 65900 | BV38: 276780 | BY38: =IFERROR(BW38*BX38, 0) | CB38: =IFERROR(BZ38*CA38, 0) | CE38: =IFERROR(CC38*CD38, 0) | CH38: =IFERROR(CF38*CG38, 0) | CK38: =IFERROR(CI38*CJ38, 0) | CN38: =IFERROR(CL38*CM38, 0) | CQ38: =IFERROR(CO38*CP38, 0) | CT38: =IFERROR(CR38*CS38, 0) | CU38: =IFERROR(SUM(F38,I38,L38,O38,R38,U38,X38,AA38,AD38,AG38,AJ38,AM38,AP38,AS38,AV38,AY38,BB38,BE38,BH38,BK38,BN38,BQ38,BT38,BW38,BZ38,CC38,CF38,CI38,CL38,CO38,CR38), 0) | CV38: =IFERROR(AVERAGE(G38,J38,M38,P38,S38,V38,Y38,AB38,AE38,AH38,AK38,AN38,AQ38,AT38,AW38,AZ38,BC38,BF38,BI38,BL38,BO38,BR38,BU38,BX38,CA38,CD38,CG38,CJ38,CM38,CP38,CS38), 0) | CW38: =CU38*CV38
A39: Marisco | B39: Kg | E39: 0 | H39: =IFERROR(F39*G39, 0) | K39: =IFERROR(I39*J39, 0) | N39: =IFERROR(L39*M39, 0) | Q39: =IFERROR(O39*P39, 0) | T39: =IFERROR(R39*S39, 0) | W39: =IFERROR(U39*V39, 0) | Z39: =IFERROR(X39*Y39, 0) | AC39: =IFERROR(AA39*AB39, 0) | AD39: 24 | AE39: 5000 | AF39: 120000 | AI39: =IFERROR(AG39*AH39, 0) | AL39: =IFERROR(AJ39*AK39, 0) | AO39: =IFERROR(AM39*AN39, 0) | AR39: =IFERROR(AP39*AQ39, 0) | AU39: =IFERROR(AS39*AT39, 0) | AX39: =IFERROR(AV39*AW39, 0) | BA39: =IFERROR(AY39*AZ39, 0) | BD39: =IFERROR(BB39*BC39, 0) | BG39: =IFERROR(BE39*BF39, 0) | BJ39: =IFERROR(BH39*BI39, 0) | BM39: =IFERROR(BK39*BL39, 0) | BP39: =IFERROR(BN39*BO39, 0) | BS39: =IFERROR(BQ39*BR39, 0) | BV39: =IFERROR(BT39*BU39, 0) | BY39: =IFERROR(BW39*BX39, 0) | CB39: =IFERROR(BZ39*CA39, 0) | CE39: =IFERROR(CC39*CD39, 0) | CH39: =IFERROR(CF39*CG39, 0) | CK39: =IFERROR(CI39*CJ39, 0) | CN39: =IFERROR(CL39*CM39, 0) | CQ39: =IFERROR(CO39*CP39, 0) | CT39: =IFERROR(CR39*CS39, 0) | CU39: =IFERROR(SUM(F39,I39,L39,O39,R39,U39,X39,AA39,AD39,AG39,AJ39,AM39,AP39,AS39,AV39,AY39,BB39,BE39,BH39,BK39,BN39,BQ39,BT39,BW39,BZ39,CC39,CF39,CI39,CL39,CO39,CR39), 0) | CV39: =IFERROR(AVERAGE(G39,J39,M39,P39,S39,V39,Y39,AB39,AE39,AH39,AK39,AN39,AQ39,AT39,AW39,AZ39,BC39,BF39,BI39,BL39,BO39,BR39,BU39,BX39,CA39,CD39,CG39,CJ39,CM39,CP39,CS39), 0) | CW39: =CU39*CV39
A40: Mix de verdura | B40: Paq | E40: 0 | H40: =IFERROR(F40*G40, 0) | I40: 10 | J40: 8487.4 | K40: 84874 | N40: =IFERROR(L40*M40, 0) | Q40: =IFERROR(O40*P40, 0) | T40: =IFERROR(R40*S40, 0) | W40: =IFERROR(U40*V40, 0) | Z40: =IFERROR(X40*Y40, 0) | AC40: =IFERROR(AA40*AB40, 0) | AF40: =IFERROR(AD40*AE40, 0) | AI40: =IFERROR(AG40*AH40, 0) | AL40: =IFERROR(AJ40*AK40, 0) | AO40: =IFERROR(AM40*AN40, 0) | AR40: =IFERROR(AP40*AQ40, 0) | AU40: =IFERROR(AS40*AT40, 0) | AX40: =IFERROR(AV40*AW40, 0) | BA40: =IFERROR(AY40*AZ40, 0) | BB40: 10 | BC40: 8487.4 | BD40: 84874 | BG40: =IFERROR(BE40*BF40, 0) | BJ40: =IFERROR(BH40*BI40, 0) | BM40: =IFERROR(BK40*BL40, 0) | BP40: =IFERROR(BN40*BO40, 0) | BS40: =IFERROR(BQ40*BR40, 0) | BV40: =IFERROR(BT40*BU40, 0) | BY40: =IFERROR(BW40*BX40, 0) | CB40: =IFERROR(BZ40*CA40, 0) | CE40: =IFERROR(CC40*CD40, 0) | CH40: =IFERROR(CF40*CG40, 0) | CK40: =IFERROR(CI40*CJ40, 0) | CN40: =IFERROR(CL40*CM40, 0) | CQ40: =IFERROR(CO40*CP40, 0) | CT40: =IFERROR(CR40*CS40, 0) | CU40: =IFERROR(SUM(F40,I40,L40,O40,R40,U40,X40,AA40,AD40,AG40,AJ40,AM40,AP40,AS40,AV40,AY40,BB40,BE40,BH40,BK40,BN40,BQ40,BT40,BW40,BZ40,CC40,CF40,CI40,CL40,CO40,CR40), 0) | CV40: =IFERROR(AVERAGE(G40,J40,M40,P40,S40,V40,Y40,AB40,AE40,AH40,AK40,AN40,AQ40,AT40,AW40,AZ40,BC40,BF40,BI40,BL40,BO40,BR40,BU40,BX40,CA40,CD40,CG40,CJ40,CM40,CP40,CS40), 0) | CW40: =CU40*CV40
A41: Morrillo | B41: Kg | E41: 0 | H41: =IFERROR(F41*G41, 0) | K41: =IFERROR(I41*J41, 0) | N41: =IFERROR(L41*M41, 0) | Q41: =IFERROR(O41*P41, 0) | T41: =IFERROR(R41*S41, 0) | W41: =IFERROR(U41*V41, 0) | Z41: =IFERROR(X41*Y41, 0) | AC41: =IFERROR(AA41*AB41, 0) | AF41: =IFERROR(AD41*AE41, 0) | AI41: =IFERROR(AG41*AH41, 0) | AL41: =IFERROR(AJ41*AK41, 0) | AO41: =IFERROR(AM41*AN41, 0) | AR41: =IFERROR(AP41*AQ41, 0) | AU41: =IFERROR(AS41*AT41, 0) | AX41: =IFERROR(AV41*AW41, 0) | BA41: =IFERROR(AY41*AZ41, 0) | BD41: =IFERROR(BB41*BC41, 0) | BG41: =IFERROR(BE41*BF41, 0) | BJ41: =IFERROR(BH41*BI41, 0) | BM41: =IFERROR(BK41*BL41, 0) | BP41: =IFERROR(BN41*BO41, 0) | BS41: =IFERROR(BQ41*BR41, 0) | BV41: =IFERROR(BT41*BU41, 0) | BY41: =IFERROR(BW41*BX41, 0) | CB41: =IFERROR(BZ41*CA41, 0) | CE41: =IFERROR(CC41*CD41, 0) | CH41: =IFERROR(CF41*CG41, 0) | CK41: =IFERROR(CI41*CJ41, 0) | CN41: =IFERROR(CL41*CM41, 0) | CQ41: =IFERROR(CO41*CP41, 0) | CT41: =IFERROR(CR41*CS41, 0) | CU41: =IFERROR(SUM(F41,I41,L41,O41,R41,U41,X41,AA41,AD41,AG41,AJ41,AM41,AP41,AS41,AV41,AY41,BB41,BE41,BH41,BK41,BN41,BQ41,BT41,BW41,BZ41,CC41,CF41,CI41,CL41,CO41,CR41), 0) | CV41: =IFERROR(AVERAGE(G41,J41,M41,P41,S41,V41,Y41,AB41,AE41,AH41,AK41,AN41,AQ41,AT41,AW41,AZ41,BC41,BF41,BI41,BL41,BO41,BR41,BU41,BX41,CA41,CD41,CG41,CJ41,CM41,CP41,CS41), 0) | CW41: =CU41*CV41
A42: Mortadela | B42: Kg | E42: 0 | H42: =IFERROR(F42*G42, 0) | K42: =IFERROR(I42*J42, 0) | N42: =IFERROR(L42*M42, 0) | Q42: =IFERROR(O42*P42, 0) | T42: =IFERROR(R42*S42, 0) | W42: =IFERROR(U42*V42, 0) | Z42: =IFERROR(X42*Y42, 0) | AC42: =IFERROR(AA42*AB42, 0) | AF42: =IFERROR(AD42*AE42, 0) | AI42: =IFERROR(AG42*AH42, 0) | AL42: =IFERROR(AJ42*AK42, 0) | AO42: =IFERROR(AM42*AN42, 0) | AR42: =IFERROR(AP42*AQ42, 0) | AU42: =IFERROR(AS42*AT42, 0) | AX42: =IFERROR(AV42*AW42, 0) | BA42: =IFERROR(AY42*AZ42, 0) | BD42: =IFERROR(BB42*BC42, 0) | BG42: =IFERROR(BE42*BF42, 0) | BJ42: =IFERROR(BH42*BI42, 0) | BM42: =IFERROR(BK42*BL42, 0) | BP42: =IFERROR(BN42*BO42, 0) | BS42: =IFERROR(BQ42*BR42, 0) | BV42: =IFERROR(BT42*BU42, 0) | BY42: =IFERROR(BW42*BX42, 0) | CB42: =IFERROR(BZ42*CA42, 0) | CE42: =IFERROR(CC42*CD42, 0) | CH42: =IFERROR(CF42*CG42, 0) | CK42: =IFERROR(CI42*CJ42, 0) | CN42: =IFERROR(CL42*CM42, 0) | CQ42: =IFERROR(CO42*CP42, 0) | CT42: =IFERROR(CR42*CS42, 0) | CU42: =IFERROR(SUM(F42,I42,L42,O42,R42,U42,X42,AA42,AD42,AG42,AJ42,AM42,AP42,AS42,AV42,AY42,BB42,BE42,BH42,BK42,BN42,BQ42,BT42,BW42,BZ42,CC42,CF42,CI42,CL42,CO42,CR42), 0) | CV42: =IFERROR(AVERAGE(G42,J42,M42,P42,S42,V42,Y42,AB42,AE42,AH42,AK42,AN42,AQ42,AT42,AW42,AZ42,BC42,BF42,BI42,BL42,BO42,BR42,BU42,BX42,CA42,CD42,CG42,CJ42,CM42,CP42,CS42), 0) | CW42: =CU42*CV42
A43: Mortadela | B43: Kg | E43: 0 | H43: =IFERROR(F43*G43, 0) | K43: =IFERROR(I43*J43, 0) | N43: =IFERROR(L43*M43, 0) | Q43: =IFERROR(O43*P43, 0) | T43: =IFERROR(R43*S43, 0) | W43: =IFERROR(U43*V43, 0) | Z43: =IFERROR(X43*Y43, 0) | AC43: =IFERROR(AA43*AB43, 0) | AF43: =IFERROR(AD43*AE43, 0) | AI43: =IFERROR(AG43*AH43, 0) | AL43: =IFERROR(AJ43*AK43, 0) | AO43: =IFERROR(AM43*AN43, 0) | AR43: =IFERROR(AP43*AQ43, 0) | AU43: =IFERROR(AS43*AT43, 0) | AX43: =IFERROR(AV43*AW43, 0) | BA43: =IFERROR(AY43*AZ43, 0) | BD43: =IFERROR(BB43*BC43, 0) | BG43: =IFERROR(BE43*BF43, 0) | BJ43: =IFERROR(BH43*BI43, 0) | BK43: 1 | BL43: 10600 | BM43: 10600 | BP43: =IFERROR(BN43*BO43, 0) | BS43: =IFERROR(BQ43*BR43, 0) | BV43: =IFERROR(BT43*BU43, 0) | BY43: =IFERROR(BW43*BX43, 0) | CB43: =IFERROR(BZ43*CA43, 0) | CE43: =IFERROR(CC43*CD43, 0) | CH43: =IFERROR(CF43*CG43, 0) | CK43: =IFERROR(CI43*CJ43, 0) | CN43: =IFERROR(CL43*CM43, 0) | CQ43: =IFERROR(CO43*CP43, 0) | CT43: =IFERROR(CR43*CS43, 0) | CU43: =IFERROR(SUM(F43,I43,L43,O43,R43,U43,X43,AA43,AD43,AG43,AJ43,AM43,AP43,AS43,AV43,AY43,BB43,BE43,BH43,BK43,BN43,BQ43,BT43,BW43,BZ43,CC43,CF43,CI43,CL43,CO43,CR43), 0) | CV43: =IFERROR(AVERAGE(G43,J43,M43,P43,S43,V43,Y43,AB43,AE43,AH43,AK43,AN43,AQ43,AT43,AW43,AZ43,BC43,BF43,BI43,BL43,BO43,BR43,BU43,BX43,CA43,CD43,CG43,CJ43,CM43,CP43,CS43), 0) | CW43: =CU43*CV43
A44: Chorizo mediano | B44: Und | E44: 0 | H44: =IFERROR(F44*G44, 0) | K44: =IFERROR(I44*J44, 0) | N44: =IFERROR(L44*M44, 0) | Q44: =IFERROR(O44*P44, 0) | T44: =IFERROR(R44*S44, 0) | W44: =IFERROR(U44*V44, 0) | Z44: =IFERROR(X44*Y44, 0) | AC44: =IFERROR(AA44*AB44, 0) | AF44: =IFERROR(AD44*AE44, 0) | AI44: =IFERROR(AG44*AH44, 0) | AL44: =IFERROR(AJ44*AK44, 0) | AO44: =IFERROR(AM44*AN44, 0) | AR44: =IFERROR(AP44*AQ44, 0) | AU44: =IFERROR(AS44*AT44, 0) | AX44: =IFERROR(AV44*AW44, 0) | BA44: =IFERROR(AY44*AZ44, 0) | BD44: =IFERROR(BB44*BC44, 0) | BG44: =IFERROR(BE44*BF44, 0) | BJ44: =IFERROR(BH44*BI44, 0) | BM44: =IFERROR(BK44*BL44, 0) | BP44: =IFERROR(BN44*BO44, 0) | BS44: =IFERROR(BQ44*BR44, 0) | BV44: =IFERROR(BT44*BU44, 0) | BY44: =IFERROR(BW44*BX44, 0) | CB44: =IFERROR(BZ44*CA44, 0) | CE44: =IFERROR(CC44*CD44, 0) | CH44: =IFERROR(CF44*CG44, 0) | CK44: =IFERROR(CI44*CJ44, 0) | CN44: =IFERROR(CL44*CM44, 0) | CQ44: =IFERROR(CO44*CP44, 0) | CT44: =IFERROR(CR44*CS44, 0) | CU44: =IFERROR(SUM(F44,I44,L44,O44,R44,U44,X44,AA44,AD44,AG44,AJ44,AM44,AP44,AS44,AV44,AY44,BB44,BE44,BH44,BK44,BN44,BQ44,BT44,BW44,BZ44,CC44,CF44,CI44,CL44,CO44,CR44), 0) | CV44: =IFERROR(AVERAGE(G44,J44,M44,P44,S44,V44,Y44,AB44,AE44,AH44,AK44,AN44,AQ44,AT44,AW44,AZ44,BC44,BF44,BI44,BL44,BO44,BR44,BU44,BX44,CA44,CD44,CG44,CJ44,CM44,CP44,CS44), 0) | CW44: =CU44*CV44
A45: Panceta de cerdo | B45: Kg | E45: 0 | H45: =IFERROR(F45*G45, 0) | K45: =IFERROR(I45*J45, 0) | N45: =IFERROR(L45*M45, 0) | Q45: =IFERROR(O45*P45, 0) | T45: =IFERROR(R45*S45, 0) | W45: =IFERROR(U45*V45, 0) | Z45: =IFERROR(X45*Y45, 0) | AC45: =IFERROR(AA45*AB45, 0) | AF45: =IFERROR(AD45*AE45, 0) | AI45: =IFERROR(AG45*AH45, 0) | AL45: =IFERROR(AJ45*AK45, 0) | AO45: =IFERROR(AM45*AN45, 0) | AR45: =IFERROR(AP45*AQ45, 0) | AU45: =IFERROR(AS45*AT45, 0) | AX45: =IFERROR(AV45*AW45, 0) | BA45: =IFERROR(AY45*AZ45, 0) | BD45: =IFERROR(BB45*BC45, 0) | BG45: =IFERROR(BE45*BF45, 0) | BJ45: =IFERROR(BH45*BI45, 0) | BM45: =IFERROR(BK45*BL45, 0) | BP45: =IFERROR(BN45*BO45, 0) | BS45: =IFERROR(BQ45*BR45, 0) | BV45: =IFERROR(BT45*BU45, 0) | BY45: =IFERROR(BW45*BX45, 0) | CB45: =IFERROR(BZ45*CA45, 0) | CE45: =IFERROR(CC45*CD45, 0) | CH45: =IFERROR(CF45*CG45, 0) | CK45: =IFERROR(CI45*CJ45, 0) | CN45: =IFERROR(CL45*CM45, 0) | CQ45: =IFERROR(CO45*CP45, 0) | CT45: =IFERROR(CR45*CS45, 0) | CU45: =IFERROR(SUM(F45,I45,L45,O45,R45,U45,X45,AA45,AD45,AG45,AJ45,AM45,AP45,AS45,AV45,AY45,BB45,BE45,BH45,BK45,BN45,BQ45,BT45,BW45,BZ45,CC45,CF45,CI45,CL45,CO45,CR45), 0) | CV45: =IFERROR(AVERAGE(G45,J45,M45,P45,S45,V45,Y45,AB45,AE45,AH45,AK45,AN45,AQ45,AT45,AW45,AZ45,BC45,BF45,BI45,BL45,BO45,BR45,BU45,BX45,CA45,CD45,CG45,CJ45,CM45,CP45,CS45), 0) | CW45: =CU45*CV45
A46: Pata de res | B46: Kg | E46: 0 | H46: =IFERROR(F46*G46, 0) | K46: =IFERROR(I46*J46, 0) | N46: =IFERROR(L46*M46, 0) | Q46: =IFERROR(O46*P46, 0) | T46: =IFERROR(R46*S46, 0) | W46: =IFERROR(U46*V46, 0) | Z46: =IFERROR(X46*Y46, 0) | AC46: =IFERROR(AA46*AB46, 0) | AF46: =IFERROR(AD46*AE46, 0) | AI46: =IFERROR(AG46*AH46, 0) | AL46: =IFERROR(AJ46*AK46, 0) | AO46: =IFERROR(AM46*AN46, 0) | AR46: =IFERROR(AP46*AQ46, 0) | AU46: =IFERROR(AS46*AT46, 0) | AX46: =IFERROR(AV46*AW46, 0) | BA46: =IFERROR(AY46*AZ46, 0) | BD46: =IFERROR(BB46*BC46, 0) | BG46: =IFERROR(BE46*BF46, 0) | BJ46: =IFERROR(BH46*BI46, 0) | BM46: =IFERROR(BK46*BL46, 0) | BP46: =IFERROR(BN46*BO46, 0) | BS46: =IFERROR(BQ46*BR46, 0) | BV46: =IFERROR(BT46*BU46, 0) | BY46: =IFERROR(BW46*BX46, 0) | CB46: =IFERROR(BZ46*CA46, 0) | CE46: =IFERROR(CC46*CD46, 0) | CH46: =IFERROR(CF46*CG46, 0) | CK46: =IFERROR(CI46*CJ46, 0) | CN46: =IFERROR(CL46*CM46, 0) | CQ46: =IFERROR(CO46*CP46, 0) | CT46: =IFERROR(CR46*CS46, 0) | CU46: =IFERROR(SUM(F46,I46,L46,O46,R46,U46,X46,AA46,AD46,AG46,AJ46,AM46,AP46,AS46,AV46,AY46,BB46,BE46,BH46,BK46,BN46,BQ46,BT46,BW46,BZ46,CC46,CF46,CI46,CL46,CO46,CR46), 0) | CV46: =IFERROR(AVERAGE(G46,J46,M46,P46,S46,V46,Y46,AB46,AE46,AH46,AK46,AN46,AQ46,AT46,AW46,AZ46,BC46,BF46,BI46,BL46,BO46,BR46,BU46,BX46,CA46,CD46,CG46,CJ46,CM46,CP46,CS46), 0) | CW46: =CU46*CV46
A47: Chorizo grande | B47: Und | E47: 0 | H47: =IFERROR(F47*G47, 0) | K47: =IFERROR(I47*J47, 0) | N47: =IFERROR(L47*M47, 0) | Q47: =IFERROR(O47*P47, 0) | T47: =IFERROR(R47*S47, 0) | W47: =IFERROR(U47*V47, 0) | Z47: =IFERROR(X47*Y47, 0) | AC47: =IFERROR(AA47*AB47, 0) | AF47: =IFERROR(AD47*AE47, 0) | AI47: =IFERROR(AG47*AH47, 0) | AL47: =IFERROR(AJ47*AK47, 0) | AO47: =IFERROR(AM47*AN47, 0) | AR47: =IFERROR(AP47*AQ47, 0) | AU47: =IFERROR(AS47*AT47, 0) | AX47: =IFERROR(AV47*AW47, 0) | BA47: =IFERROR(AY47*AZ47, 0) | BD47: =IFERROR(BB47*BC47, 0) | BG47: =IFERROR(BE47*BF47, 0) | BJ47: =IFERROR(BH47*BI47, 0) | BM47: =IFERROR(BK47*BL47, 0) | BP47: =IFERROR(BN47*BO47, 0) | BS47: =IFERROR(BQ47*BR47, 0) | BV47: =IFERROR(BT47*BU47, 0) | BY47: =IFERROR(BW47*BX47, 0) | CB47: =IFERROR(BZ47*CA47, 0) | CE47: =IFERROR(CC47*CD47, 0) | CH47: =IFERROR(CF47*CG47, 0) | CK47: =IFERROR(CI47*CJ47, 0) | CN47: =IFERROR(CL47*CM47, 0) | CQ47: =IFERROR(CO47*CP47, 0) | CT47: =IFERROR(CR47*CS47, 0) | CU47: =IFERROR(SUM(F47,I47,L47,O47,R47,U47,X47,AA47,AD47,AG47,AJ47,AM47,AP47,AS47,AV47,AY47,BB47,BE47,BH47,BK47,BN47,BQ47,BT47,BW47,BZ47,CC47,CF47,CI47,CL47,CO47,CR47), 0) | CV47: =IFERROR(AVERAGE(G47,J47,M47,P47,S47,V47,Y47,AB47,AE47,AH47,AK47,AN47,AQ47,AT47,AW47,AZ47,BC47,BF47,BI47,BL47,BO47,BR47,BU47,BX47,CA47,CD47,CG47,CJ47,CM47,CP47,CS47), 0) | CW47: =CU47*CV47
A48: Pernil de cerdo | B48: Kg | E48: 0 | H48: =IFERROR(F48*G48, 0) | K48: =IFERROR(I48*J48, 0) | N48: =IFERROR(L48*M48, 0) | Q48: =IFERROR(O48*P48, 0) | T48: =IFERROR(R48*S48, 0) | W48: =IFERROR(U48*V48, 0) | Z48: =IFERROR(X48*Y48, 0) | AC48: =IFERROR(AA48*AB48, 0) | AF48: =IFERROR(AD48*AE48, 0) | AI48: =IFERROR(AG48*AH48, 0) | AL48: =IFERROR(AJ48*AK48, 0) | AO48: =IFERROR(AM48*AN48, 0) | AR48: =IFERROR(AP48*AQ48, 0) | AU48: =IFERROR(AS48*AT48, 0) | AX48: =IFERROR(AV48*AW48, 0) | BA48: =IFERROR(AY48*AZ48, 0) | BD48: =IFERROR(BB48*BC48, 0) | BG48: =IFERROR(BE48*BF48, 0) | BJ48: =IFERROR(BH48*BI48, 0) | BM48: =IFERROR(BK48*BL48, 0) | BP48: =IFERROR(BN48*BO48, 0) | BS48: =IFERROR(BQ48*BR48, 0) | BV48: =IFERROR(BT48*BU48, 0) | BY48: =IFERROR(BW48*BX48, 0) | CB48: =IFERROR(BZ48*CA48, 0) | CE48: =IFERROR(CC48*CD48, 0) | CH48: =IFERROR(CF48*CG48, 0) | CK48: =IFERROR(CI48*CJ48, 0) | CN48: =IFERROR(CL48*CM48, 0) | CQ48: =IFERROR(CO48*CP48, 0) | CT48: =IFERROR(CR48*CS48, 0) | CU48: =IFERROR(SUM(F48,I48,L48,O48,R48,U48,X48,AA48,AD48,AG48,AJ48,AM48,AP48,AS48,AV48,AY48,BB48,BE48,BH48,BK48,BN48,BQ48,BT48,BW48,BZ48,CC48,CF48,CI48,CL48,CO48,CR48), 0) | CV48: =IFERROR(AVERAGE(G48,J48,M48,P48,S48,V48,Y48,AB48,AE48,AH48,AK48,AN48,AQ48,AT48,AW48,AZ48,BC48,BF48,BI48,BL48,BO48,BR48,BU48,BX48,CA48,CD48,CG48,CJ48,CM48,CP48,CS48), 0) | CW48: =CU48*CV48
A49: Pernil de pollo | B49: Kg | E49: 0 | F49: 8.98 | G49: 15000 | H49: 70800 | K49: =IFERROR(I49*J49, 0) | N49: =IFERROR(L49*M49, 0) | Q49: =IFERROR(O49*P49, 0) | T49: =IFERROR(R49*S49, 0) | W49: =IFERROR(U49*V49, 0) | Z49: =IFERROR(X49*Y49, 0) | AA49: 35.36 | AB49: 7635.75 | AC49: 270000 | AD49: 6.6 | AE49: 7700 | AF49: 50820 | AI49: =IFERROR(AG49*AH49, 0) | AL49: =IFERROR(AJ49*AK49, 0) | AO49: =IFERROR(AM49*AN49, 0) | AR49: =IFERROR(AP49*AQ49, 0) | AU49: =IFERROR(AS49*AT49, 0) | AV49: 44 | AW49: 7700 | AX49: 338800 | BA49: =IFERROR(AY49*AZ49, 0) | BD49: =IFERROR(BB49*BC49, 0) | BG49: =IFERROR(BE49*BF49, 0) | BJ49: =IFERROR(BH49*BI49, 0) | BM49: =IFERROR(BK49*BL49, 0) | BP49: =IFERROR(BN49*BO49, 0) | BS49: =IFERROR(BQ49*BR49, 0) | BT49: 37 | BU49: 7700 | BV49: 284900 | BY49: =IFERROR(BW49*BX49, 0) | CB49: =IFERROR(BZ49*CA49, 0) | CE49: =IFERROR(CC49*CD49, 0) | CH49: =IFERROR(CF49*CG49, 0) | CK49: =IFERROR(CI49*CJ49, 0) | CN49: =IFERROR(CL49*CM49, 0) | CQ49: =IFERROR(CO49*CP49, 0) | CT49: =IFERROR(CR49*CS49, 0) | CU49: =IFERROR(SUM(F49,I49,L49,O49,R49,U49,X49,AA49,AD49,AG49,AJ49,AM49,AP49,AS49,AV49,AY49,BB49,BE49,BH49,BK49,BN49,BQ49,BT49,BW49,BZ49,CC49,CF49,CI49,CL49,CO49,CR49), 0) | CV49: =IFERROR(AVERAGE(G49,J49,M49,P49,S49,V49,Y49,AB49,AE49,AH49,AK49,AN49,AQ49,AT49,AW49,AZ49,BC49,BF49,BI49,BL49,BO49,BR49,BU49,BX49,CA49,CD49,CG49,CJ49,CM49,CP49,CS49), 0) | CW49: =CU49*CV49
A50: Pescado bagre | B50: Kg | E50: 0 | H50: =IFERROR(F50*G50, 0) | K50: =IFERROR(I50*J50, 0) | N50: =IFERROR(L50*M50, 0) | Q50: =IFERROR(O50*P50, 0) | T50: =IFERROR(R50*S50, 0) | W50: =IFERROR(U50*V50, 0) | Z50: =IFERROR(X50*Y50, 0) | AC50: =IFERROR(AA50*AB50, 0) | AF50: =IFERROR(AD50*AE50, 0) | AI50: =IFERROR(AG50*AH50, 0) | AL50: =IFERROR(AJ50*AK50, 0) | AO50: =IFERROR(AM50*AN50, 0) | AR50: =IFERROR(AP50*AQ50, 0) | AU50: =IFERROR(AS50*AT50, 0) | AX50: =IFERROR(AV50*AW50, 0) | BA50: =IFERROR(AY50*AZ50, 0) | BD50: =IFERROR(BB50*BC50, 0) | BG50: =IFERROR(BE50*BF50, 0) | BJ50: =IFERROR(BH50*BI50, 0) | BM50: =IFERROR(BK50*BL50, 0) | BP50: =IFERROR(BN50*BO50, 0) | BS50: =IFERROR(BQ50*BR50, 0) | BV50: =IFERROR(BT50*BU50, 0) | BY50: =IFERROR(BW50*BX50, 0) | CB50: =IFERROR(BZ50*CA50, 0) | CE50: =IFERROR(CC50*CD50, 0) | CH50: =IFERROR(CF50*CG50, 0) | CK50: =IFERROR(CI50*CJ50, 0) | CN50: =IFERROR(CL50*CM50, 0) | CQ50: =IFERROR(CO50*CP50, 0) | CT50: =IFERROR(CR50*CS50, 0) | CU50: =IFERROR(SUM(F50,I50,L50,O50,R50,U50,X50,AA50,AD50,AG50,AJ50,AM50,AP50,AS50,AV50,AY50,BB50,BE50,BH50,BK50,BN50,BQ50,BT50,BW50,BZ50,CC50,CF50,CI50,CL50,CO50,CR50), 0) | CV50: =IFERROR(AVERAGE(G50,J50,M50,P50,S50,V50,Y50,AB50,AE50,AH50,AK50,AN50,AQ50,AT50,AW50,AZ50,BC50,BF50,BI50,BL50,BO50,BR50,BU50,BX50,CA50,CD50,CG50,CJ50,CM50,CP50,CS50), 0) | CW50: =CU50*CV50
A51: Pezuña | B51: Kg | E51: 0 | H51: =IFERROR(F51*G51, 0) | K51: =IFERROR(I51*J51, 0) | N51: =IFERROR(L51*M51, 0) | Q51: =IFERROR(O51*P51, 0) | R51: 8.044 | S51: 9699 | T51: 78027 | W51: =IFERROR(U51*V51, 0) | Z51: =IFERROR(X51*Y51, 0) | AA51: 6.065 | AB51: 9700 | AC51: 58831 | AF51: =IFERROR(AD51*AE51, 0) | AI51: =IFERROR(AG51*AH51, 0) | AL51: =IFERROR(AJ51*AK51, 0) | AM51: 11.812 | AN51: 9700 | AO51: 114577 | AR51: =IFERROR(AP51*AQ51, 0) | AU51: =IFERROR(AS51*AT51, 0) | AX51: =IFERROR(AV51*AW51, 0) | BA51: =IFERROR(AY51*AZ51, 0) | BD51: =IFERROR(BB51*BC51, 0) | BG51: =IFERROR(BE51*BF51, 0) | BJ51: =IFERROR(BH51*BI51, 0) | BM51: =IFERROR(BK51*BL51, 0) | BP51: =IFERROR(BN51*BO51, 0) | BS51: =IFERROR(BQ51*BR51, 0) | BV51: =IFERROR(BT51*BU51, 0) | BW51: 8.972 | BX51: 9700 | BY51: 87028 | CB51: =IFERROR(BZ51*CA51, 0) | CE51: =IFERROR(CC51*CD51, 0) | CH51: =IFERROR(CF51*CG51, 0) | CK51: =IFERROR(CI51*CJ51, 0) | CN51: =IFERROR(CL51*CM51, 0) | CQ51: =IFERROR(CO51*CP51, 0) | CT51: =IFERROR(CR51*CS51, 0) | CU51: =IFERROR(SUM(F51,I51,L51,O51,R51,U51,X51,AA51,AD51,AG51,AJ51,AM51,AP51,AS51,AV51,AY51,BB51,BE51,BH51,BK51,BN51,BQ51,BT51,BW51,BZ51,CC51,CF51,CI51,CL51,CO51,CR51), 0) | CV51: =IFERROR(AVERAGE(G51,J51,M51,P51,S51,V51,Y51,AB51,AE51,AH51,AK51,AN51,AQ51,AT51,AW51,AZ51,BC51,BF51,BI51,BL51,BO51,BR51,BU51,BX51,CA51,CD51,CG51,CJ51,CM51,CP51,CS51), 0) | CW51: =CU51*CV51
A52: Punta de anca | B52: Kg | E52: 0 | H52: =IFERROR(F52*G52, 0) | K52: =IFERROR(I52*J52, 0) | N52: =IFERROR(L52*M52, 0) | Q52: =IFERROR(O52*P52, 0) | T52: =IFERROR(R52*S52, 0) | W52: =IFERROR(U52*V52, 0) | Z52: =IFERROR(X52*Y52, 0) | AC52: =IFERROR(AA52*AB52, 0) | AF52: =IFERROR(AD52*AE52, 0) | AG52: 15.5 | AH52: 44000 | AI52: 682000 | AL52: =IFERROR(AJ52*AK52, 0) | AO52: =IFERROR(AM52*AN52, 0) | AR52: =IFERROR(AP52*AQ52, 0) | AU52: =IFERROR(AS52*AT52, 0) | AX52: =IFERROR(AV52*AW52, 0) | BA52: =IFERROR(AY52*AZ52, 0) | BB52: 32.5 | BC52: 44000 | BD52: 1430000 | BG52: =IFERROR(BE52*BF52, 0) | BJ52: =IFERROR(BH52*BI52, 0) | BM52: =IFERROR(BK52*BL52, 0) | BP52: =IFERROR(BN52*BO52, 0) | BS52: =IFERROR(BQ52*BR52, 0) | BT52: 6.355 | BU52: 57900 | BV52: 367955 | BY52: =IFERROR(BW52*BX52, 0) | CB52: =IFERROR(BZ52*CA52, 0) | CE52: =IFERROR(CC52*CD52, 0) | CH52: =IFERROR(CF52*CG52, 0) | CK52: =IFERROR(CI52*CJ52, 0) | CN52: =IFERROR(CL52*CM52, 0) | CQ52: =IFERROR(CO52*CP52, 0) | CT52: =IFERROR(CR52*CS52, 0) | CU52: =IFERROR(SUM(F52,I52,L52,O52,R52,U52,X52,AA52,AD52,AG52,AJ52,AM52,AP52,AS52,AV52,AY52,BB52,BE52,BH52,BK52,BN52,BQ52,BT52,BW52,BZ52,CC52,CF52,CI52,CL52,CO52,CR52), 0) | CV52: =IFERROR(AVERAGE(G52,J52,M52,P52,S52,V52,Y52,AB52,AE52,AH52,AK52,AN52,AQ52,AT52,AW52,AZ52,BC52,BF52,BI52,BL52,BO52,BR52,BU52,BX52,CA52,CD52,CG52,CJ52,CM52,CP52,CS52), 0) | CW52: =CU52*CV52
A53: Rellena | B53: Kg | E53: 0 | H53: =IFERROR(F53*G53, 0) | K53: =IFERROR(I53*J53, 0) | N53: =IFERROR(L53*M53, 0) | Q53: =IFERROR(O53*P53, 0) | T53: =IFERROR(R53*S53, 0) | W53: =IFERROR(U53*V53, 0) | Z53: =IFERROR(X53*Y53, 0) | AC53: =IFERROR(AA53*AB53, 0) | AF53: =IFERROR(AD53*AE53, 0) | AI53: =IFERROR(AG53*AH53, 0) | AL53: =IFERROR(AJ53*AK53, 0) | AO53: =IFERROR(AM53*AN53, 0) | AR53: =IFERROR(AP53*AQ53, 0) | AU53: =IFERROR(AS53*AT53, 0) | AX53: =IFERROR(AV53*AW53, 0) | BA53: =IFERROR(AY53*AZ53, 0) | BD53: =IFERROR(BB53*BC53, 0) | BE53: 3 | BF53: 20000 | BG53: 60000 | BJ53: =IFERROR(BH53*BI53, 0) | BM53: =IFERROR(BK53*BL53, 0) | BP53: =IFERROR(BN53*BO53, 0) | BS53: =IFERROR(BQ53*BR53, 0) | BV53: =IFERROR(BT53*BU53, 0) | BY53: =IFERROR(BW53*BX53, 0) | CB53: =IFERROR(BZ53*CA53, 0) | CE53: =IFERROR(CC53*CD53, 0) | CH53: =IFERROR(CF53*CG53, 0) | CK53: =IFERROR(CI53*CJ53, 0) | CN53: =IFERROR(CL53*CM53, 0) | CQ53: =IFERROR(CO53*CP53, 0) | CT53: =IFERROR(CR53*CS53, 0) | CU53: =IFERROR(SUM(F53,I53,L53,O53,R53,U53,X53,AA53,AD53,AG53,AJ53,AM53,AP53,AS53,AV53,AY53,BB53,BE53,BH53,BK53,BN53,BQ53,BT53,BW53,BZ53,CC53,CF53,CI53,CL53,CO53,CR53), 0) | CV53: =IFERROR(AVERAGE(G53,J53,M53,P53,S53,V53,Y53,AB53,AE53,AH53,AK53,AN53,AQ53,AT53,AW53,AZ53,BC53,BF53,BI53,BL53,BO53,BR53,BU53,BX53,CA53,CD53,CG53,CJ53,CM53,CP53,CS53), 0) | CW53: =CU53*CV53
A54: Salchicha | B54: Kg | E54: 0 | H54: =IFERROR(F54*G54, 0) | K54: =IFERROR(I54*J54, 0) | N54: =IFERROR(L54*M54, 0) | Q54: =IFERROR(O54*P54, 0) | T54: =IFERROR(R54*S54, 0) | W54: =IFERROR(U54*V54, 0) | Z54: =IFERROR(X54*Y54, 0) | AC54: =IFERROR(AA54*AB54, 0) | AF54: =IFERROR(AD54*AE54, 0) | AI54: =IFERROR(AG54*AH54, 0) | AL54: =IFERROR(AJ54*AK54, 0) | AO54: =IFERROR(AM54*AN54, 0) | AR54: =IFERROR(AP54*AQ54, 0) | AU54: =IFERROR(AS54*AT54, 0) | AX54: =IFERROR(AV54*AW54, 0) | BA54: =IFERROR(AY54*AZ54, 0) | BD54: =IFERROR(BB54*BC54, 0) | BG54: =IFERROR(BE54*BF54, 0) | BJ54: =IFERROR(BH54*BI54, 0) | BM54: =IFERROR(BK54*BL54, 0) | BP54: =IFERROR(BN54*BO54, 0) | BS54: =IFERROR(BQ54*BR54, 0) | BV54: =IFERROR(BT54*BU54, 0) | BY54: =IFERROR(BW54*BX54, 0) | CB54: =IFERROR(BZ54*CA54, 0) | CE54: =IFERROR(CC54*CD54, 0) | CH54: =IFERROR(CF54*CG54, 0) | CK54: =IFERROR(CI54*CJ54, 0) | CN54: =IFERROR(CL54*CM54, 0) | CQ54: =IFERROR(CO54*CP54, 0) | CT54: =IFERROR(CR54*CS54, 0) | CU54: =IFERROR(SUM(F54,I54,L54,O54,R54,U54,X54,AA54,AD54,AG54,AJ54,AM54,AP54,AS54,AV54,AY54,BB54,BE54,BH54,BK54,BN54,BQ54,BT54,BW54,BZ54,CC54,CF54,CI54,CL54,CO54,CR54), 0) | CV54: =IFERROR(AVERAGE(G54,J54,M54,P54,S54,V54,Y54,AB54,AE54,AH54,AK54,AN54,AQ54,AT54,AW54,AZ54,BC54,BF54,BI54,BL54,BO54,BR54,BU54,BX54,CA54,CD54,CG54,CJ54,CM54,CP54,CS54), 0) | CW54: =CU54*CV54
A55: Salmon | B55: Kg | E55: 0 | H55: =IFERROR(F55*G55, 0) | K55: =IFERROR(I55*J55, 0) | N55: =IFERROR(L55*M55, 0) | Q55: =IFERROR(O55*P55, 0) | T55: =IFERROR(R55*S55, 0) | W55: =IFERROR(U55*V55, 0) | Z55: =IFERROR(X55*Y55, 0) | AC55: =IFERROR(AA55*AB55, 0) | AD55: 55 | AE55: 7250 | AF55: 398750 | AI55: =IFERROR(AG55*AH55, 0) | AL55: =IFERROR(AJ55*AK55, 0) | AO55: =IFERROR(AM55*AN55, 0) | AR55: =IFERROR(AP55*AQ55, 0) | AU55: =IFERROR(AS55*AT55, 0) | AX55: =IFERROR(AV55*AW55, 0) | BA55: =IFERROR(AY55*AZ55, 0) | BD55: =IFERROR(BB55*BC55, 0) | BG55: =IFERROR(BE55*BF55, 0) | BJ55: =IFERROR(BH55*BI55, 0) | BM55: =IFERROR(BK55*BL55, 0) | BP55: =IFERROR(BN55*BO55, 0) | BS55: =IFERROR(BQ55*BR55, 0) | BV55: =IFERROR(BT55*BU55, 0) | BY55: =IFERROR(BW55*BX55, 0) | CB55: =IFERROR(BZ55*CA55, 0) | CE55: =IFERROR(CC55*CD55, 0) | CH55: =IFERROR(CF55*CG55, 0) | CK55: =IFERROR(CI55*CJ55, 0) | CN55: =IFERROR(CL55*CM55, 0) | CQ55: =IFERROR(CO55*CP55, 0) | CT55: =IFERROR(CR55*CS55, 0) | CU55: =IFERROR(SUM(F55,I55,L55,O55,R55,U55,X55,AA55,AD55,AG55,AJ55,AM55,AP55,AS55,AV55,AY55,BB55,BE55,BH55,BK55,BN55,BQ55,BT55,BW55,BZ55,CC55,CF55,CI55,CL55,CO55,CR55), 0) | CV55: =IFERROR(AVERAGE(G55,J55,M55,P55,S55,V55,Y55,AB55,AE55,AH55,AK55,AN55,AQ55,AT55,AW55,AZ55,BC55,BF55,BI55,BL55,BO55,BR55,BU55,BX55,CA55,CD55,CG55,CJ55,CM55,CP55,CS55), 0) | CW55: =CU55*CV55
A56: Sobaco | B56: Kg | E56: 0 | H56: =IFERROR(F56*G56, 0) | I56: 21.71 | J56: 25900 | K56: 562289 | N56: =IFERROR(L56*M56, 0) | Q56: =IFERROR(O56*P56, 0) | T56: =IFERROR(R56*S56, 0) | W56: =IFERROR(U56*V56, 0) | Z56: =IFERROR(X56*Y56, 0) | AC56: =IFERROR(AA56*AB56, 0) | AD56: 18.1 | AE56: 25900 | AF56: 468790 | AI56: =IFERROR(AG56*AH56, 0) | AL56: =IFERROR(AJ56*AK56, 0) | AO56: =IFERROR(AM56*AN56, 0) | AR56: =IFERROR(AP56*AQ56, 0) | AU56: =IFERROR(AS56*AT56, 0) | AX56: =IFERROR(AV56*AW56, 0) | BA56: =IFERROR(AY56*AZ56, 0) | BD56: =IFERROR(BB56*BC56, 0) | BG56: =IFERROR(BE56*BF56, 0) | BJ56: =IFERROR(BH56*BI56, 0) | BM56: =IFERROR(BK56*BL56, 0) | BP56: =IFERROR(BN56*BO56, 0) | BS56: =IFERROR(BQ56*BR56, 0) | BV56: =IFERROR(BT56*BU56, 0) | BY56: =IFERROR(BW56*BX56, 0) | CB56: =IFERROR(BZ56*CA56, 0) | CE56: =IFERROR(CC56*CD56, 0) | CH56: =IFERROR(CF56*CG56, 0) | CK56: =IFERROR(CI56*CJ56, 0) | CN56: =IFERROR(CL56*CM56, 0) | CQ56: =IFERROR(CO56*CP56, 0) | CT56: =IFERROR(CR56*CS56, 0) | CU56: =IFERROR(SUM(F56,I56,L56,O56,R56,U56,X56,AA56,AD56,AG56,AJ56,AM56,AP56,AS56,AV56,AY56,BB56,BE56,BH56,BK56,BN56,BQ56,BT56,BW56,BZ56,CC56,CF56,CI56,CL56,CO56,CR56), 0) | CV56: =IFERROR(AVERAGE(G56,J56,M56,P56,S56,V56,Y56,AB56,AE56,AH56,AK56,AN56,AQ56,AT56,AW56,AZ56,BC56,BF56,BI56,BL56,BO56,BR56,BU56,BX56,CA56,CD56,CG56,CJ56,CM56,CP56,CS56), 0) | CW56: =CU56*CV56
A57: Sobrebarriga delgada | B57: Kg | E57: 0 | F57: 9.27 | G57: 30500 | H57: 282735 | I57: 22.8 | J57: 34500 | K57: 786600 | N57: =IFERROR(L57*M57, 0) | Q57: =IFERROR(O57*P57, 0) | T57: =IFERROR(R57*S57, 0) | W57: =IFERROR(U57*V57, 0) | X57: 21.8 | Y57: 34500 | Z57: 752100 | AC57: =IFERROR(AA57*AB57, 0) | AF57: =IFERROR(AD57*AE57, 0) | AI57: =IFERROR(AG57*AH57, 0) | AL57: =IFERROR(AJ57*AK57, 0) | AO57: =IFERROR(AM57*AN57, 0) | AR57: =IFERROR(AP57*AQ57, 0) | AU57: =IFERROR(AS57*AT57, 0) | AX57: =IFERROR(AV57*AW57, 0) | BA57: =IFERROR(AY57*AZ57, 0) | BB57: 30.6 | BC57: 34500 | BD57: 1055700 | BG57: =IFERROR(BE57*BF57, 0) | BJ57: =IFERROR(BH57*BI57, 0) | BM57: =IFERROR(BK57*BL57, 0) | BN57: 10 | BO57: 30000 | BP57: 300000 | BS57: =IFERROR(BQ57*BR57, 0) | BT57: 17.05 | BU57: 34500 | BV57: 588225 | BY57: =IFERROR(BW57*BX57, 0) | CB57: =IFERROR(BZ57*CA57, 0) | CE57: =IFERROR(CC57*CD57, 0) | CH57: =IFERROR(CF57*CG57, 0) | CK57: =IFERROR(CI57*CJ57, 0) | CN57: =IFERROR(CL57*CM57, 0) | CQ57: =IFERROR(CO57*CP57, 0) | CT57: =IFERROR(CR57*CS57, 0) | CU57: =IFERROR(SUM(F57,I57,L57,O57,R57,U57,X57,AA57,AD57,AG57,AJ57,AM57,AP57,AS57,AV57,AY57,BB57,BE57,BH57,BK57,BN57,BQ57,BT57,BW57,BZ57,CC57,CF57,CI57,CL57,CO57,CR57), 0) | CV57: =IFERROR(AVERAGE(G57,J57,M57,P57,S57,V57,Y57,AB57,AE57,AH57,AK57,AN57,AQ57,AT57,AW57,AZ57,BC57,BF57,BI57,BL57,BO57,BR57,BU57,BX57,CA57,CD57,CG57,CJ57,CM57,CP57,CS57), 0) | CW57: =CU57*CV57
A58: Tamal | B58: Und | E58: 0 | H58: =IFERROR(F58*G58, 0) | K58: =IFERROR(I58*J58, 0) | N58: =IFERROR(L58*M58, 0) | Q58: =IFERROR(O58*P58, 0) | T58: =IFERROR(R58*S58, 0) | W58: =IFERROR(U58*V58, 0) | Z58: =IFERROR(X58*Y58, 0) | AC58: =IFERROR(AA58*AB58, 0) | AF58: =IFERROR(AD58*AE58, 0) | AI58: =IFERROR(AG58*AH58, 0) | AL58: =IFERROR(AJ58*AK58, 0) | AO58: =IFERROR(AM58*AN58, 0) | AR58: =IFERROR(AP58*AQ58, 0) | AU58: =IFERROR(AS58*AT58, 0) | AX58: =IFERROR(AV58*AW58, 0) | BA58: =IFERROR(AY58*AZ58, 0) | BD58: =IFERROR(BB58*BC58, 0) | BG58: =IFERROR(BE58*BF58, 0) | BJ58: =IFERROR(BH58*BI58, 0) | BM58: =IFERROR(BK58*BL58, 0) | BP58: =IFERROR(BN58*BO58, 0) | BS58: =IFERROR(BQ58*BR58, 0) | BV58: =IFERROR(BT58*BU58, 0) | BY58: =IFERROR(BW58*BX58, 0) | CB58: =IFERROR(BZ58*CA58, 0) | CE58: =IFERROR(CC58*CD58, 0) | CH58: =IFERROR(CF58*CG58, 0) | CK58: =IFERROR(CI58*CJ58, 0) | CN58: =IFERROR(CL58*CM58, 0) | CQ58: =IFERROR(CO58*CP58, 0) | CT58: =IFERROR(CR58*CS58, 0) | CU58: =IFERROR(SUM(F58,I58,L58,O58,R58,U58,X58,AA58,AD58,AG58,AJ58,AM58,AP58,AS58,AV58,AY58,BB58,BE58,BH58,BK58,BN58,BQ58,BT58,BW58,BZ58,CC58,CF58,CI58,CL58,CO58,CR58), 0) | CV58: =IFERROR(AVERAGE(G58,J58,M58,P58,S58,V58,Y58,AB58,AE58,AH58,AK58,AN58,AQ58,AT58,AW58,AZ58,BC58,BF58,BI58,BL58,BO58,BR58,BU58,BX58,CA58,CD58,CG58,CJ58,CM58,CP58,CS58), 0) | CW58: =CU58*CV58
A59: Tilapia 350/450 | B59: Kg | E59: 0 | H59: =IFERROR(F59*G59, 0) | K59: =IFERROR(I59*J59, 0) | N59: =IFERROR(L59*M59, 0) | Q59: =IFERROR(O59*P59, 0) | T59: =IFERROR(R59*S59, 0) | W59: =IFERROR(U59*V59, 0) | Z59: =IFERROR(X59*Y59, 0) | AC59: =IFERROR(AA59*AB59, 0) | AF59: =IFERROR(AD59*AE59, 0) | AI59: =IFERROR(AG59*AH59, 0) | AL59: =IFERROR(AJ59*AK59, 0) | AO59: =IFERROR(AM59*AN59, 0) | AR59: =IFERROR(AP59*AQ59, 0) | AU59: =IFERROR(AS59*AT59, 0) | AX59: =IFERROR(AV59*AW59, 0) | BA59: =IFERROR(AY59*AZ59, 0) | BD59: =IFERROR(BB59*BC59, 0) | BG59: =IFERROR(BE59*BF59, 0) | BJ59: =IFERROR(BH59*BI59, 0) | BM59: =IFERROR(BK59*BL59, 0) | BP59: =IFERROR(BN59*BO59, 0) | BS59: =IFERROR(BQ59*BR59, 0) | BV59: =IFERROR(BT59*BU59, 0) | BY59: =IFERROR(BW59*BX59, 0) | CB59: =IFERROR(BZ59*CA59, 0) | CE59: =IFERROR(CC59*CD59, 0) | CH59: =IFERROR(CF59*CG59, 0) | CK59: =IFERROR(CI59*CJ59, 0) | CN59: =IFERROR(CL59*CM59, 0) | CQ59: =IFERROR(CO59*CP59, 0) | CT59: =IFERROR(CR59*CS59, 0) | CU59: =IFERROR(SUM(F59,I59,L59,O59,R59,U59,X59,AA59,AD59,AG59,AJ59,AM59,AP59,AS59,AV59,AY59,BB59,BE59,BH59,BK59,BN59,BQ59,BT59,BW59,BZ59,CC59,CF59,CI59,CL59,CO59,CR59), 0) | CV59: =IFERROR(AVERAGE(G59,J59,M59,P59,S59,V59,Y59,AB59,AE59,AH59,AK59,AN59,AQ59,AT59,AW59,AZ59,BC59,BF59,BI59,BL59,BO59,BR59,BU59,BX59,CA59,CD59,CG59,CJ59,CM59,CP59,CS59), 0) | CW59: =CU59*CV59
A60: Tilapia x 300 | B60: Kg | E60: 0 | H60: =IFERROR(F60*G60, 0) | K60: =IFERROR(I60*J60, 0) | N60: =IFERROR(L60*M60, 0) | Q60: =IFERROR(O60*P60, 0) | T60: =IFERROR(R60*S60, 0) | W60: =IFERROR(U60*V60, 0) | Z60: =IFERROR(X60*Y60, 0) | AC60: =IFERROR(AA60*AB60, 0) | AF60: =IFERROR(AD60*AE60, 0) | AI60: =IFERROR(AG60*AH60, 0) | AL60: =IFERROR(AJ60*AK60, 0) | AO60: =IFERROR(AM60*AN60, 0) | AR60: =IFERROR(AP60*AQ60, 0) | AU60: =IFERROR(AS60*AT60, 0) | AX60: =IFERROR(AV60*AW60, 0) | BA60: =IFERROR(AY60*AZ60, 0) | BD60: =IFERROR(BB60*BC60, 0) | BG60: =IFERROR(BE60*BF60, 0) | BJ60: =IFERROR(BH60*BI60, 0) | BM60: =IFERROR(BK60*BL60, 0) | BP60: =IFERROR(BN60*BO60, 0) | BS60: =IFERROR(BQ60*BR60, 0) | BV60: =IFERROR(BT60*BU60, 0) | BY60: =IFERROR(BW60*BX60, 0) | CB60: =IFERROR(BZ60*CA60, 0) | CE60: =IFERROR(CC60*CD60, 0) | CH60: =IFERROR(CF60*CG60, 0) | CK60: =IFERROR(CI60*CJ60, 0) | CN60: =IFERROR(CL60*CM60, 0) | CQ60: =IFERROR(CO60*CP60, 0) | CT60: =IFERROR(CR60*CS60, 0) | CU60: =IFERROR(SUM(F60,I60,L60,O60,R60,U60,X60,AA60,AD60,AG60,AJ60,AM60,AP60,AS60,AV60,AY60,BB60,BE60,BH60,BK60,BN60,BQ60,BT60,BW60,BZ60,CC60,CF60,CI60,CL60,CO60,CR60), 0) | CV60: =IFERROR(AVERAGE(G60,J60,M60,P60,S60,V60,Y60,AB60,AE60,AH60,AK60,AN60,AQ60,AT60,AW60,AZ60,BC60,BF60,BI60,BL60,BO60,BR60,BU60,BX60,CA60,CD60,CG60,CJ60,CM60,CP60,CS60), 0) | CW60: =CU60*CV60
A61: Tocineta barril | B61: Kg | E61: 0 | H61: =IFERROR(F61*G61, 0) | I61: 66.65 | J61: 21900 | K61: 1459635 | N61: =IFERROR(L61*M61, 0) | O61: 61.65 | P61: 21900 | Q61: 1350135 | T61: =IFERROR(R61*S61, 0) | W61: =IFERROR(U61*V61, 0) | X61: 62.7 | Y61: 21900 | Z61: 1373130 | AC61: =IFERROR(AA61*AB61, 0) | AF61: =IFERROR(AD61*AE61, 0) | AG61: 151.95 | AH61: 21900 | AI61: 3327705 | AL61: =IFERROR(AJ61*AK61, 0) | AO61: =IFERROR(AM61*AN61, 0) | AR61: =IFERROR(AP61*AQ61, 0) | AU61: =IFERROR(AS61*AT61, 0) | AV61: 48.7 | AW61: 21900 | AX61: 1066530 | BA61: =IFERROR(AY61*AZ61, 0) | BB61: 106.45 | BC61: 21900 | BD61: 2331255 | BG61: =IFERROR(BE61*BF61, 0) | BJ61: =IFERROR(BH61*BI61, 0) | BM61: =IFERROR(BK61*BL61, 0) | BP61: =IFERROR(BN61*BO61, 0) | BS61: =IFERROR(BQ61*BR61, 0) | BT61: 64.1 | BU61: 21900 | BV61: 1403790 | BY61: =IFERROR(BW61*BX61, 0) | CB61: =IFERROR(BZ61*CA61, 0) | CE61: =IFERROR(CC61*CD61, 0) | CH61: =IFERROR(CF61*CG61, 0) | CK61: =IFERROR(CI61*CJ61, 0) | CN61: =IFERROR(CL61*CM61, 0) | CQ61: =IFERROR(CO61*CP61, 0) | CT61: =IFERROR(CR61*CS61, 0) | CU61: =IFERROR(SUM(F61,I61,L61,O61,R61,U61,X61,AA61,AD61,AG61,AJ61,AM61,AP61,AS61,AV61,AY61,BB61,BE61,BH61,BK61,BN61,BQ61,BT61,BW61,BZ61,CC61,CF61,CI61,CL61,CO61,CR61), 0) | CV61: =IFERROR(AVERAGE(G61,J61,M61,P61,S61,V61,Y61,AB61,AE61,AH61,AK61,AN61,AQ61,AT61,AW61,AZ61,BC61,BF61,BI61,BL61,BO61,BR61,BU61,BX61,CA61,CD61,CG61,CJ61,CM61,CP61,CS61), 0) | CW61: =CU61*CV61
A62: Tocineta premium | B62: Kg | E62: 0 | H62: =IFERROR(F62*G62, 0) | K62: =IFERROR(I62*J62, 0) | N62: =IFERROR(L62*M62, 0) | Q62: =IFERROR(O62*P62, 0) | T62: =IFERROR(R62*S62, 0) | W62: =IFERROR(U62*V62, 0) | Z62: =IFERROR(X62*Y62, 0) | AC62: =IFERROR(AA62*AB62, 0) | AF62: =IFERROR(AD62*AE62, 0) | AI62: =IFERROR(AG62*AH62, 0) | AL62: =IFERROR(AJ62*AK62, 0) | AO62: =IFERROR(AM62*AN62, 0) | AR62: =IFERROR(AP62*AQ62, 0) | AU62: =IFERROR(AS62*AT62, 0) | AX62: =IFERROR(AV62*AW62, 0) | BA62: =IFERROR(AY62*AZ62, 0) | BD62: =IFERROR(BB62*BC62, 0) | BG62: =IFERROR(BE62*BF62, 0) | BJ62: =IFERROR(BH62*BI62, 0) | BM62: =IFERROR(BK62*BL62, 0) | BP62: =IFERROR(BN62*BO62, 0) | BS62: =IFERROR(BQ62*BR62, 0) | BV62: =IFERROR(BT62*BU62, 0) | BY62: =IFERROR(BW62*BX62, 0) | CB62: =IFERROR(BZ62*CA62, 0) | CE62: =IFERROR(CC62*CD62, 0) | CH62: =IFERROR(CF62*CG62, 0) | CK62: =IFERROR(CI62*CJ62, 0) | CN62: =IFERROR(CL62*CM62, 0) | CQ62: =IFERROR(CO62*CP62, 0) | CT62: =IFERROR(CR62*CS62, 0) | CU62: =IFERROR(SUM(F62,I62,L62,O62,R62,U62,X62,AA62,AD62,AG62,AJ62,AM62,AP62,AS62,AV62,AY62,BB62,BE62,BH62,BK62,BN62,BQ62,BT62,BW62,BZ62,CC62,CF62,CI62,CL62,CO62,CR62), 0) | CV62: =IFERROR(AVERAGE(G62,J62,M62,P62,S62,V62,Y62,AB62,AE62,AH62,AK62,AN62,AQ62,AT62,AW62,AZ62,BC62,BF62,BI62,BL62,BO62,BR62,BU62,BX62,CA62,CD62,CG62,CJ62,CM62,CP62,CS62), 0) | CW62: =CU62*CV62
A63: Trozos e pechuga | B63: Kg | E63: 0 | H63: =IFERROR(F63*G63, 0) | K63: =IFERROR(I63*J63, 0) | N63: =IFERROR(L63*M63, 0) | Q63: =IFERROR(O63*P63, 0) | T63: =IFERROR(R63*S63, 0) | W63: =IFERROR(U63*V63, 0) | X63: 18.26 | Y63: 11500 | Z63: 209990 | AC63: =IFERROR(AA63*AB63, 0) | AF63: =IFERROR(AD63*AE63, 0) | AI63: =IFERROR(AG63*AH63, 0) | AL63: =IFERROR(AJ63*AK63, 0) | AO63: =IFERROR(AM63*AN63, 0) | AR63: =IFERROR(AP63*AQ63, 0) | AU63: =IFERROR(AS63*AT63, 0) | AV63: 18.26 | AW63: 11500 | AX63: 209990 | BA63: =IFERROR(AY63*AZ63, 0) | BD63: =IFERROR(BB63*BC63, 0) | BG63: =IFERROR(BE63*BF63, 0) | BJ63: =IFERROR(BH63*BI63, 0) | BM63: =IFERROR(BK63*BL63, 0) | BP63: =IFERROR(BN63*BO63, 0) | BS63: =IFERROR(BQ63*BR63, 0) | BV63: =IFERROR(BT63*BU63, 0) | BY63: =IFERROR(BW63*BX63, 0) | CB63: =IFERROR(BZ63*CA63, 0) | CE63: =IFERROR(CC63*CD63, 0) | CH63: =IFERROR(CF63*CG63, 0) | CK63: =IFERROR(CI63*CJ63, 0) | CN63: =IFERROR(CL63*CM63, 0) | CQ63: =IFERROR(CO63*CP63, 0) | CT63: =IFERROR(CR63*CS63, 0) | CU63: =IFERROR(SUM(F63,I63,L63,O63,R63,U63,X63,AA63,AD63,AG63,AJ63,AM63,AP63,AS63,AV63,AY63,BB63,BE63,BH63,BK63,BN63,BQ63,BT63,BW63,BZ63,CC63,CF63,CI63,CL63,CO63,CR63), 0) | CV63: =IFERROR(AVERAGE(G63,J63,M63,P63,S63,V63,Y63,AB63,AE63,AH63,AK63,AN63,AQ63,AT63,AW63,AZ63,BC63,BF63,BI63,BL63,BO63,BR63,BU63,BX63,CA63,CD63,CG63,CJ63,CM63,CP63,CS63), 0) | CW63: =CU63*CV63
A64: Trucha | B64: Kg | E64: 0 | H64: =IFERROR(F64*G64, 0) | I64: 4.8 | J64: 22000 | K64: 105600 | N64: =IFERROR(L64*M64, 0) | Q64: =IFERROR(O64*P64, 0) | T64: =IFERROR(R64*S64, 0) | W64: =IFERROR(U64*V64, 0) | Z64: =IFERROR(X64*Y64, 0) | AA64: 4.5 | AB64: 22000 | AC64: 99000 | AD64: 6.2 | AE64: 22000 | AF64: 136400 | AI64: =IFERROR(AG64*AH64, 0) | AL64: =IFERROR(AJ64*AK64, 0) | AO64: =IFERROR(AM64*AN64, 0) | AR64: =IFERROR(AP64*AQ64, 0) | AU64: =IFERROR(AS64*AT64, 0) | AX64: =IFERROR(AV64*AW64, 0) | BA64: =IFERROR(AY64*AZ64, 0) | BD64: =IFERROR(BB64*BC64, 0) | BG64: =IFERROR(BE64*BF64, 0) | BJ64: =IFERROR(BH64*BI64, 0) | BM64: =IFERROR(BK64*BL64, 0) | BP64: =IFERROR(BN64*BO64, 0) | BS64: =IFERROR(BQ64*BR64, 0) | BV64: =IFERROR(BT64*BU64, 0) | BY64: =IFERROR(BW64*BX64, 0) | CB64: =IFERROR(BZ64*CA64, 0) | CE64: =IFERROR(CC64*CD64, 0) | CH64: =IFERROR(CF64*CG64, 0) | CK64: =IFERROR(CI64*CJ64, 0) | CN64: =IFERROR(CL64*CM64, 0) | CQ64: =IFERROR(CO64*CP64, 0) | CT64: =IFERROR(CR64*CS64, 0) | CU64: =IFERROR(SUM(F64,I64,L64,O64,R64,U64,X64,AA64,AD64,AG64,AJ64,AM64,AP64,AS64,AV64,AY64,BB64,BE64,BH64,BK64,BN64,BQ64,BT64,BW64,BZ64,CC64,CF64,CI64,CL64,CO64,CR64), 0) | CV64: =IFERROR(AVERAGE(G64,J64,M64,P64,S64,V64,Y64,AB64,AE64,AH64,AK64,AN64,AQ64,AT64,AW64,AZ64,BC64,BF64,BI64,BL64,BO64,BR64,BU64,BX64,CA64,CD64,CG64,CJ64,CM64,CP64,CS64), 0) | CW64: =CU64*CV64
A65: Visceras | B65: Kg | E65: 0 | H65: =IFERROR(F65*G65, 0) | K65: =IFERROR(I65*J65, 0) | N65: =IFERROR(L65*M65, 0) | Q65: =IFERROR(O65*P65, 0) | T65: =IFERROR(R65*S65, 0) | W65: =IFERROR(U65*V65, 0) | Z65: =IFERROR(X65*Y65, 0) | AC65: =IFERROR(AA65*AB65, 0) | AF65: =IFERROR(AD65*AE65, 0) | AI65: =IFERROR(AG65*AH65, 0) | AL65: =IFERROR(AJ65*AK65, 0) | AO65: =IFERROR(AM65*AN65, 0) | AR65: =IFERROR(AP65*AQ65, 0) | AU65: =IFERROR(AS65*AT65, 0) | AX65: =IFERROR(AV65*AW65, 0) | BA65: =IFERROR(AY65*AZ65, 0) | BD65: =IFERROR(BB65*BC65, 0) | BG65: =IFERROR(BE65*BF65, 0) | BJ65: =IFERROR(BH65*BI65, 0) | BM65: =IFERROR(BK65*BL65, 0) | BP65: =IFERROR(BN65*BO65, 0) | BS65: =IFERROR(BQ65*BR65, 0) | BV65: =IFERROR(BT65*BU65, 0) | BY65: =IFERROR(BW65*BX65, 0) | CB65: =IFERROR(BZ65*CA65, 0) | CE65: =IFERROR(CC65*CD65, 0) | CH65: =IFERROR(CF65*CG65, 0) | CK65: =IFERROR(CI65*CJ65, 0) | CN65: =IFERROR(CL65*CM65, 0) | CQ65: =IFERROR(CO65*CP65, 0) | CT65: =IFERROR(CR65*CS65, 0) | CU65: =IFERROR(SUM(F65,I65,L65,O65,R65,U65,X65,AA65,AD65,AG65,AJ65,AM65,AP65,AS65,AV65,AY65,BB65,BE65,BH65,BK65,BN65,BQ65,BT65,BW65,BZ65,CC65,CF65,CI65,CL65,CO65,CR65), 0) | CV65: =IFERROR(AVERAGE(G65,J65,M65,P65,S65,V65,Y65,AB65,AE65,AH65,AK65,AN65,AQ65,AT65,AW65,AZ65,BC65,BF65,BI65,BL65,BO65,BR65,BU65,BX65,CA65,CD65,CG65,CJ65,CM65,CP65,CS65), 0) | CW65: =CU65*CV65
A66: Costilla Especial | B66: Kg | E66: 0 | H66: =IFERROR(F66*G66, 0) | K66: =IFERROR(I66*J66, 0) | N66: =IFERROR(L66*M66, 0) | Q66: =IFERROR(O66*P66, 0) | T66: =IFERROR(R66*S66, 0) | U66: 20 | V66: 19900 | W66: 398000 | Z66: =IFERROR(X66*Y66, 0) | AC66: =IFERROR(AA66*AB66, 0) | AD66: 21.15 | AE66: 20000 | AF66: 423000 | AI66: =IFERROR(AG66*AH66, 0) | AJ66: 40.85 | AK66: 19900 | AL66: 815000 | AO66: =IFERROR(AM66*AN66, 0) | AR66: =IFERROR(AP66*AQ66, 0) | AS66: 10 | AT66: 19900 | AU66: 199000 | AX66: =IFERROR(AV66*AW66, 0) | BA66: =IFERROR(AY66*AZ66, 0) | BD66: =IFERROR(BB66*BC66, 0) | BG66: =IFERROR(BE66*BF66, 0) | BJ66: =IFERROR(BH66*BI66, 0) | BM66: =IFERROR(BK66*BL66, 0) | BP66: =IFERROR(BN66*BO66, 0) | BS66: =IFERROR(BQ66*BR66, 0) | BV66: =IFERROR(BT66*BU66, 0) | BY66: =IFERROR(BW66*BX66, 0) | CB66: =IFERROR(BZ66*CA66, 0) | CE66: =IFERROR(CC66*CD66, 0) | CH66: =IFERROR(CF66*CG66, 0) | CK66: =IFERROR(CI66*CJ66, 0) | CN66: =IFERROR(CL66*CM66, 0) | CQ66: =IFERROR(CO66*CP66, 0) | CT66: =IFERROR(CR66*CS66, 0) | CU66: =IFERROR(SUM(F66,I66,L66,O66,R66,U66,X66,AA66,AD66,AG66,AJ66,AM66,AP66,AS66,AV66,AY66,BB66,BE66,BH66,BK66,BN66,BQ66,BT66,BW66,BZ66,CC66,CF66,CI66,CL66,CO66,CR66), 0) | CV66: =IFERROR(AVERAGE(G66,J66,M66,P66,S66,V66,Y66,AB66,AE66,AH66,AK66,AN66,AQ66,AT66,AW66,AZ66,BC66,BF66,BI66,BL66,BO66,BR66,BU66,BX66,CA66,CD66,CG66,CJ66,CM66,CP66,CS66), 0) | CW66: =CU66*CV66
A67: Gallina gigante | B67: Und | E67: 0 | H67: =IFERROR(F67*G67, 0) | K67: =IFERROR(I67*J67, 0) | N67: =IFERROR(L67*M67, 0) | Q67: =IFERROR(O67*P67, 0) | T67: =IFERROR(R67*S67, 0) | W67: =IFERROR(U67*V67, 0) | Z67: =IFERROR(X67*Y67, 0) | AC67: =IFERROR(AA67*AB67, 0) | AF67: =IFERROR(AD67*AE67, 0) | AI67: =IFERROR(AG67*AH67, 0) | AL67: =IFERROR(AJ67*AK67, 0) | AO67: =IFERROR(AM67*AN67, 0) | AR67: =IFERROR(AP67*AQ67, 0) | AU67: =IFERROR(AS67*AT67, 0) | AX67: =IFERROR(AV67*AW67, 0) | BA67: =IFERROR(AY67*AZ67, 0) | BD67: =IFERROR(BB67*BC67, 0) | BG67: =IFERROR(BE67*BF67, 0) | BJ67: =IFERROR(BH67*BI67, 0) | BM67: =IFERROR(BK67*BL67, 0) | BP67: =IFERROR(BN67*BO67, 0) | BS67: =IFERROR(BQ67*BR67, 0) | BV67: =IFERROR(BT67*BU67, 0) | BY67: =IFERROR(BW67*BX67, 0) | CB67: =IFERROR(BZ67*CA67, 0) | CE67: =IFERROR(CC67*CD67, 0) | CH67: =IFERROR(CF67*CG67, 0) | CK67: =IFERROR(CI67*CJ67, 0) | CN67: =IFERROR(CL67*CM67, 0) | CQ67: =IFERROR(CO67*CP67, 0) | CT67: =IFERROR(CR67*CS67, 0) | CU67: =IFERROR(SUM(F67,I67,L67,O67,R67,U67,X67,AA67,AD67,AG67,AJ67,AM67,AP67,AS67,AV67,AY67,BB67,BE67,BH67,BK67,BN67,BQ67,BT67,BW67,BZ67,CC67,CF67,CI67,CL67,CO67,CR67), 0) | CV67: =IFERROR(AVERAGE(G67,J67,M67,P67,S67,V67,Y67,AB67,AE67,AH67,AK67,AN67,AQ67,AT67,AW67,AZ67,BC67,BF67,BI67,BL67,BO67,BR67,BU67,BX67,CA67,CD67,CG67,CJ67,CM67,CP67,CS67), 0) | CW67: =CU67*CV67
A68: Salchicha ranchera | B68: Und | E68: 0 | H68: =IFERROR(F68*G68, 0) | K68: =IFERROR(I68*J68, 0) | N68: =IFERROR(L68*M68, 0) | Q68: =IFERROR(O68*P68, 0) | T68: =IFERROR(R68*S68, 0) | W68: =IFERROR(U68*V68, 0) | Z68: =IFERROR(X68*Y68, 0) | AC68: =IFERROR(AA68*AB68, 0) | AF68: =IFERROR(AD68*AE68, 0) | AI68: =IFERROR(AG68*AH68, 0) | AL68: =IFERROR(AJ68*AK68, 0) | AO68: =IFERROR(AM68*AN68, 0) | AR68: =IFERROR(AP68*AQ68, 0) | AU68: =IFERROR(AS68*AT68, 0) | AX68: =IFERROR(AV68*AW68, 0) | BA68: =IFERROR(AY68*AZ68, 0) | BD68: =IFERROR(BB68*BC68, 0) | BG68: =IFERROR(BE68*BF68, 0) | BJ68: =IFERROR(BH68*BI68, 0) | BM68: =IFERROR(BK68*BL68, 0) | BP68: =IFERROR(BN68*BO68, 0) | BS68: =IFERROR(BQ68*BR68, 0) | BV68: =IFERROR(BT68*BU68, 0) | BY68: =IFERROR(BW68*BX68, 0) | CB68: =IFERROR(BZ68*CA68, 0) | CE68: =IFERROR(CC68*CD68, 0) | CH68: =IFERROR(CF68*CG68, 0) | CK68: =IFERROR(CI68*CJ68, 0) | CN68: =IFERROR(CL68*CM68, 0) | CQ68: =IFERROR(CO68*CP68, 0) | CT68: =IFERROR(CR68*CS68, 0) | CU68: =IFERROR(SUM(F68,I68,L68,O68,R68,U68,X68,AA68,AD68,AG68,AJ68,AM68,AP68,AS68,AV68,AY68,BB68,BE68,BH68,BK68,BN68,BQ68,BT68,BW68,BZ68,CC68,CF68,CI68,CL68,CO68,CR68), 0) | CV68: =IFERROR(AVERAGE(G68,J68,M68,P68,S68,V68,Y68,AB68,AE68,AH68,AK68,AN68,AQ68,AT68,AW68,AZ68,BC68,BF68,BI68,BL68,BO68,BR68,BU68,BX68,CA68,CD68,CG68,CJ68,CM68,CP68,CS68), 0) | CW68: =CU68*CV68
A69: Pechuga mcpollo | B69: Und | E69: 0 | H69: =IFERROR(F69*G69, 0) | K69: =IFERROR(I69*J69, 0) | N69: =IFERROR(L69*M69, 0) | Q69: =IFERROR(O69*P69, 0) | T69: =IFERROR(R69*S69, 0) | W69: =IFERROR(U69*V69, 0) | Z69: =IFERROR(X69*Y69, 0) | AC69: =IFERROR(AA69*AB69, 0) | AF69: =IFERROR(AD69*AE69, 0) | AI69: =IFERROR(AG69*AH69, 0) | AL69: =IFERROR(AJ69*AK69, 0) | AO69: =IFERROR(AM69*AN69, 0) | AR69: =IFERROR(AP69*AQ69, 0) | AU69: =IFERROR(AS69*AT69, 0) | AX69: =IFERROR(AV69*AW69, 0) | BA69: =IFERROR(AY69*AZ69, 0) | BD69: =IFERROR(BB69*BC69, 0) | BG69: =IFERROR(BE69*BF69, 0) | BJ69: =IFERROR(BH69*BI69, 0) | BM69: =IFERROR(BK69*BL69, 0) | BP69: =IFERROR(BN69*BO69, 0) | BS69: =IFERROR(BQ69*BR69, 0) | BV69: =IFERROR(BT69*BU69, 0) | BY69: =IFERROR(BW69*BX69, 0) | CB69: =IFERROR(BZ69*CA69, 0) | CE69: =IFERROR(CC69*CD69, 0) | CH69: =IFERROR(CF69*CG69, 0) | CK69: =IFERROR(CI69*CJ69, 0) | CN69: =IFERROR(CL69*CM69, 0) | CQ69: =IFERROR(CO69*CP69, 0) | CT69: =IFERROR(CR69*CS69, 0) | CU69: =IFERROR(SUM(F69,I69,L69,O69,R69,U69,X69,AA69,AD69,AG69,AJ69,AM69,AP69,AS69,AV69,AY69,BB69,BE69,BH69,BK69,BN69,BQ69,BT69,BW69,BZ69,CC69,CF69,CI69,CL69,CO69,CR69), 0) | CV69: =IFERROR(AVERAGE(G69,J69,M69,P69,S69,V69,Y69,AB69,AE69,AH69,AK69,AN69,AQ69,AT69,AW69,AZ69,BC69,BF69,BI69,BL69,BO69,BR69,BU69,BX69,CA69,CD69,CG69,CJ69,CM69,CP69,CS69), 0) | CW69: =CU69*CV69
A70: Espinazo | B70: Und | E70: 0 | H70: =IFERROR(F70*G70, 0) | K70: =IFERROR(I70*J70, 0) | N70: =IFERROR(L70*M70, 0) | Q70: =IFERROR(O70*P70, 0) | T70: =IFERROR(R70*S70, 0) | W70: =IFERROR(U70*V70, 0) | Z70: =IFERROR(X70*Y70, 0) | AC70: =IFERROR(AA70*AB70, 0) | AF70: =IFERROR(AD70*AE70, 0) | AI70: =IFERROR(AG70*AH70, 0) | AL70: =IFERROR(AJ70*AK70, 0) | AO70: =IFERROR(AM70*AN70, 0) | AR70: =IFERROR(AP70*AQ70, 0) | AU70: =IFERROR(AS70*AT70, 0) | AX70: =IFERROR(AV70*AW70, 0) | BA70: =IFERROR(AY70*AZ70, 0) | BD70: =IFERROR(BB70*BC70, 0) | BG70: =IFERROR(BE70*BF70, 0) | BJ70: =IFERROR(BH70*BI70, 0) | BM70: =IFERROR(BK70*BL70, 0) | BP70: =IFERROR(BN70*BO70, 0) | BS70: =IFERROR(BQ70*BR70, 0) | BV70: =IFERROR(BT70*BU70, 0) | BW70: 6 | BX70: 3666.67 | BY70: 22000 | CB70: =IFERROR(BZ70*CA70, 0) | CE70: =IFERROR(CC70*CD70, 0) | CH70: =IFERROR(CF70*CG70, 0) | CK70: =IFERROR(CI70*CJ70, 0) | CN70: =IFERROR(CL70*CM70, 0) | CQ70: =IFERROR(CO70*CP70, 0) | CT70: =IFERROR(CR70*CS70, 0) | CU70: =IFERROR(SUM(F70,I70,L70,O70,R70,U70,X70,AA70,AD70,AG70,AJ70,AM70,AP70,AS70,AV70,AY70,BB70,BE70,BH70,BK70,BN70,BQ70,BT70,BW70,BZ70,CC70,CF70,CI70,CL70,CO70,CR70), 0) | CV70: =IFERROR(AVERAGE(G70,J70,M70,P70,S70,V70,Y70,AB70,AE70,AH70,AK70,AN70,AQ70,AT70,AW70,AZ70,BC70,BF70,BI70,BL70,BO70,BR70,BU70,BX70,CA70,CD70,CG70,CJ70,CM70,CP70,CS70), 0) | CW70: =CU70*CV70
A71: Tilapia y truchas | B71: Kg | E71: 0 | H71: =IFERROR(F71*G71, 0) | I71: 20 | J71: 16000 | K71: 320000 | N71: =IFERROR(L71*M71, 0) | Q71: =IFERROR(O71*P71, 0) | T71: =IFERROR(R71*S71, 0) | W71: =IFERROR(U71*V71, 0) | Z71: =IFERROR(X71*Y71, 0) | AC71: =IFERROR(AA71*AB71, 0) | AD71: 19.8 | AE71: 17000 | AF71: 336600 | AI71: =IFERROR(AG71*AH71, 0) | AL71: =IFERROR(AJ71*AK71, 0) | AO71: =IFERROR(AM71*AN71, 0) | AR71: =IFERROR(AP71*AQ71, 0) | AU71: =IFERROR(AS71*AT71, 0) | AV71: 8.5 | AW71: 17000 | AX71: 144500 | BA71: =IFERROR(AY71*AZ71, 0) | BD71: =IFERROR(BB71*BC71, 0) | BG71: =IFERROR(BE71*BF71, 0) | BJ71: =IFERROR(BH71*BI71, 0) | BM71: =IFERROR(BK71*BL71, 0) | BP71: =IFERROR(BN71*BO71, 0) | BS71: =IFERROR(BQ71*BR71, 0) | BV71: =IFERROR(BT71*BU71, 0) | BY71: =IFERROR(BW71*BX71, 0) | CB71: =IFERROR(BZ71*CA71, 0) | CE71: =IFERROR(CC71*CD71, 0) | CH71: =IFERROR(CF71*CG71, 0) | CK71: =IFERROR(CI71*CJ71, 0) | CN71: =IFERROR(CL71*CM71, 0) | CQ71: =IFERROR(CO71*CP71, 0) | CT71: =IFERROR(CR71*CS71, 0) | CU71: =IFERROR(SUM(F71,I71,L71,O71,R71,U71,X71,AA71,AD71,AG71,AJ71,AM71,AP71,AS71,AV71,AY71,BB71,BE71,BH71,BK71,BN71,BQ71,BT71,BW71,BZ71,CC71,CF71,CI71,CL71,CO71,CR71), 0) | CV71: =IFERROR(AVERAGE(G71,J71,M71,P71,S71,V71,Y71,AB71,AE71,AH71,AK71,AN71,AQ71,AT71,AW71,AZ71,BC71,BF71,BI71,BL71,BO71,BR71,BU71,BX71,CA71,CD71,CG71,CJ71,CM71,CP71,CS71), 0) | CW71: =CU71*CV71
A72: Atunes | B72: Und | E72: 0 | H72: =IFERROR(F72*G72, 0) | K72: =IFERROR(I72*J72, 0) | N72: =IFERROR(L72*M72, 0) | Q72: =IFERROR(O72*P72, 0) | T72: =IFERROR(R72*S72, 0) | W72: =IFERROR(U72*V72, 0) | Z72: =IFERROR(X72*Y72, 0) | AC72: =IFERROR(AA72*AB72, 0) | AF72: =IFERROR(AD72*AE72, 0) | AI72: =IFERROR(AG72*AH72, 0) | AL72: =IFERROR(AJ72*AK72, 0) | AO72: =IFERROR(AM72*AN72, 0) | AR72: =IFERROR(AP72*AQ72, 0) | AU72: =IFERROR(AS72*AT72, 0) | AX72: =IFERROR(AV72*AW72, 0) | BA72: =IFERROR(AY72*AZ72, 0) | BD72: =IFERROR(BB72*BC72, 0) | BG72: =IFERROR(BE72*BF72, 0) | BJ72: =IFERROR(BH72*BI72, 0) | BM72: =IFERROR(BK72*BL72, 0) | BP72: =IFERROR(BN72*BO72, 0) | BS72: =IFERROR(BQ72*BR72, 0) | BV72: =IFERROR(BT72*BU72, 0) | BY72: =IFERROR(BW72*BX72, 0) | CB72: =IFERROR(BZ72*CA72, 0) | CE72: =IFERROR(CC72*CD72, 0) | CH72: =IFERROR(CF72*CG72, 0) | CK72: =IFERROR(CI72*CJ72, 0) | CN72: =IFERROR(CL72*CM72, 0) | CQ72: =IFERROR(CO72*CP72, 0) | CT72: =IFERROR(CR72*CS72, 0) | CU72: =IFERROR(SUM(F72,I72,L72,O72,R72,U72,X72,AA72,AD72,AG72,AJ72,AM72,AP72,AS72,AV72,AY72,BB72,BE72,BH72,BK72,BN72,BQ72,BT72,BW72,BZ72,CC72,CF72,CI72,CL72,CO72,CR72), 0) | CV72: =IFERROR(AVERAGE(G72,J72,M72,P72,S72,V72,Y72,AB72,AE72,AH72,AK72,AN72,AQ72,AT72,AW72,AZ72,BC72,BF72,BI72,BL72,BO72,BR72,BU72,BX72,CA72,CD72,CG72,CJ72,CM72,CP72,CS72), 0) | CW72: =CU72*CV72
A73: Chorizo de pollo | B73: Und | E73: 0 | H73: =IFERROR(F73*G73, 0) | K73: =IFERROR(I73*J73, 0) | N73: =IFERROR(L73*M73, 0) | Q73: =IFERROR(O73*P73, 0) | T73: =IFERROR(R73*S73, 0) | W73: =IFERROR(U73*V73, 0) | Z73: =IFERROR(X73*Y73, 0) | AC73: =IFERROR(AA73*AB73, 0) | AD73: 1 | AE73: 17000 | AF73: 17000 | AI73: =IFERROR(AG73*AH73, 0) | AL73: =IFERROR(AJ73*AK73, 0) | AO73: =IFERROR(AM73*AN73, 0) | AR73: =IFERROR(AP73*AQ73, 0) | AU73: =IFERROR(AS73*AT73, 0) | AX73: =IFERROR(AV73*AW73, 0) | BA73: =IFERROR(AY73*AZ73, 0) | BD73: =IFERROR(BB73*BC73, 0) | BG73: =IFERROR(BE73*BF73, 0) | BJ73: =IFERROR(BH73*BI73, 0) | BM73: =IFERROR(BK73*BL73, 0) | BP73: =IFERROR(BN73*BO73, 0) | BS73: =IFERROR(BQ73*BR73, 0) | BV73: =IFERROR(BT73*BU73, 0) | BY73: =IFERROR(BW73*BX73, 0) | CB73: =IFERROR(BZ73*CA73, 0) | CE73: =IFERROR(CC73*CD73, 0) | CH73: =IFERROR(CF73*CG73, 0) | CK73: =IFERROR(CI73*CJ73, 0) | CN73: =IFERROR(CL73*CM73, 0) | CQ73: =IFERROR(CO73*CP73, 0) | CT73: =IFERROR(CR73*CS73, 0) | CU73: =IFERROR(SUM(F73,I73,L73,O73,R73,U73,X73,AA73,AD73,AG73,AJ73,AM73,AP73,AS73,AV73,AY73,BB73,BE73,BH73,BK73,BN73,BQ73,BT73,BW73,BZ73,CC73,CF73,CI73,CL73,CO73,CR73), 0) | CV73: =IFERROR(AVERAGE(G73,J73,M73,P73,S73,V73,Y73,AB73,AE73,AH73,AK73,AN73,AQ73,AT73,AW73,AZ73,BC73,BF73,BI73,BL73,BO73,BR73,BU73,BX73,CA73,CD73,CG73,CJ73,CM73,CP73,CS73), 0) | CW73: =CU73*CV73
A74: Chorizo coctelero x 40 | B74: Und | E74: 0 | H74: =IFERROR(F74*G74, 0) | K74: =IFERROR(I74*J74, 0) | N74: =IFERROR(L74*M74, 0) | O74: 5 | P74: 48000 | Q74: 240000 | T74: =IFERROR(R74*S74, 0) | W74: =IFERROR(U74*V74, 0) | Z74: =IFERROR(X74*Y74, 0) | AC74: =IFERROR(AA74*AB74, 0) | AF74: =IFERROR(AD74*AE74, 0) | AG74: 6 | AH74: 48000 | AI74: 288000 | AL74: =IFERROR(AJ74*AK74, 0) | AO74: =IFERROR(AM74*AN74, 0) | AR74: =IFERROR(AP74*AQ74, 0) | AU74: =IFERROR(AS74*AT74, 0) | AV74: 3 | AW74: 48000 | AX74: 144000 | BA74: =IFERROR(AY74*AZ74, 0) | BD74: =IFERROR(BB74*BC74, 0) | BG74: =IFERROR(BE74*BF74, 0) | BJ74: =IFERROR(BH74*BI74, 0) | BK74: 5 | BL74: 48000 | BM74: 240000 | BP74: =IFERROR(BN74*BO74, 0) | BS74: =IFERROR(BQ74*BR74, 0) | BV74: =IFERROR(BT74*BU74, 0) | BY74: =IFERROR(BW74*BX74, 0) | CB74: =IFERROR(BZ74*CA74, 0) | CE74: =IFERROR(CC74*CD74, 0) | CH74: =IFERROR(CF74*CG74, 0) | CK74: =IFERROR(CI74*CJ74, 0) | CN74: =IFERROR(CL74*CM74, 0) | CQ74: =IFERROR(CO74*CP74, 0) | CT74: =IFERROR(CR74*CS74, 0) | CU74: =IFERROR(SUM(F74,I74,L74,O74,R74,U74,X74,AA74,AD74,AG74,AJ74,AM74,AP74,AS74,AV74,AY74,BB74,BE74,BH74,BK74,BN74,BQ74,BT74,BW74,BZ74,CC74,CF74,CI74,CL74,CO74,CR74), 0) | CV74: =IFERROR(AVERAGE(G74,J74,M74,P74,S74,V74,Y74,AB74,AE74,AH74,AK74,AN74,AQ74,AT74,AW74,AZ74,BC74,BF74,BI74,BL74,BO74,BR74,BU74,BX74,CA74,CD74,CG74,CJ74,CM74,CP74,CS74), 0) | CW74: =CU74*CV74
A75: Filete basa

Sheet Verduras
A1: Verduras | F1: 1 | I1: 2 | L1: 3 | O1: 4 | R1: 5 | U1: 6 | X1: 7 | AA1: 8 | AD1: 9 | AG1: 10 | AJ1: 11 | AM1: 12 | AP1: 13 | AS1: 14 | AV1: 15 | AY1: 16 | BB1: 17 | BE1: 18 | BH1: 19 | BK1: 20 | BN1: 21 | BQ1: 22 | BT1: 23 | BW1: 24 | BZ1: 25 | CC1: 26 | CF1: 27 | CI1: 28 | CL1: 29 | CO1: 30 | CR1: 31 | CU1: Total mes
A2: Producto | B2: Medida | C2: Inv -inicial | D2: Valor | E2: Total | F2: Cantid | G2: Costo unit | H2: Vr. compra | I2: Cantid | J2: Costo unit | K2: Vr. compra | L2: Cantid | M2: Costo unit | N2: Vr. compra | O2: Cantid | P2: Costo unit | Q2: Vr. compra | R2: Cantid | S2: Costo | T2: Vr. compra | U2: Cantid | V2: Costo unit | W2: Vr. compra | X2: Cantid | Y2: Costo unit | Z2: Vr. compra | AA2: Cantid | AB2: Costo unit | AC2: Vr. compra | AD2: Cantid | AE2: Costo unit | AF2: Vr. compra | AG2: Cantid | AH2: Costo unit | AI2: Vr. compra | AJ2: Cantid | AK2: Costo unit | AL2: Vr. compra | AM2: Cantid | AN2: Costo unit | AO2: Vr. compra | AP2: Cantid | AQ2: Costo | AR2: Vr. compra | AS2: Cantid | AT2: Costo unit | AU2: Vr. compra | AV2: Cantid | AW2: Costo unit | AX2: Vr. compra | AY2: Cantid | AZ2: Costo unit | BA2: Vr. compra | BB2: Cantid | BC2: Costo unit | BD2: Vr. compra | BE2: Cantid | BF2: Costo unit | BG2: Vr. compra | BH2: Cantid | BI2: Costo unit | BJ2: Vr. compra | BK2: Cantid | BL2: Costo unit | BM2: Vr. compra | BN2: Cantid | BO2: Costo | BP2: Vr. compra | BQ2: Cantid | BR2: Costo unit | BS2: Vr. compra | BT2: Cantid | BU2: Costo unit | BV2: Vr. compra | BW2: Cantid | BX2: Costo unit | BY2: Vr. compra | BZ2: Cantid | CA2: Costo unit | CB2: Vr. compra | CC2: Cantid | CD2: Costo unit | CE2: Vr. compra | CF2: Cantid | CG2: Costo unit | CH2: Vr. compra | CI2: Cantid | CJ2: Costo unit | CK2: Vr. compra | CL2: Cantid | CM2: Costo | CN2: Vr. compra | CO2: Cantid | CP2: Costo unit | CQ2: Vr. compra | CR2: Cantid | CS2: Costo unit | CT2: Vr. compra | CU2: Cantid | CV2: Costo unit | CW2: Vr. compra
A3: Zapayo | B3: Kg | H3: =IFERROR(F3*G3, 0) | K3: =IFERROR(I3*J3, 0) | N3: =IFERROR(L3*M3, 0) | Q3: =IFERROR(O3*P3, 0) | T3: =IFERROR(R3*S3, 0) | W3: =IFERROR(U3*V3, 0) | Z3: =IFERROR(X3*Y3, 0) | AC3: =IFERROR(AA3*AB3, 0) | AF3: =IFERROR(AD3*AE3, 0) | AI3: =IFERROR(AG3*AH3, 0) | AL3: =IFERROR(AJ3*AK3, 0) | AO3: =IFERROR(AM3*AN3, 0) | AR3: =IFERROR(AP3*AQ3, 0) | AU3: =IFERROR(AS3*AT3, 0) | AX3: =IFERROR(AV3*AW3, 0) | BA3: =IFERROR(AY3*AZ3, 0) | BD3: =IFERROR(BB3*BC3, 0) | BG3: =IFERROR(BE3*BF3, 0) | BJ3: =IFERROR(BH3*BI3, 0) | BM3: =IFERROR(BK3*BL3, 0) | BP3: =IFERROR(BN3*BO3, 0) | BS3: =IFERROR(BQ3*BR3, 0) | BV3: =IFERROR(BT3*BU3, 0) | BY3: =IFERROR(BW3*BX3, 0) | CB3: =IFERROR(BZ3*CA3, 0) | CE3: =IFERROR(CC3*CD3, 0) | CH3: =IFERROR(CF3*CG3, 0) | CK3: =IFERROR(CI3*CJ3, 0) | CN3: =IFERROR(CL3*CM3, 0) | CQ3: =IFERROR(CO3*CP3, 0) | CT3: =IFERROR(CR3*CS3, 0) | CU3: =IFERROR(SUM(F3,I3,L3,O3,R3,U3,X3,AA3,AD3,AG3,AJ3,AM3,AP3,AS3,AV3,AY3,BB3,BE3,BH3,BK3,BN3,BQ3,BT3,BW3,BZ3,CC3,CF3,CI3,CL3,CO3,CR3), 0) | CV3: =IFERROR(AVERAGE(G3,J3,M3,P3,S3,V3,Y3,AB3,AE3,AH3,AK3,AN3,AQ3,AT3,AW3,AZ3,BC3,BF3,BI3,BL3,BO3,BR3,BU3,BX3,CA3,CD3,CG3,CJ3,CM3,CP3,CS3), 0) | CW3: =CU3*CV3
A4: Zanahoria | B4: Kg | H4: =IFERROR(F4*G4, 0) | K4: =IFERROR(I4*J4, 0) | N4: =IFERROR(L4*M4, 0) | Q4: =IFERROR(O4*P4, 0) | T4: =IFERROR(R4*S4, 0) | W4: =IFERROR(U4*V4, 0) | Z4: =IFERROR(X4*Y4, 0) | AC4: =IFERROR(AA4*AB4, 0) | AF4: =IFERROR(AD4*AE4, 0) | AI4: =IFERROR(AG4*AH4, 0) | AL4: =IFERROR(AJ4*AK4, 0) | AO4: =IFERROR(AM4*AN4, 0) | AP4: 16.5 | AQ4: 2800 | AR4: 44460 | AS4: 9.1 | AT4: 2000 | AU4: 18200 | AX4: =IFERROR(AV4*AW4, 0) | BA4: =IFERROR(AY4*AZ4, 0) | BD4: =IFERROR(BB4*BC4, 0) | BG4: =IFERROR(BE4*BF4, 0) | BJ4: =IFERROR(BH4*BI4, 0) | BM4: =IFERROR(BK4*BL4, 0) | BN4: 15.2 | BO4: 2000 | BP4: 36700 | BS4: =IFERROR(BQ4*BR4, 0) | BV4: =IFERROR(BT4*BU4, 0) | BY4: =IFERROR(BW4*BX4, 0) | CB4: =IFERROR(BZ4*CA4, 0) | CE4: =IFERROR(CC4*CD4, 0) | CH4: =IFERROR(CF4*CG4, 0) | CK4: =IFERROR(CI4*CJ4, 0) | CN4: =IFERROR(CL4*CM4, 0) | CQ4: =IFERROR(CO4*CP4, 0) | CT4: =IFERROR(CR4*CS4, 0) | CU4: =IFERROR(SUM(F4,I4,L4,O4,R4,U4,X4,AA4,AD4,AG4,AJ4,AM4,AP4,AS4,AV4,AY4,BB4,BE4,BH4,BK4,BN4,BQ4,BT4,BW4,BZ4,CC4,CF4,CI4,CL4,CO4,CR4), 0) | CV4: =IFERROR(AVERAGE(G4,J4,M4,P4,S4,V4,Y4,AB4,AE4,AH4,AK4,AN4,AQ4,AT4,AW4,AZ4,BC4,BF4,BI4,BL4,BO4,BR4,BU4,BX4,CA4,CD4,CG4,CJ4,CM4,CP4,CS4), 0) | CW4: =CU4*CV4
A5: Yuca | B5: Kg | H5: =IFERROR(F5*G5, 0) | K5: =IFERROR(I5*J5, 0) | N5: =IFERROR(L5*M5, 0) | Q5: =IFERROR(O5*P5, 0) | T5: =IFERROR(R5*S5, 0) | W5: =IFERROR(U5*V5, 0) | Z5: =IFERROR(X5*Y5, 0) | AC5: =IFERROR(AA5*AB5, 0) | AF5: =IFERROR(AD5*AE5, 0) | AI5: =IFERROR(AG5*AH5, 0) | AL5: =IFERROR(AJ5*AK5, 0) | AO5: =IFERROR(AM5*AN5, 0) | AR5: =IFERROR(AP5*AQ5, 0) | AU5: =IFERROR(AS5*AT5, 0) | AX5: =IFERROR(AV5*AW5, 0) | BA5: =IFERROR(AY5*AZ5, 0) | BD5: =IFERROR(BB5*BC5, 0) | BG5: =IFERROR(BE5*BF5, 0) | BJ5: =IFERROR(BH5*BI5, 0) | BM5: =IFERROR(BK5*BL5, 0) | BP5: =IFERROR(BN5*BO5, 0) | BS5: =IFERROR(BQ5*BR5, 0) | BV5: =IFERROR(BT5*BU5, 0) | BY5: =IFERROR(BW5*BX5, 0) | CB5: =IFERROR(BZ5*CA5, 0) | CE5: =IFERROR(CC5*CD5, 0) | CH5: =IFERROR(CF5*CG5, 0) | CK5: =IFERROR(CI5*CJ5, 0) | CN5: =IFERROR(CL5*CM5, 0) | CQ5: =IFERROR(CO5*CP5, 0) | CT5: =IFERROR(CR5*CS5, 0) | CU5: =IFERROR(SUM(F5,I5,L5,O5,R5,U5,X5,AA5,AD5,AG5,AJ5,AM5,AP5,AS5,AV5,AY5,BB5,BE5,BH5,BK5,BN5,BQ5,BT5,BW5,BZ5,CC5,CF5,CI5,CL5,CO5,CR5), 0) | CV5: =IFERROR(AVERAGE(G5,J5,M5,P5,S5,V5,Y5,AB5,AE5,AH5,AK5,AN5,AQ5,AT5,AW5,AZ5,BC5,BF5,BI5,BL5,BO5,BR5,BU5,BX5,CA5,CD5,CG5,CJ5,CM5,CP5,CS5), 0) | CW5: =CU5*CV5
A6: Uva | B6: Kg | H6: =IFERROR(F6*G6, 0) | K6: =IFERROR(I6*J6, 0) | N6: =IFERROR(L6*M6, 0) | Q6: =IFERROR(O6*P6, 0) | T6: =IFERROR(R6*S6, 0) | W6: =IFERROR(U6*V6, 0) | Z6: =IFERROR(X6*Y6, 0) | AC6: =IFERROR(AA6*AB6, 0) | AF6: =IFERROR(AD6*AE6, 0) | AI6: =IFERROR(AG6*AH6, 0) | AL6: =IFERROR(AJ6*AK6, 0) | AO6: =IFERROR(AM6*AN6, 0) | AR6: =IFERROR(AP6*AQ6, 0) | AU6: =IFERROR(AS6*AT6, 0) | AX6: =IFERROR(AV6*AW6, 0) | BA6: =IFERROR(AY6*AZ6, 0) | BD6: =IFERROR(BB6*BC6, 0) | BG6: =IFERROR(BE6*BF6, 0) | BJ6: =IFERROR(BH6*BI6, 0) | BM6: =IFERROR(BK6*BL6, 0) | BP6: =IFERROR(BN6*BO6, 0) | BS6: =IFERROR(BQ6*BR6, 0) | BV6: =IFERROR(BT6*BU6, 0) | BY6: =IFERROR(BW6*BX6, 0) | CB6: =IFERROR(BZ6*CA6, 0) | CE6: =IFERROR(CC6*CD6, 0) | CH6: =IFERROR(CF6*CG6, 0) | CK6: =IFERROR(CI6*CJ6, 0) | CN6: =IFERROR(CL6*CM6, 0) | CQ6: =IFERROR(CO6*CP6, 0) | CT6: =IFERROR(CR6*CS6, 0) | CU6: =IFERROR(SUM(F6,I6,L6,O6,R6,U6,X6,AA6,AD6,AG6,AJ6,AM6,AP6,AS6,AV6,AY6,BB6,BE6,BH6,BK6,BN6,BQ6,BT6,BW6,BZ6,CC6,CF6,CI6,CL6,CO6,CR6), 0) | CV6: =IFERROR(AVERAGE(G6,J6,M6,P6,S6,V6,Y6,AB6,AE6,AH6,AK6,AN6,AQ6,AT6,AW6,AZ6,BC6,BF6,BI6,BL6,BO6,BR6,BU6,BX6,CA6,CD6,CG6,CJ6,CM6,CP6,CS6), 0) | CW6: =CU6*CV6
A7: Ulluco Limpio | B7: Kg | H7: =IFERROR(F7*G7, 0) | K7: =IFERROR(I7*J7, 0) | N7: =IFERROR(L7*M7, 0) | Q7: =IFERROR(O7*P7, 0) | T7: =IFERROR(R7*S7, 0) | W7: =IFERROR(U7*V7, 0) | Z7: =IFERROR(X7*Y7, 0) | AC7: =IFERROR(AA7*AB7, 0) | AF7: =IFERROR(AD7*AE7, 0) | AI7: =IFERROR(AG7*AH7, 0) | AL7: =IFERROR(AJ7*AK7, 0) | AO7: =IFERROR(AM7*AN7, 0) | AP7: 4.8 | AQ7: 9000 | AR7: 43200 | AS7: 5 | AT7: 10000 | AU7: 50000 | AX7: =IFERROR(AV7*AW7, 0) | BA7: =IFERROR(AY7*AZ7, 0) | BD7: =IFERROR(BB7*BC7, 0) | BG7: =IFERROR(BE7*BF7, 0) | BJ7: =IFERROR(BH7*BI7, 0) | BM7: =IFERROR(BK7*BL7, 0) | BP7: =IFERROR(BN7*BO7, 0) | BS7: =IFERROR(BQ7*BR7, 0) | BV7: =IFERROR(BT7*BU7, 0) | BY7: =IFERROR(BW7*BX7, 0) | CB7: =IFERROR(BZ7*CA7, 0) | CE7: =IFERROR(CC7*CD7, 0) | CH7: =IFERROR(CF7*CG7, 0) | CK7: =IFERROR(CI7*CJ7, 0) | CN7: =IFERROR(CL7*CM7, 0) | CQ7: =IFERROR(CO7*CP7, 0) | CT7: =IFERROR(CR7*CS7, 0) | CU7: =IFERROR(SUM(F7,I7,L7,O7,R7,U7,X7,AA7,AD7,AG7,AJ7,AM7,AP7,AS7,AV7,AY7,BB7,BE7,BH7,BK7,BN7,BQ7,BT7,BW7,BZ7,CC7,CF7,CI7,CL7,CO7,CR7), 0) | CV7: =IFERROR(AVERAGE(G7,J7,M7,P7,S7,V7,Y7,AB7,AE7,AH7,AK7,AN7,AQ7,AT7,AW7,AZ7,BC7,BF7,BI7,BL7,BO7,BR7,BU7,BX7,CA7,CD7,CG7,CJ7,CM7,CP7,CS7), 0) | CW7: =CU7*CV7
A8: Tortillas | B8: Atados | H8: =IFERROR(F8*G8, 0) | K8: =IFERROR(I8*J8, 0) | N8: =IFERROR(L8*M8, 0) | Q8: =IFERROR(O8*P8, 0) | T8: =IFERROR(R8*S8, 0) | W8: =IFERROR(U8*V8, 0) | Z8: =IFERROR(X8*Y8, 0) | AC8: =IFERROR(AA8*AB8, 0) | AF8: =IFERROR(AD8*AE8, 0) | AI8: =IFERROR(AG8*AH8, 0) | AL8: =IFERROR(AJ8*AK8, 0) | AO8: =IFERROR(AM8*AN8, 0) | AR8: =IFERROR(AP8*AQ8, 0) | AU8: =IFERROR(AS8*AT8, 0) | AX8: =IFERROR(AV8*AW8, 0) | BA8: =IFERROR(AY8*AZ8, 0) | BD8: =IFERROR(BB8*BC8, 0) | BG8: =IFERROR(BE8*BF8, 0) | BJ8: =IFERROR(BH8*BI8, 0) | BM8: =IFERROR(BK8*BL8, 0) | BP8: =IFERROR(BN8*BO8, 0) | BS8: =IFERROR(BQ8*BR8, 0) | BV8: =IFERROR(BT8*BU8, 0) | BY8: =IFERROR(BW8*BX8, 0) | CB8: =IFERROR(BZ8*CA8, 0) | CE8: =IFERROR(CC8*CD8, 0) | CH8: =IFERROR(CF8*CG8, 0) | CK8: =IFERROR(CI8*CJ8, 0) | CN8: =IFERROR(CL8*CM8, 0) | CQ8: =IFERROR(CO8*CP8, 0) | CT8: =IFERROR(CR8*CS8, 0) | CU8: =IFERROR(SUM(F8,I8,L8,O8,R8,U8,X8,AA8,AD8,AG8,AJ8,AM8,AP8,AS8,AV8,AY8,BB8,BE8,BH8,BK8,BN8,BQ8,BT8,BW8,BZ8,CC8,CF8,CI8,CL8,CO8,CR8), 0) | CV8: =IFERROR(AVERAGE(G8,J8,M8,P8,S8,V8,Y8,AB8,AE8,AH8,AK8,AN8,AQ8,AT8,AW8,AZ8,BC8,BF8,BI8,BL8,BO8,BR8,BU8,BX8,CA8,CD8,CG8,CJ8,CM8,CP8,CS8), 0) | CW8: =CU8*CV8
A9: Tomillo | B9: Kg | H9: =IFERROR(F9*G9, 0) | K9: =IFERROR(I9*J9, 0) | N9: =IFERROR(L9*M9, 0) | Q9: =IFERROR(O9*P9, 0) | T9: =IFERROR(R9*S9, 0) | W9: =IFERROR(U9*V9, 0) | Z9: =IFERROR(X9*Y9, 0) | AC9: =IFERROR(AA9*AB9, 0) | AF9: =IFERROR(AD9*AE9, 0) | AI9: =IFERROR(AG9*AH9, 0) | AL9: =IFERROR(AJ9*AK9, 0) | AO9: =IFERROR(AM9*AN9, 0) | AP9: 1 | AQ9: 10000 | AR9: 10000 | AS9: 1 | AT9: 10000 | AU9: 10000 | AX9: =IFERROR(AV9*AW9, 0) | BA9: =IFERROR(AY9*AZ9, 0) | BD9: =IFERROR(BB9*BC9, 0) | BG9: =IFERROR(BE9*BF9, 0) | BJ9: =IFERROR(BH9*BI9, 0) | BM9: =IFERROR(BK9*BL9, 0) | BP9: =IFERROR(BN9*BO9, 0) | BS9: =IFERROR(BQ9*BR9, 0) | BV9: =IFERROR(BT9*BU9, 0) | BY9: =IFERROR(BW9*BX9, 0) | CB9: =IFERROR(BZ9*CA9, 0) | CE9: =IFERROR(CC9*CD9, 0) | CH9: =IFERROR(CF9*CG9, 0) | CK9: =IFERROR(CI9*CJ9, 0) | CN9: =IFERROR(CL9*CM9, 0) | CQ9: =IFERROR(CO9*CP9, 0) | CT9: =IFERROR(CR9*CS9, 0) | CU9: =IFERROR(SUM(F9,I9,L9,O9,R9,U9,X9,AA9,AD9,AG9,AJ9,AM9,AP9,AS9,AV9,AY9,BB9,BE9,BH9,BK9,BN9,BQ9,BT9,BW9,BZ9,CC9,CF9,CI9,CL9,CO9,CR9), 0) | CV9: =IFERROR(AVERAGE(G9,J9,M9,P9,S9,V9,Y9,AB9,AE9,AH9,AK9,AN9,AQ9,AT9,AW9,AZ9,BC9,BF9,BI9,BL9,BO9,BR9,BU9,BX9,CA9,CD9,CG9,CJ9,CM9,CP9,CS9), 0) | CW9: =CU9*CV9
A10: Tomate tahiti | B10: Kg | H10: =IFERROR(F10*G10, 0) | K10: =IFERROR(I10*J10, 0) | N10: =IFERROR(L10*M10, 0) | Q10: =IFERROR(O10*P10, 0) | T10: =IFERROR(R10*S10, 0) | W10: =IFERROR(U10*V10, 0) | Z10: =IFERROR(X10*Y10, 0) | AC10: =IFERROR(AA10*AB10, 0) | AF10: =IFERROR(AD10*AE10, 0) | AI10: =IFERROR(AG10*AH10, 0) | AL10: =IFERROR(AJ10*AK10, 0) | AO10: =IFERROR(AM10*AN10, 0) | AR10: =IFERROR(AP10*AQ10, 0) | AU10: =IFERROR(AS10*AT10, 0) | AX10: =IFERROR(AV10*AW10, 0) | BA10: =IFERROR(AY10*AZ10, 0) | BD10: =IFERROR(BB10*BC10, 0) | BG10: =IFERROR(BE10*BF10, 0) | BJ10: =IFERROR(BH10*BI10, 0) | BM10: =IFERROR(BK10*BL10, 0) | BP10: =IFERROR(BN10*BO10, 0) | BS10: =IFERROR(BQ10*BR10, 0) | BV10: =IFERROR(BT10*BU10, 0) | BY10: =IFERROR(BW10*BX10, 0) | CB10: =IFERROR(BZ10*CA10, 0) | CE10: =IFERROR(CC10*CD10, 0) | CH10: =IFERROR(CF10*CG10, 0) | CK10: =IFERROR(CI10*CJ10, 0) | CN10: =IFERROR(CL10*CM10, 0) | CQ10: =IFERROR(CO10*CP10, 0) | CT10: =IFERROR(CR10*CS10, 0) | CU10: =IFERROR(SUM(F10,I10,L10,O10,R10,U10,X10,AA10,AD10,AG10,AJ10,AM10,AP10,AS10,AV10,AY10,BB10,BE10,BH10,BK10,BN10,BQ10,BT10,BW10,BZ10,CC10,CF10,CI10,CL10,CO10,CR10), 0) | CV10: =IFERROR(AVERAGE(G10,J10,M10,P10,S10,V10,Y10,AB10,AE10,AH10,AK10,AN10,AQ10,AT10,AW10,AZ10,BC10,BF10,BI10,BL10,BO10,BR10,BU10,BX10,CA10,CD10,CG10,CJ10,CM10,CP10,CS10), 0) | CW10: =CU10*CV10
A11: Tomate milano | B11: Kg | H11: =IFERROR(F11*G11, 0) | I11: 16 | J11: 1800 | K11: 28800 | N11: =IFERROR(L11*M11, 0) | Q11: =IFERROR(O11*P11, 0) | T11: =IFERROR(R11*S11, 0) | W11: =IFERROR(U11*V11, 0) | Z11: =IFERROR(X11*Y11, 0) | AC11: =IFERROR(AA11*AB11, 0) | AF11: =IFERROR(AD11*AE11, 0) | AI11: =IFERROR(AG11*AH11, 0) | AL11: =IFERROR(AJ11*AK11, 0) | AO11: =IFERROR(AM11*AN11, 0) | AP11: 3.8 | AQ11: 5000 | AR11: 19000 | AS11: 4 | AT11: 4500 | AU11: 18000 | AX11: =IFERROR(AV11*AW11, 0) | BA11: =IFERROR(AY11*AZ11, 0) | BD11: =IFERROR(BB11*BC11, 0) | BG11: =IFERROR(BE11*BF11, 0) | BJ11: =IFERROR(BH11*BI11, 0) | BM11: =IFERROR(BK11*BL11, 0) | BN11: 3.2 | BO11: 5000 | BP11: 16000 | BS11: =IFERROR(BQ11*BR11, 0) | BV11: =IFERROR(BT11*BU11, 0) | BY11: =IFERROR(BW11*BX11, 0) | CB11: =IFERROR(BZ11*CA11, 0) | CE11: =IFERROR(CC11*CD11, 0) | CH11: =IFERROR(CF11*CG11, 0) | CK11: =IFERROR(CI11*CJ11, 0) | CN11: =IFERROR(CL11*CM11, 0) | CQ11: =IFERROR(CO11*CP11, 0) | CT11: =IFERROR(CR11*CS11, 0) | CU11: =IFERROR(SUM(F11,I11,L11,O11,R11,U11,X11,AA11,AD11,AG11,AJ11,AM11,AP11,AS11,AV11,AY11,BB11,BE11,BH11,BK11,BN11,BQ11,BT11,BW11,BZ11,CC11,CF11,CI11,CL11,CO11,CR11), 0) | CV11: =IFERROR(AVERAGE(G11,J11,M11,P11,S11,V11,Y11,AB11,AE11,AH11,AK11,AN11,AQ11,AT11,AW11,AZ11,BC11,BF11,BI11,BL11,BO11,BR11,BU11,BX11,CA11,CD11,CG11,CJ11,CM11,CP11,CS11), 0) | CW11: =CU11*CV11
A12: Tomate chonto | B12: Kg | H12: =IFERROR(F12*G12, 0) | K12: =IFERROR(I12*J12, 0) | N12: =IFERROR(L12*M12, 0) | Q12: =IFERROR(O12*P12, 0) | T12: =IFERROR(R12*S12, 0) | W12: =IFERROR(U12*V12, 0) | X12: 2.71 | Y12: 5450 | Z12: 14769 | AC12: =IFERROR(AA12*AB12, 0) | AF12: =IFERROR(AD12*AE12, 0) | AI12: =IFERROR(AG12*AH12, 0) | AL12: =IFERROR(AJ12*AK12, 0) | AO12: =IFERROR(AM12*AN12, 0) | AP12: 14.4 | AQ12: 4000 | AR12: 55150 | AS12: 14.5 | AT12: 3800 | AU12: 55100 | AX12: =IFERROR(AV12*AW12, 0) | BA12: =IFERROR(AY12*AZ12, 0) | BD12: =IFERROR(BB12*BC12, 0) | BG12: =IFERROR(BE12*BF12, 0) | BJ12: =IFERROR(BH12*BI12, 0) | BM12: =IFERROR(BK12*BL12, 0) | BN12: 19 | BO12: 3800 | BP12: 72200 | BS12: =IFERROR(BQ12*BR12, 0) | BV12: =IFERROR(BT12*BU12, 0) | BY12: =IFERROR(BW12*BX12, 0) | CB12: =IFERROR(BZ12*CA12, 0) | CE12: =IFERROR(CC12*CD12, 0) | CH12: =IFERROR(CF12*CG12, 0) | CK12: =IFERROR(CI12*CJ12, 0) | CN12: =IFERROR(CL12*CM12, 0) | CQ12: =IFERROR(CO12*CP12, 0) | CT12: =IFERROR(CR12*CS12, 0) | CU12: =IFERROR(SUM(F12,I12,L12,O12,R12,U12,X12,AA12,AD12,AG12,AJ12,AM12,AP12,AS12,AV12,AY12,BB12,BE12,BH12,BK12,BN12,BQ12,BT12,BW12,BZ12,CC12,CF12,CI12,CL12,CO12,CR12), 0) | CV12: =IFERROR(AVERAGE(G12,J12,M12,P12,S12,V12,Y12,AB12,AE12,AH12,AK12,AN12,AQ12,AT12,AW12,AZ12,BC12,BF12,BI12,BL12,BO12,BR12,BU12,BX12,CA12,CD12,CG12,CJ12,CM12,CP12,CS12), 0) | CW12: =CU12*CV12
A13: Repollo morado | B13: Kg | H13: =IFERROR(F13*G13, 0) | K13: =IFERROR(I13*J13, 0) | N13: =IFERROR(L13*M13, 0) | Q13: =IFERROR(O13*P13, 0) | T13: =IFERROR(R13*S13, 0) | W13: =IFERROR(U13*V13, 0) | Z13: =IFERROR(X13*Y13, 0) | AC13: =IFERROR(AA13*AB13, 0) | AF13: =IFERROR(AD13*AE13, 0) | AI13: =IFERROR(AG13*AH13, 0) | AL13: =IFERROR(AJ13*AK13, 0) | AO13: =IFERROR(AM13*AN13, 0) | AP13: 3.4 | AQ13: 2500 | AR13: 8500 | AS13: 2.2 | AT13: 2500 | AU13: 5500 | AX13: =IFERROR(AV13*AW13, 0) | BA13: =IFERROR(AY13*AZ13, 0) | BD13: =IFERROR(BB13*BC13, 0) | BG13: =IFERROR(BE13*BF13, 0) | BJ13: =IFERROR(BH13*BI13, 0) | BM13: =IFERROR(BK13*BL13, 0) | BP13: =IFERROR(BN13*BO13, 0) | BQ13: 2.325 | BR13: 2800 | BS13: 6510 | BV13: =IFERROR(BT13*BU13, 0) | BY13: =IFERROR(BW13*BX13, 0) | CB13: =IFERROR(BZ13*CA13, 0) | CE13: =IFERROR(CC13*CD13, 0) | CH13: =IFERROR(CF13*CG13, 0) | CK13: =IFERROR(CI13*CJ13, 0) | CN13: =IFERROR(CL13*CM13, 0) | CQ13: =IFERROR(CO13*CP13, 0) | CT13: =IFERROR(CR13*CS13, 0) | CU13: =IFERROR(SUM(F13,I13,L13,O13,R13,U13,X13,AA13,AD13,AG13,AJ13,AM13,AP13,AS13,AV13,AY13,BB13,BE13,BH13,BK13,BN13,BQ13,BT13,BW13,BZ13,CC13,CF13,CI13,CL13,CO13,CR13), 0) | CV13: =IFERROR(AVERAGE(G13,J13,M13,P13,S13,V13,Y13,AB13,AE13,AH13,AK13,AN13,AQ13,AT13,AW13,AZ13,BC13,BF13,BI13,BL13,BO13,BR13,BU13,BX13,CA13,CD13,CG13,CJ13,CM13,CP13,CS13), 0) | CW13: =CU13*CV13
A14: Remolacha | B14: Kg | H14: =IFERROR(F14*G14, 0) | K14: =IFERROR(I14*J14, 0) | N14: =IFERROR(L14*M14, 0) | Q14: =IFERROR(O14*P14, 0) | T14: =IFERROR(R14*S14, 0) | W14: =IFERROR(U14*V14, 0) | Z14: =IFERROR(X14*Y14, 0) | AC14: =IFERROR(AA14*AB14, 0) | AF14: =IFERROR(AD14*AE14, 0) | AI14: =IFERROR(AG14*AH14, 0) | AL14: =IFERROR(AJ14*AK14, 0) | AO14: =IFERROR(AM14*AN14, 0) | AR14: =IFERROR(AP14*AQ14, 0) | AU14: =IFERROR(AS14*AT14, 0) | AX14: =IFERROR(AV14*AW14, 0) | BA14: =IFERROR(AY14*AZ14, 0) | BD14: =IFERROR(BB14*BC14, 0) | BG14: =IFERROR(BE14*BF14, 0) | BJ14: =IFERROR(BH14*BI14, 0) | BM14: =IFERROR(BK14*BL14, 0) | BN14: 4 | BO14: 1500 | BP14: 6000 | BS14: =IFERROR(BQ14*BR14, 0) | BV14: =IFERROR(BT14*BU14, 0) | BY14: =IFERROR(BW14*BX14, 0) | CB14: =IFERROR(BZ14*CA14, 0) | CE14: =IFERROR(CC14*CD14, 0) | CH14: =IFERROR(CF14*CG14, 0) | CK14: =IFERROR(CI14*CJ14, 0) | CN14: =IFERROR(CL14*CM14, 0) | CQ14: =IFERROR(CO14*CP14, 0) | CT14: =IFERROR(CR14*CS14, 0) | CU14: =IFERROR(SUM(F14,I14,L14,O14,R14,U14,X14,AA14,AD14,AG14,AJ14,AM14,AP14,AS14,AV14,AY14,BB14,BE14,BH14,BK14,BN14,BQ14,BT14,BW14,BZ14,CC14,CF14,CI14,CL14,CO14,CR14), 0) | CV14: =IFERROR(AVERAGE(G14,J14,M14,P14,S14,V14,Y14,AB14,AE14,AH14,AK14,AN14,AQ14,AT14,AW14,AZ14,BC14,BF14,BI14,BL14,BO14,BR14,BU14,BX14,CA14,CD14,CG14,CJ14,CM14,CP14,CS14), 0) | CW14: =CU14*CV14
A15: Raices chinas | B15: Kg | H15: =IFERROR(F15*G15, 0) | K15: =IFERROR(I15*J15, 0) | N15: =IFERROR(L15*M15, 0) | Q15: =IFERROR(O15*P15, 0) | T15: =IFERROR(R15*S15, 0) | W15: =IFERROR(U15*V15, 0) | Z15: =IFERROR(X15*Y15, 0) | AC15: =IFERROR(AA15*AB15, 0) | AF15: =IFERROR(AD15*AE15, 0) | AI15: =IFERROR(AG15*AH15, 0) | AL15: =IFERROR(AJ15*AK15, 0) | AO15: =IFERROR(AM15*AN15, 0) | AR15: =IFERROR(AP15*AQ15, 0) | AU15: =IFERROR(AS15*AT15, 0) | AX15: =IFERROR(AV15*AW15, 0) | BA15: =IFERROR(AY15*AZ15, 0) | BD15: =IFERROR(BB15*BC15, 0) | BG15: =IFERROR(BE15*BF15, 0) | BJ15: =IFERROR(BH15*BI15, 0) | BM15: =IFERROR(BK15*BL15, 0) | BP15: =IFERROR(BN15*BO15, 0) | BS15: =IFERROR(BQ15*BR15, 0) | BV15: =IFERROR(BT15*BU15, 0) | BY15: =IFERROR(BW15*BX15, 0) | CB15: =IFERROR(BZ15*CA15, 0) | CE15: =IFERROR(CC15*CD15, 0) | CH15: =IFERROR(CF15*CG15, 0) | CK15: =IFERROR(CI15*CJ15, 0) | CN15: =IFERROR(CL15*CM15, 0) | CQ15: =IFERROR(CO15*CP15, 0) | CT15: =IFERROR(CR15*CS15, 0) | CU15: =IFERROR(SUM(F15,I15,L15,O15,R15,U15,X15,AA15,AD15,AG15,AJ15,AM15,AP15,AS15,AV15,AY15,BB15,BE15,BH15,BK15,BN15,BQ15,BT15,BW15,BZ15,CC15,CF15,CI15,CL15,CO15,CR15), 0) | CV15: =IFERROR(AVERAGE(G15,J15,M15,P15,S15,V15,Y15,AB15,AE15,AH15,AK15,AN15,AQ15,AT15,AW15,AZ15,BC15,BF15,BI15,BL15,BO15,BR15,BU15,BX15,CA15,CD15,CG15,CJ15,CM15,CP15,CS15), 0) | CW15: =CU15*CV15
A16: Queso mozarella | B16: Kl | H16: =IFERROR(F16*G16, 0) | K16: =IFERROR(I16*J16, 0) | N16: =IFERROR(L16*M16, 0) | Q16: =IFERROR(O16*P16, 0) | T16: =IFERROR(R16*S16, 0) | W16: =IFERROR(U16*V16, 0) | Z16: =IFERROR(X16*Y16, 0) | AC16: =IFERROR(AA16*AB16, 0) | AF16: =IFERROR(AD16*AE16, 0) | AI16: =IFERROR(AG16*AH16, 0) | AL16: =IFERROR(AJ16*AK16, 0) | AO16: =IFERROR(AM16*AN16, 0) | AR16: =IFERROR(AP16*AQ16, 0) | AU16: =IFERROR(AS16*AT16, 0) | AX16: =IFERROR(AV16*AW16, 0) | BA16: =IFERROR(AY16*AZ16, 0) | BD16: =IFERROR(BB16*BC16, 0) | BG16: =IFERROR(BE16*BF16, 0) | BJ16: =IFERROR(BH16*BI16, 0) | BM16: =IFERROR(BK16*BL16, 0) | BP16: =IFERROR(BN16*BO16, 0) | BS16: =IFERROR(BQ16*BR16, 0) | BV16: =IFERROR(BT16*BU16, 0) | BY16: =IFERROR(BW16*BX16, 0) | CB16: =IFERROR(BZ16*CA16, 0) | CE16: =IFERROR(CC16*CD16, 0) | CH16: =IFERROR(CF16*CG16, 0) | CK16: =IFERROR(CI16*CJ16, 0) | CN16: =IFERROR(CL16*CM16, 0) | CQ16: =IFERROR(CO16*CP16, 0) | CT16: =IFERROR(CR16*CS16, 0) | CU16: =IFERROR(SUM(F16,I16,L16,O16,R16,U16,X16,AA16,AD16,AG16,AJ16,AM16,AP16,AS16,AV16,AY16,BB16,BE16,BH16,BK16,BN16,BQ16,BT16,BW16,BZ16,CC16,CF16,CI16,CL16,CO16,CR16), 0) | CV16: =IFERROR(AVERAGE(G16,J16,M16,P16,S16,V16,Y16,AB16,AE16,AH16,AK16,AN16,AQ16,AT16,AW16,AZ16,BC16,BF16,BI16,BL16,BO16,BR16,BU16,BX16,CA16,CD16,CG16,CJ16,CM16,CP16,CS16), 0) | CW16: =CU16*CV16
A17: Queso mozarella | B17: Kl | H17: =IFERROR(F17*G17, 0) | K17: =IFERROR(I17*J17, 0) | N17: =IFERROR(L17*M17, 0) | Q17: =IFERROR(O17*P17, 0) | T17: =IFERROR(R17*S17, 0) | W17: =IFERROR(U17*V17, 0) | X17: 4 | Y17: 11450 | Z17: 55440 | AC17: =IFERROR(AA17*AB17, 0) | AF17: =IFERROR(AD17*AE17, 0) | AI17: =IFERROR(AG17*AH17, 0) | AL17: =IFERROR(AJ17*AK17, 0) | AO17: =IFERROR(AM17*AN17, 0) | AR17: =IFERROR(AP17*AQ17, 0) | AU17: =IFERROR(AS17*AT17, 0) | AX17: =IFERROR(AV17*AW17, 0) | BA17: =IFERROR(AY17*AZ17, 0) | BD17: =IFERROR(BB17*BC17, 0) | BG17: =IFERROR(BE17*BF17, 0) | BJ17: =IFERROR(BH17*BI17, 0) | BM17: =IFERROR(BK17*BL17, 0) | BP17: =IFERROR(BN17*BO17, 0) | BS17: =IFERROR(BQ17*BR17, 0) | BV17: =IFERROR(BT17*BU17, 0) | BY17: =IFERROR(BW17*BX17, 0) | CB17: =IFERROR(BZ17*CA17, 0) | CE17: =IFERROR(CC17*CD17, 0) | CH17: =IFERROR(CF17*CG17, 0) | CK17: =IFERROR(CI17*CJ17, 0) | CN17: =IFERROR(CL17*CM17, 0) | CQ17: =IFERROR(CO17*CP17, 0) | CT17: =IFERROR(CR17*CS17, 0) | CU17: =IFERROR(SUM(F17,I17,L17,O17,R17,U17,X17,AA17,AD17,AG17,AJ17,AM17,AP17,AS17,AV17,AY17,BB17,BE17,BH17,BK17,BN17,BQ17,BT17,BW17,BZ17,CC17,CF17,CI17,CL17,CO17,CR17), 0) | CV17: =IFERROR(AVERAGE(G17,J17,M17,P17,S17,V17,Y17,AB17,AE17,AH17,AK17,AN17,AQ17,AT17,AW17,AZ17,BC17,BF17,BI17,BL17,BO17,BR17,BU17,BX17,CA17,CD17,CG17,CJ17,CM17,CP17,CS17), 0) | CW17: =CU17*CV17
A18: Platano verde | B18: Kg | H18: =IFERROR(F18*G18, 0) | I18: 1 | J18: 130000 | K18: 130000 | N18: =IFERROR(L18*M18, 0) | Q18: =IFERROR(O18*P18, 0) | T18: =IFERROR(R18*S18, 0) | W18: =IFERROR(U18*V18, 0) | Z18: =IFERROR(X18*Y18, 0) | AC18: =IFERROR(AA18*AB18, 0) | AF18: =IFERROR(AD18*AE18, 0) | AI18: =IFERROR(AG18*AH18, 0) | AL18: =IFERROR(AJ18*AK18, 0) | AO18: =IFERROR(AM18*AN18, 0) | AP18: 237.6 | AQ18: 1800 | AR18: 427680 | AS18: 75.2 | AT18: 1600 | AU18: 120320 | AX18: =IFERROR(AV18*AW18, 0) | BA18: =IFERROR(AY18*AZ18, 0) | BD18: =IFERROR(BB18*BC18, 0) | BG18: =IFERROR(BE18*BF18, 0) | BJ18: =IFERROR(BH18*BI18, 0) | BM18: =IFERROR(BK18*BL18, 0) | BN18: 87.6 | BO18: 1500 | BP18: 146640 | BS18: =IFERROR(BQ18*BR18, 0) | BV18: =IFERROR(BT18*BU18, 0) | BY18: =IFERROR(BW18*BX18, 0) | CB18: =IFERROR(BZ18*CA18, 0) | CE18: =IFERROR(CC18*CD18, 0) | CH18: =IFERROR(CF18*CG18, 0) | CK18: =IFERROR(CI18*CJ18, 0) | CN18: =IFERROR(CL18*CM18, 0) | CQ18: =IFERROR(CO18*CP18, 0) | CT18: =IFERROR(CR18*CS18, 0) | CU18: =IFERROR(SUM(F18,I18,L18,O18,R18,U18,X18,AA18,AD18,AG18,AJ18,AM18,AP18,AS18,AV18,AY18,BB18,BE18,BH18,BK18,BN18,BQ18,BT18,BW18,BZ18,CC18,CF18,CI18,CL18,CO18,CR18), 0) | CV18: =IFERROR(AVERAGE(G18,J18,M18,P18,S18,V18,Y18,AB18,AE18,AH18,AK18,AN18,AQ18,AT18,AW18,AZ18,BC18,BF18,BI18,BL18,BO18,BR18,BU18,BX18,CA18,CD18,CG18,CJ18,CM18,CP18,CS18), 0) | CW18: =CU18*CV18
A19: Platano Promocion | B19: Kg | H19: =IFERROR(F19*G19, 0) | K19: =IFERROR(I19*J19, 0) | N19: =IFERROR(L19*M19, 0) | Q19: =IFERROR(O19*P19, 0) | T19: =IFERROR(R19*S19, 0) | W19: =IFERROR(U19*V19, 0) | Z19: =IFERROR(X19*Y19, 0) | AC19: =IFERROR(AA19*AB19, 0) | AF19: =IFERROR(AD19*AE19, 0) | AI19: =IFERROR(AG19*AH19, 0) | AL19: =IFERROR(AJ19*AK19, 0) | AO19: =IFERROR(AM19*AN19, 0) | AR19: =IFERROR(AP19*AQ19, 0) | AU19: =IFERROR(AS19*AT19, 0) | AX19: =IFERROR(AV19*AW19, 0) | BA19: =IFERROR(AY19*AZ19, 0) | BD19: =IFERROR(BB19*BC19, 0) | BG19: =IFERROR(BE19*BF19, 0) | BJ19: =IFERROR(BH19*BI19, 0) | BM19: =IFERROR(BK19*BL19, 0) | BP19: =IFERROR(BN19*BO19, 0) | BS19: =IFERROR(BQ19*BR19, 0) | BV19: =IFERROR(BT19*BU19, 0) | BY19: =IFERROR(BW19*BX19, 0) | CB19: =IFERROR(BZ19*CA19, 0) | CE19: =IFERROR(CC19*CD19, 0) | CH19: =IFERROR(CF19*CG19, 0) | CK19: =IFERROR(CI19*CJ19, 0) | CN19: =IFERROR(CL19*CM19, 0) | CQ19: =IFERROR(CO19*CP19, 0) | CT19: =IFERROR(CR19*CS19, 0) | CU19: =IFERROR(SUM(F19,I19,L19,O19,R19,U19,X19,AA19,AD19,AG19,AJ19,AM19,AP19,AS19,AV19,AY19,BB19,BE19,BH19,BK19,BN19,BQ19,BT19,BW19,BZ19,CC19,CF19,CI19,CL19,CO19,CR19), 0) | CV19: =IFERROR(AVERAGE(G19,J19,M19,P19,S19,V19,Y19,AB19,AE19,AH19,AK19,AN19,AQ19,AT19,AW19,AZ19,BC19,BF19,BI19,BL19,BO19,BR19,BU19,BX19,CA19,CD19,CG19,CJ19,CM19,CP19,CS19), 0) | CW19: =CU19*CV19
A20: Platano maduro | B20: Kg | H20: =IFERROR(F20*G20, 0) | K20: =IFERROR(I20*J20, 0) | N20: =IFERROR(L20*M20, 0) | Q20: =IFERROR(O20*P20, 0) | T20: =IFERROR(R20*S20, 0) | W20: =IFERROR(U20*V20, 0) | Z20: =IFERROR(X20*Y20, 0) | AC20: =IFERROR(AA20*AB20, 0) | AF20: =IFERROR(AD20*AE20, 0) | AI20: =IFERROR(AG20*AH20, 0) | AL20: =IFERROR(AJ20*AK20, 0) | AO20: =IFERROR(AM20*AN20, 0) | AP20: 86.7 | AQ20: 1800 | AR20: 156060 | AS20: 43.7 | AT20: 1600 | AU20: 69920 | AX20: =IFERROR(AV20*AW20, 0) | BA20: =IFERROR(AY20*AZ20, 0) | BD20: =IFERROR(BB20*BC20, 0) | BG20: =IFERROR(BE20*BF20, 0) | BJ20: =IFERROR(BH20*BI20, 0) | BM20: =IFERROR(BK20*BL20, 0) | BP20: =IFERROR(BN20*BO20, 0) | BS20: =IFERROR(BQ20*BR20, 0) | BV20: =IFERROR(BT20*BU20, 0) | BY20: =IFERROR(BW20*BX20, 0) | CB20: =IFERROR(BZ20*CA20, 0) | CE20: =IFERROR(CC20*CD20, 0) | CH20: =IFERROR(CF20*CG20, 0) | CK20: =IFERROR(CI20*CJ20, 0) | CN20: =IFERROR(CL20*CM20, 0) | CQ20: =IFERROR(CO20*CP20, 0) | CT20: =IFERROR(CR20*CS20, 0) | CU20: =IFERROR(SUM(F20,I20,L20,O20,R20,U20,X20,AA20,AD20,AG20,AJ20,AM20,AP20,AS20,AV20,AY20,BB20,BE20,BH20,BK20,BN20,BQ20,BT20,BW20,BZ20,CC20,CF20,CI20,CL20,CO20,CR20), 0) | CV20: =IFERROR(AVERAGE(G20,J20,M20,P20,S20,V20,Y20,AB20,AE20,AH20,AK20,AN20,AQ20,AT20,AW20,AZ20,BC20,BF20,BI20,BL20,BO20,BR20,BU20,BX20,CA20,CD20,CG20,CJ20,CM20,CP20,CS20), 0) | CW20: =CU20*CV20
A21: Platano guineo | B21: Kg | H21: =IFERROR(F21*G21, 0) | K21: =IFERROR(I21*J21, 0) | N21: =IFERROR(L21*M21, 0) | Q21: =IFERROR(O21*P21, 0) | T21: =IFERROR(R21*S21, 0) | W21: =IFERROR(U21*V21, 0) | Z21: =IFERROR(X21*Y21, 0) | AC21: =IFERROR(AA21*AB21, 0) | AF21: =IFERROR(AD21*AE21, 0) | AI21: =IFERROR(AG21*AH21, 0) | AL21: =IFERROR(AJ21*AK21, 0) | AO21: =IFERROR(AM21*AN21, 0) | AR21: =IFERROR(AP21*AQ21, 0) | AU21: =IFERROR(AS21*AT21, 0) | AX21: =IFERROR(AV21*AW21, 0) | BA21: =IFERROR(AY21*AZ21, 0) | BD21: =IFERROR(BB21*BC21, 0) | BG21: =IFERROR(BE21*BF21, 0) | BJ21: =IFERROR(BH21*BI21, 0) | BM21: =IFERROR(BK21*BL21, 0) | BP21: =IFERROR(BN21*BO21, 0) | BS21: =IFERROR(BQ21*BR21, 0) | BV21: =IFERROR(BT21*BU21, 0) | BY21: =IFERROR(BW21*BX21, 0) | CB21: =IFERROR(BZ21*CA21, 0) | CE21: =IFERROR(CC21*CD21, 0) | CH21: =IFERROR(CF21*CG21, 0) | CK21: =IFERROR(CI21*CJ21, 0) | CN21: =IFERROR(CL21*CM21, 0) | CQ21: =IFERROR(CO21*CP21, 0) | CT21: =IFERROR(CR21*CS21, 0) | CU21: =IFERROR(SUM(F21,I21,L21,O21,R21,U21,X21,AA21,AD21,AG21,AJ21,AM21,AP21,AS21,AV21,AY21,BB21,BE21,BH21,BK21,BN21,BQ21,BT21,BW21,BZ21,CC21,CF21,CI21,CL21,CO21,CR21), 0) | CV21: =IFERROR(AVERAGE(G21,J21,M21,P21,S21,V21,Y21,AB21,AE21,AH21,AK21,AN21,AQ21,AT21,AW21,AZ21,BC21,BF21,BI21,BL21,BO21,BR21,BU21,BX21,CA21,CD21,CG21,CJ21,CM21,CP21,CS21), 0) | CW21: =CU21*CV21
A22: Platano | B22: Kg | H22: =IFERROR(F22*G22, 0) | K22: =IFERROR(I22*J22, 0) | L22: 5.405 | M22: 3280 | N22: 17729 | Q22: =IFERROR(O22*P22, 0) | T22: =IFERROR(R22*S22, 0) | W22: =IFERROR(U22*V22, 0) | Z22: =IFERROR(X22*Y22, 0) | AC22: =IFERROR(AA22*AB22, 0) | AF22: =IFERROR(AD22*AE22, 0) | AI22: =IFERROR(AG22*AH22, 0) | AL22: =IFERROR(AJ22*AK22, 0) | AO22: =IFERROR(AM22*AN22, 0) | AR22: =IFERROR(AP22*AQ22, 0) | AU22: =IFERROR(AS22*AT22, 0) | AX22: =IFERROR(AV22*AW22, 0) | BA22: =IFERROR(AY22*AZ22, 0) | BD22: =IFERROR(BB22*BC22, 0) | BG22: =IFERROR(BE22*BF22, 0) | BJ22: =IFERROR(BH22*BI22, 0) | BK22: 1 | BL22: 70000 | BM22: 70000 | BP22: =IFERROR(BN22*BO22, 0) | BS22: =IFERROR(BQ22*BR22, 0) | BV22: =IFERROR(BT22*BU22, 0) | BY22: =IFERROR(BW22*BX22, 0) | CB22: =IFERROR(BZ22*CA22, 0) | CE22: =IFERROR(CC22*CD22, 0) | CH22: =IFERROR(CF22*CG22, 0) | CK22: =IFERROR(CI22*CJ22, 0) | CN22: =IFERROR(CL22*CM22, 0) | CQ22: =IFERROR(CO22*CP22, 0) | CT22: =IFERROR(CR22*CS22, 0) | CU22: =IFERROR(SUM(F22,I22,L22,O22,R22,U22,X22,AA22,AD22,AG22,AJ22,AM22,AP22,AS22,AV22,AY22,BB22,BE22,BH22,BK22,BN22,BQ22,BT22,BW22,BZ22,CC22,CF22,CI22,CL22,CO22,CR22), 0) | CV22: =IFERROR(AVERAGE(G22,J22,M22,P22,S22,V22,Y22,AB22,AE22,AH22,AK22,AN22,AQ22,AT22,AW22,AZ22,BC22,BF22,BI22,BL22,BO22,BR22,BU22,BX22,CA22,CD22,CG22,CJ22,CM22,CP22,CS22), 0) | CW22: =CU22*CV22
A23: Piña oromiel | B23: Kg | H23: =IFERROR(F23*G23, 0) | K23: =IFERROR(I23*J23, 0) | N23: =IFERROR(L23*M23, 0) | Q23: =IFERROR(O23*P23, 0) | T23: =IFERROR(R23*S23, 0) | W23: =IFERROR(U23*V23, 0) | Z23: =IFERROR(X23*Y23, 0) | AC23: =IFERROR(AA23*AB23, 0) | AF23: =IFERROR(AD23*AE23, 0) | AI23: =IFERROR(AG23*AH23, 0) | AL23: =IFERROR(AJ23*AK23, 0) | AO23: =IFERROR(AM23*AN23, 0) | AR23: =IFERROR(AP23*AQ23, 0) | AU23: =IFERROR(AS23*AT23, 0) | AX23: =IFERROR(AV23*AW23, 0) | BA23: =IFERROR(AY23*AZ23, 0) | BD23: =IFERROR(BB23*BC23, 0) | BG23: =IFERROR(BE23*BF23, 0) | BJ23: =IFERROR(BH23*BI23, 0) | BM23: =IFERROR(BK23*BL23, 0) | BP23: =IFERROR(BN23*BO23, 0) | BS23: =IFERROR(BQ23*BR23, 0) | BV23: =IFERROR(BT23*BU23, 0) | BY23: =IFERROR(BW23*BX23, 0) | CB23: =IFERROR(BZ23*CA23, 0) | CE23: =IFERROR(CC23*CD23, 0) | CH23: =IFERROR(CF23*CG23, 0) | CK23: =IFERROR(CI23*CJ23, 0) | CN23: =IFERROR(CL23*CM23, 0) | CQ23: =IFERROR(CO23*CP23, 0) | CT23: =IFERROR(CR23*CS23, 0) | CU23: =IFERROR(SUM(F23,I23,L23,O23,R23,U23,X23,AA23,AD23,AG23,AJ23,AM23,AP23,AS23,AV23,AY23,BB23,BE23,BH23,BK23,BN23,BQ23,BT23,BW23,BZ23,CC23,CF23,CI23,CL23,CO23,CR23), 0) | CV23: =IFERROR(AVERAGE(G23,J23,M23,P23,S23,V23,Y23,AB23,AE23,AH23,AK23,AN23,AQ23,AT23,AW23,AZ23,BC23,BF23,BI23,BL23,BO23,BR23,BU23,BX23,CA23,CD23,CG23,CJ23,CM23,CP23,CS23), 0) | CW23: =CU23*CV23
A24: Piña | B24: Kg | H24: =IFERROR(F24*G24, 0) | K24: =IFERROR(I24*J24, 0) | N24: =IFERROR(L24*M24, 0) | Q24: =IFERROR(O24*P24, 0) | T24: =IFERROR(R24*S24, 0) | W24: =IFERROR(U24*V24, 0) | Z24: =IFERROR(X24*Y24, 0) | AC24: =IFERROR(AA24*AB24, 0) | AF24: =IFERROR(AD24*AE24, 0) | AI24: =IFERROR(AG24*AH24, 0) | AL24: =IFERROR(AJ24*AK24, 0) | AO24: =IFERROR(AM24*AN24, 0) | AR24: =IFERROR(AP24*AQ24, 0) | AU24: =IFERROR(AS24*AT24, 0) | AX24: =IFERROR(AV24*AW24, 0) | BA24: =IFERROR(AY24*AZ24, 0) | BD24: =IFERROR(BB24*BC24, 0) | BG24: =IFERROR(BE24*BF24, 0) | BJ24: =IFERROR(BH24*BI24, 0) | BM24: =IFERROR(BK24*BL24, 0) | BP24: =IFERROR(BN24*BO24, 0) | BS24: =IFERROR(BQ24*BR24, 0) | BV24: =IFERROR(BT24*BU24, 0) | BY24: =IFERROR(BW24*BX24, 0) | CB24: =IFERROR(BZ24*CA24, 0) | CE24: =IFERROR(CC24*CD24, 0) | CH24: =IFERROR(CF24*CG24, 0) | CK24: =IFERROR(CI24*CJ24, 0) | CN24: =IFERROR(CL24*CM24, 0) | CQ24: =IFERROR(CO24*CP24, 0) | CT24: =IFERROR(CR24*CS24, 0) | CU24: =IFERROR(SUM(F24,I24,L24,O24,R24,U24,X24,AA24,AD24,AG24,AJ24,AM24,AP24,AS24,AV24,AY24,BB24,BE24,BH24,BK24,BN24,BQ24,BT24,BW24,BZ24,CC24,CF24,CI24,CL24,CO24,CR24), 0) | CV24: =IFERROR(AVERAGE(G24,J24,M24,P24,S24,V24,Y24,AB24,AE24,AH24,AK24,AN24,AQ24,AT24,AW24,AZ24,BC24,BF24,BI24,BL24,BO24,BR24,BU24,BX24,CA24,CD24,CG24,CJ24,CM24,CP24,CS24), 0) | CW24: =CU24*CV24
A25: Pimenton | B25: Kg | H25: =IFERROR(F25*G25, 0) | K25: =IFERROR(I25*J25, 0) | N25: =IFERROR(L25*M25, 0) | Q25: =IFERROR(O25*P25, 0) | T25: =IFERROR(R25*S25, 0) | W25: =IFERROR(U25*V25, 0) | Z25: =IFERROR(X25*Y25, 0) | AC25: =IFERROR(AA25*AB25, 0) | AF25: =IFERROR(AD25*AE25, 0) | AI25: =IFERROR(AG25*AH25, 0) | AL25: =IFERROR(AJ25*AK25, 0) | AO25: =IFERROR(AM25*AN25, 0) | AP25: 10.9 | AQ25: 3000 | AR25: 34150 | AS25: 1 | AT25: 35000 | AU25: 35000 | AX25: =IFERROR(AV25*AW25, 0) | BA25: =IFERROR(AY25*AZ25, 0) | BD25: =IFERROR(BB25*BC25, 0) | BG25: =IFERROR(BE25*BF25, 0) | BJ25: =IFERROR(BH25*BI25, 0) | BM25: =IFERROR(BK25*BL25, 0) | BN25: 5.5 | BO25: 3500 | BP25: 19250 | BS25: =IFERROR(BQ25*BR25, 0) | BV25: =IFERROR(BT25*BU25, 0) | BW25: 1 | BX25: 40000 | BY25: 40000 | CB25: =IFERROR(BZ25*CA25, 0) | CE25: =IFERROR(CC25*CD25, 0) | CH25: =IFERROR(CF25*CG25, 0) | CK25: =IFERROR(CI25*CJ25, 0) | CN25: =IFERROR(CL25*CM25, 0) | CQ25: =IFERROR(CO25*CP25, 0) | CT25: =IFERROR(CR25*CS25, 0) | CU25: =IFERROR(SUM(F25,I25,L25,O25,R25,U25,X25,AA25,AD25,AG25,AJ25,AM25,AP25,AS25,AV25,AY25,BB25,BE25,BH25,BK25,BN25,BQ25,BT25,BW25,BZ25,CC25,CF25,CI25,CL25,CO25,CR25), 0) | CV25: =IFERROR(AVERAGE(G25,J25,M25,P25,S25,V25,Y25,AB25,AE25,AH25,AK25,AN25,AQ25,AT25,AW25,AZ25,BC25,BF25,BI25,BL25,BO25,BR25,BU25,BX25,CA25,CD25,CG25,CJ25,CM25,CP25,CS25), 0) | CW25: =CU25*CV25
A26: Perejil | B26: Atado | H26: =IFERROR(F26*G26, 0) | K26: =IFERROR(I26*J26, 0) | N26: =IFERROR(L26*M26, 0) | Q26: =IFERROR(O26*P26, 0) | T26: =IFERROR(R26*S26, 0) | W26: =IFERROR(U26*V26, 0) | Z26: =IFERROR(X26*Y26, 0) | AC26: =IFERROR(AA26*AB26, 0) | AF26: =IFERROR(AD26*AE26, 0) | AI26: =IFERROR(AG26*AH26, 0) | AL26: =IFERROR(AJ26*AK26, 0) | AO26: =IFERROR(AM26*AN26, 0) | AP26: 2 | AQ26: 8000 | AR26: 16000 | AS26: 3 | AT26: 8000 | AU26: 24000 | AX26: =IFERROR(AV26*AW26, 0) | BA26: =IFERROR(AY26*AZ26, 0) | BD26: =IFERROR(BB26*BC26, 0) | BG26: =IFERROR(BE26*BF26, 0) | BJ26: =IFERROR(BH26*BI26, 0) | BM26: =IFERROR(BK26*BL26, 0) | BP26: =IFERROR(BN26*BO26, 0) | BS26: =IFERROR(BQ26*BR26, 0) | BV26: =IFERROR(BT26*BU26, 0) | BY26: =IFERROR(BW26*BX26, 0) | CB26: =IFERROR(BZ26*CA26, 0) | CE26: =IFERROR(CC26*CD26, 0) | CH26: =IFERROR(CF26*CG26, 0) | CK26: =IFERROR(CI26*CJ26, 0) | CN26: =IFERROR(CL26*CM26, 0) | CQ26: =IFERROR(CO26*CP26, 0) | CT26: =IFERROR(CR26*CS26, 0) | CU26: =IFERROR(SUM(F26,I26,L26,O26,R26,U26,X26,AA26,AD26,AG26,AJ26,AM26,AP26,AS26,AV26,AY26,BB26,BE26,BH26,BK26,BN26,BQ26,BT26,BW26,BZ26,CC26,CF26,CI26,CL26,CO26,CR26), 0) | CV26: =IFERROR(AVERAGE(G26,J26,M26,P26,S26,V26,Y26,AB26,AE26,AH26,AK26,AN26,AQ26,AT26,AW26,AZ26,BC26,BF26,BI26,BL26,BO26,BR26,BU26,BX26,CA26,CD26,CG26,CJ26,CM26,CP26,CS26), 0) | CW26: =CU26*CV26
A27: Pepino comun | B27: Kg | H27: =IFERROR(F27*G27, 0) | K27: =IFERROR(I27*J27, 0) | N27: =IFERROR(L27*M27, 0) | Q27: =IFERROR(O27*P27, 0) | T27: =IFERROR(R27*S27, 0) | W27: =IFERROR(U27*V27, 0) | Z27: =IFERROR(X27*Y27, 0) | AC27: =IFERROR(AA27*AB27, 0) | AF27: =IFERROR(AD27*AE27, 0) | AI27: =IFERROR(AG27*AH27, 0) | AL27: =IFERROR(AJ27*AK27, 0) | AO27: =IFERROR(AM27*AN27, 0) | AP27: 8.9 | AQ27: 1800 | AR27: 14400 | AS27: 5.5 | AT27: 1800 | AU27: 9900 | AX27: =IFERROR(AV27*AW27, 0) | BA27: =IFERROR(AY27*AZ27, 0) | BD27: =IFERROR(BB27*BC27, 0) | BG27: =IFERROR(BE27*BF27, 0) | BJ27: =IFERROR(BH27*BI27, 0) | BM27: =IFERROR(BK27*BL27, 0) | BN27: 3.5 | BO27: 1800 | BP27: 6300 | BS27: =IFERROR(BQ27*BR27, 0) | BV27: =IFERROR(BT27*BU27, 0) | BY27: =IFERROR(BW27*BX27, 0) | CB27: =IFERROR(BZ27*CA27, 0) | CE27: =IFERROR(CC27*CD27, 0) | CH27: =IFERROR(CF27*CG27, 0) | CK27: =IFERROR(CI27*CJ27, 0) | CN27: =IFERROR(CL27*CM27, 0) | CQ27: =IFERROR(CO27*CP27, 0) | CT27: =IFERROR(CR27*CS27, 0) | CU27: =IFERROR(SUM(F27,I27,L27,O27,R27,U27,X27,AA27,AD27,AG27,AJ27,AM27,AP27,AS27,AV27,AY27,BB27,BE27,BH27,BK27,BN27,BQ27,BT27,BW27,BZ27,CC27,CF27,CI27,CL27,CO27,CR27), 0) | CV27: =IFERROR(AVERAGE(G27,J27,M27,P27,S27,V27,Y27,AB27,AE27,AH27,AK27,AN27,AQ27,AT27,AW27,AZ27,BC27,BF27,BI27,BL27,BO27,BR27,BU27,BX27,CA27,CD27,CG27,CJ27,CM27,CP27,CS27), 0) | CW27: =CU27*CV27
A28: Papa potera kl | B28: Kg | H28: =IFERROR(F28*G28, 0) | K28: =IFERROR(I28*J28, 0) | N28: =IFERROR(L28*M28, 0) | Q28: =IFERROR(O28*P28, 0) | T28: =IFERROR(R28*S28, 0) | W28: =IFERROR(U28*V28, 0) | Z28: =IFERROR(X28*Y28, 0) | AC28: =IFERROR(AA28*AB28, 0) | AF28: =IFERROR(AD28*AE28, 0) | AI28: =IFERROR(AG28*AH28, 0) | AL28: =IFERROR(AJ28*AK28, 0) | AO28: =IFERROR(AM28*AN28, 0) | AR28: =IFERROR(AP28*AQ28, 0) | AU28: =IFERROR(AS28*AT28, 0) | AX28: =IFERROR(AV28*AW28, 0) | BA28: =IFERROR(AY28*AZ28, 0) | BD28: =IFERROR(BB28*BC28, 0) | BG28: =IFERROR(BE28*BF28, 0) | BJ28: =IFERROR(BH28*BI28, 0) | BM28: =IFERROR(BK28*BL28, 0) | BP28: =IFERROR(BN28*BO28, 0) | BS28: =IFERROR(BQ28*BR28, 0) | BV28: =IFERROR(BT28*BU28, 0) | BY28: =IFERROR(BW28*BX28, 0) | CB28: =IFERROR(BZ28*CA28, 0) | CE28: =IFERROR(CC28*CD28, 0) | CH28: =IFERROR(CF28*CG28, 0) | CK28: =IFERROR(CI28*CJ28, 0) | CN28: =IFERROR(CL28*CM28, 0) | CQ28: =IFERROR(CO28*CP28, 0) | CT28: =IFERROR(CR28*CS28, 0) | CU28: =IFERROR(SUM(F28,I28,L28,O28,R28,U28,X28,AA28,AD28,AG28,AJ28,AM28,AP28,AS28,AV28,AY28,BB28,BE28,BH28,BK28,BN28,BQ28,BT28,BW28,BZ28,CC28,CF28,CI28,CL28,CO28,CR28), 0) | CV28: =IFERROR(AVERAGE(G28,J28,M28,P28,S28,V28,Y28,AB28,AE28,AH28,AK28,AN28,AQ28,AT28,AW28,AZ28,BC28,BF28,BI28,BL28,BO28,BR28,BU28,BX28,CA28,CD28,CG28,CJ28,CM28,CP28,CS28), 0) | CW28: =CU28*CV28
A29: Papa pollera | B29: Kg | H29: =IFERROR(F29*G29, 0) | K29: =IFERROR(I29*J29, 0) | N29: =IFERROR(L29*M29, 0) | Q29: =IFERROR(O29*P29, 0) | T29: =IFERROR(R29*S29, 0) | W29: =IFERROR(U29*V29, 0) | Z29: =IFERROR(X29*Y29, 0) | AC29: =IFERROR(AA29*AB29, 0) | AF29: =IFERROR(AD29*AE29, 0) | AI29: =IFERROR(AG29*AH29, 0) | AL29: =IFERROR(AJ29*AK29, 0) | AO29: =IFERROR(AM29*AN29, 0) | AP29: 26.3 | AQ29: 2000 | AR29: 52600 | AS29: 30 | AT29: 2000 | AU29: 60000 | AX29: =IFERROR(AV29*AW29, 0) | BA29: =IFERROR(AY29*AZ29, 0) | BD29: =IFERROR(BB29*BC29, 0) | BG29: =IFERROR(BE29*BF29, 0) | BJ29: =IFERROR(BH29*BI29, 0) | BM29: =IFERROR(BK29*BL29, 0) | BP29: =IFERROR(BN29*BO29, 0) | BS29: =IFERROR(BQ29*BR29, 0) | BV29: =IFERROR(BT29*BU29, 0) | BY29: =IFERROR(BW29*BX29, 0) | CB29: =IFERROR(BZ29*CA29, 0) | CE29: =IFERROR(CC29*CD29, 0) | CH29: =IFERROR(CF29*CG29, 0) | CK29: =IFERROR(CI29*CJ29, 0) | CN29: =IFERROR(CL29*CM29, 0) | CQ29: =IFERROR(CO29*CP29, 0) | CT29: =IFERROR(CR29*CS29, 0) | CU29: =IFERROR(SUM(F29,I29,L29,O29,R29,U29,X29,AA29,AD29,AG29,AJ29,AM29,AP29,AS29,AV29,AY29,BB29,BE29,BH29,BK29,BN29,BQ29,BT29,BW29,BZ29,CC29,CF29,CI29,CL29,CO29,CR29), 0) | CV29: =IFERROR(AVERAGE(G29,J29,M29,P29,S29,V29,Y29,AB29,AE29,AH29,AK29,AN29,AQ29,AT29,AW29,AZ29,BC29,BF29,BI29,BL29,BO29,BR29,BU29,BX29,CA29,CD29,CG29,CJ29,CM29,CP29,CS29), 0) | CW29: =CU29*CV29
A30: Papa parda | B30: Kg | H30: =IFERROR(F30*G30, 0) | K30: =IFERROR(I30*J30, 0) | N30: =IFERROR(L30*M30, 0) | Q30: =IFERROR(O30*P30, 0) | T30: =IFERROR(R30*S30, 0) | W30: =IFERROR(U30*V30, 0) | Z30: =IFERROR(X30*Y30, 0) | AC30: =IFERROR(AA30*AB30, 0) | AF30: =IFERROR(AD30*AE30, 0) | AI30: =IFERROR(AG30*AH30, 0) | AL30: =IFERROR(AJ30*AK30, 0) | AO30: =IFERROR(AM30*AN30, 0) | AR30: =IFERROR(AP30*AQ30, 0) | AU30: =IFERROR(AS30*AT30, 0) | AX30: =IFERROR(AV30*AW30, 0) | BA30: =IFERROR(AY30*AZ30, 0) | BD30: =IFERROR(BB30*BC30, 0) | BG30: =IFERROR(BE30*BF30, 0) | BJ30: =IFERROR(BH30*BI30, 0) | BM30: =IFERROR(BK30*BL30, 0) | BP30: =IFERROR(BN30*BO30, 0) | BS30: =IFERROR(BQ30*BR30, 0) | BV30: =IFERROR(BT30*BU30, 0) | BY30: =IFERROR(BW30*BX30, 0) | CB30: =IFERROR(BZ30*CA30, 0) | CE30: =IFERROR(CC30*CD30, 0) | CH30: =IFERROR(CF30*CG30, 0) | CK30: =IFERROR(CI30*CJ30, 0) | CN30: =IFERROR(CL30*CM30, 0) | CQ30: =IFERROR(CO30*CP30, 0) | CT30: =IFERROR(CR30*CS30, 0) | CU30: =IFERROR(SUM(F30,I30,L30,O30,R30,U30,X30,AA30,AD30,AG30,AJ30,AM30,AP30,AS30,AV30,AY30,BB30,BE30,BH30,BK30,BN30,BQ30,BT30,BW30,BZ30,CC30,CF30,CI30,CL30,CO30,CR30), 0) | CV30: =IFERROR(AVERAGE(G30,J30,M30,P30,S30,V30,Y30,AB30,AE30,AH30,AK30,AN30,AQ30,AT30,AW30,AZ30,BC30,BF30,BI30,BL30,BO30,BR30,BU30,BX30,CA30,CD30,CG30,CJ30,CM30,CP30,CS30), 0) | CW30: =CU30*CV30
A31: Papa manbera | B31: Kg | H31: =IFERROR(F31*G31, 0) | K31: =IFERROR(I31*J31, 0) | N31: =IFERROR(L31*M31, 0) | Q31: =IFERROR(O31*P31, 0) | T31: =IFERROR(R31*S31, 0) | W31: =IFERROR(U31*V31, 0) | Z31: =IFERROR(X31*Y31, 0) | AC31: =IFERROR(AA31*AB31, 0) | AF31: =IFERROR(AD31*AE31, 0) | AI31: =IFERROR(AG31*AH31, 0) | AL31: =IFERROR(AJ31*AK31, 0) | AO31: =IFERROR(AM31*AN31, 0) | AR31: =IFERROR(AP31*AQ31, 0) | AU31: =IFERROR(AS31*AT31, 0) | AX31: =IFERROR(AV31*AW31, 0) | BA31: =IFERROR(AY31*AZ31, 0) | BD31: =IFERROR(BB31*BC31, 0) | BG31: =IFERROR(BE31*BF31, 0) | BJ31: =IFERROR(BH31*BI31, 0) | BM31: =IFERROR(BK31*BL31, 0) | BN31: 6.7 | BO31: 3500 | BP31: 23450 | BS31: =IFERROR(BQ31*BR31, 0) | BV31: =IFERROR(BT31*BU31, 0) | BY31: =IFERROR(BW31*BX31, 0) | CB31: =IFERROR(BZ31*CA31, 0) | CE31: =IFERROR(CC31*CD31, 0) | CH31: =IFERROR(CF31*CG31, 0) | CK31: =IFERROR(CI31*CJ31, 0) | CN31: =IFERROR(CL31*CM31, 0) | CQ31: =IFERROR(CO31*CP31, 0) | CT31: =IFERROR(CR31*CS31, 0) | CU31: =IFERROR(SUM(F31,I31,L31,O31,R31,U31,X31,AA31,AD31,AG31,AJ31,AM31,AP31,AS31,AV31,AY31,BB31,BE31,BH31,BK31,BN31,BQ31,BT31,BW31,BZ31,CC31,CF31,CI31,CL31,CO31,CR31), 0) | CV31: =IFERROR(AVERAGE(G31,J31,M31,P31,S31,V31,Y31,AB31,AE31,AH31,AK31,AN31,AQ31,AT31,AW31,AZ31,BC31,BF31,BI31,BL31,BO31,BR31,BU31,BX31,CA31,CD31,CG31,CJ31,CM31,CP31,CS31), 0) | CW31: =CU31*CV31
A32: Papa lavada | B32: Kg | H32: =IFERROR(F32*G32, 0) | K32: =IFERROR(I32*J32, 0) | N32: =IFERROR(L32*M32, 0) | Q32: =IFERROR(O32*P32, 0) | T32: =IFERROR(R32*S32, 0) | W32: =IFERROR(U32*V32, 0) | Z32: =IFERROR(X32*Y32, 0) | AC32: =IFERROR(AA32*AB32, 0) | AF32: =IFERROR(AD32*AE32, 0) | AI32: =IFERROR(AG32*AH32, 0) | AL32: =IFERROR(AJ32*AK32, 0) | AO32: =IFERROR(AM32*AN32, 0) | AR32: =IFERROR(AP32*AQ32, 0) | AU32: =IFERROR(AS32*AT32, 0) | AX32: =IFERROR(AV32*AW32, 0) | BA32: =IFERROR(AY32*AZ32, 0) | BD32: =IFERROR(BB32*BC32, 0) | BG32: =IFERROR(BE32*BF32, 0) | BJ32: =IFERROR(BH32*BI32, 0) | BM32: =IFERROR(BK32*BL32, 0) | BP32: =IFERROR(BN32*BO32, 0) | BS32: =IFERROR(BQ32*BR32, 0) | BV32: =IFERROR(BT32*BU32, 0) | BY32: =IFERROR(BW32*BX32, 0) | CB32: =IFERROR(BZ32*CA32, 0) | CE32: =IFERROR(CC32*CD32, 0) | CH32: =IFERROR(CF32*CG32, 0) | CK32: =IFERROR(CI32*CJ32, 0) | CN32: =IFERROR(CL32*CM32, 0) | CQ32: =IFERROR(CO32*CP32, 0) | CT32: =IFERROR(CR32*CS32, 0) | CU32: =IFERROR(SUM(F32,I32,L32,O32,R32,U32,X32,AA32,AD32,AG32,AJ32,AM32,AP32,AS32,AV32,AY32,BB32,BE32,BH32,BK32,BN32,BQ32,BT32,BW32,BZ32,CC32,CF32,CI32,CL32,CO32,CR32), 0) | CV32: =IFERROR(AVERAGE(G32,J32,M32,P32,S32,V32,Y32,AB32,AE32,AH32,AK32,AN32,AQ32,AT32,AW32,AZ32,BC32,BF32,BI32,BL32,BO32,BR32,BU32,BX32,CA32,CD32,CG32,CJ32,CM32,CP32,CS32), 0) | CW32: =CU32*CV32
A33: Papa cero | B33: Bulto | H33: =IFERROR(F33*G33, 0) | K33: =IFERROR(I33*J33, 0) | N33: =IFERROR(L33*M33, 0) | Q33: =IFERROR(O33*P33, 0) | T33: =IFERROR(R33*S33, 0) | W33: =IFERROR(U33*V33, 0) | Z33: =IFERROR(X33*Y33, 0) | AC33: =IFERROR(AA33*AB33, 0) | AF33: =IFERROR(AD33*AE33, 0) | AI33: =IFERROR(AG33*AH33, 0) | AL33: =IFERROR(AJ33*AK33, 0) | AO33: =IFERROR(AM33*AN33, 0) | AR33: =IFERROR(AP33*AQ33, 0) | AU33: =IFERROR(AS33*AT33, 0) | AX33: =IFERROR(AV33*AW33, 0) | BA33: =IFERROR(AY33*AZ33, 0) | BD33: =IFERROR(BB33*BC33, 0) | BG33: =IFERROR(BE33*BF33, 0) | BJ33: =IFERROR(BH33*BI33, 0) | BM33: =IFERROR(BK33*BL33, 0) | BP33: =IFERROR(BN33*BO33, 0) | BS33: =IFERROR(BQ33*BR33, 0) | BV33: =IFERROR(BT33*BU33, 0) | BY33: =IFERROR(BW33*BX33, 0) | CB33: =IFERROR(BZ33*CA33, 0) | CE33: =IFERROR(CC33*CD33, 0) | CH33: =IFERROR(CF33*CG33, 0) | CK33: =IFERROR(CI33*CJ33, 0) | CN33: =IFERROR(CL33*CM33, 0) | CQ33: =IFERROR(CO33*CP33, 0) | CT33: =IFERROR(CR33*CS33, 0) | CU33: =IFERROR(SUM(F33,I33,L33,O33,R33,U33,X33,AA33,AD33,AG33,AJ33,AM33,AP33,AS33,AV33,AY33,BB33,BE33,BH33,BK33,BN33,BQ33,BT33,BW33,BZ33,CC33,CF33,CI33,CL33,CO33,CR33), 0) | CV33: =IFERROR(AVERAGE(G33,J33,M33,P33,S33,V33,Y33,AB33,AE33,AH33,AK33,AN33,AQ33,AT33,AW33,AZ33,BC33,BF33,BI33,BL33,BO33,BR33,BU33,BX33,CA33,CD33,CG33,CJ33,CM33,CP33,CS33), 0) | CW33: =CU33*CV33
A34: Papa Capira bulto | B34: Bulto | H34: =IFERROR(F34*G34, 0) | K34: =IFERROR(I34*J34, 0) | N34: =IFERROR(L34*M34, 0) | Q34: =IFERROR(O34*P34, 0) | T34: =IFERROR(R34*S34, 0) | W34: =IFERROR(U34*V34, 0) | Z34: =IFERROR(X34*Y34, 0) | AC34: =IFERROR(AA34*AB34, 0) | AF34: =IFERROR(AD34*AE34, 0) | AI34: =IFERROR(AG34*AH34, 0) | AL34: =IFERROR(AJ34*AK34, 0) | AO34: =IFERROR(AM34*AN34, 0) | AP34: 1.5 | AQ34: 100000 | AR34: 140000 | AS34: 1 | AT34: 110000 | AU34: 105000 | AX34: =IFERROR(AV34*AW34, 0) | BA34: =IFERROR(AY34*AZ34, 0) | BD34: =IFERROR(BB34*BC34, 0) | BG34: =IFERROR(BE34*BF34, 0) | BJ34: =IFERROR(BH34*BI34, 0) | BM34: =IFERROR(BK34*BL34, 0) | BN34: 0.5 | BO34: 100000 | BP34: 50000 | BS34: =IFERROR(BQ34*BR34, 0) | BV34: =IFERROR(BT34*BU34, 0) | BY34: =IFERROR(BW34*BX34, 0) | CB34: =IFERROR(BZ34*CA34, 0) | CE34: =IFERROR(CC34*CD34, 0) | CH34: =IFERROR(CF34*CG34, 0) | CK34: =IFERROR(CI34*CJ34, 0) | CN34: =IFERROR(CL34*CM34, 0) | CQ34: =IFERROR(CO34*CP34, 0) | CT34: =IFERROR(CR34*CS34, 0) | CU34: =IFERROR(SUM(F34,I34,L34,O34,R34,U34,X34,AA34,AD34,AG34,AJ34,AM34,AP34,AS34,AV34,AY34,BB34,BE34,BH34,BK34,BN34,BQ34,BT34,BW34,BZ34,CC34,CF34,CI34,CL34,CO34,CR34), 0) | CV34: =IFERROR(AVERAGE(G34,J34,M34,P34,S34,V34,Y34,AB34,AE34,AH34,AK34,AN34,AQ34,AT34,AW34,AZ34,BC34,BF34,BI34,BL34,BO34,BR34,BU34,BX34,CA34,CD34,CG34,CJ34,CM34,CP34,CS34), 0) | CW34: =CU34*CV34
A35: Papa capira | B35: Bulto | H35: =IFERROR(F35*G35, 0) | K35: =IFERROR(I35*J35, 0) | N35: =IFERROR(L35*M35, 0) | Q35: =IFERROR(O35*P35, 0) | T35: =IFERROR(R35*S35, 0) | W35: =IFERROR(U35*V35, 0) | Z35: =IFERROR(X35*Y35, 0) | AC35: =IFERROR(AA35*AB35, 0) | AF35: =IFERROR(AD35*AE35, 0) | AI35: =IFERROR(AG35*AH35, 0) | AL35: =IFERROR(AJ35*AK35, 0) | AO35: =IFERROR(AM35*AN35, 0) | AR35: =IFERROR(AP35*AQ35, 0) | AU35: =IFERROR(AS35*AT35, 0) | AX35: =IFERROR(AV35*AW35, 0) | BA35: =IFERROR(AY35*AZ35, 0) | BD35: =IFERROR(BB35*BC35, 0) | BG35: =IFERROR(BE35*BF35, 0) | BJ35: =IFERROR(BH35*BI35, 0) | BM35: =IFERROR(BK35*BL35, 0) | BP35: =IFERROR(BN35*BO35, 0) | BS35: =IFERROR(BQ35*BR35, 0) | BV35: =IFERROR(BT35*BU35, 0) | BY35: =IFERROR(BW35*BX35, 0) | CB35: =IFERROR(BZ35*CA35, 0) | CE35: =IFERROR(CC35*CD35, 0) | CH35: =IFERROR(CF35*CG35, 0) | CK35: =IFERROR(CI35*CJ35, 0) | CN35: =IFERROR(CL35*CM35, 0) | CQ35: =IFERROR(CO35*CP35, 0) | CT35: =IFERROR(CR35*CS35, 0) | CU35: =IFERROR(SUM(F35,I35,L35,O35,R35,U35,X35,AA35,AD35,AG35,AJ35,AM35,AP35,AS35,AV35,AY35,BB35,BE35,BH35,BK35,BN35,BQ35,BT35,BW35,BZ35,CC35,CF35,CI35,CL35,CO35,CR35), 0) | CV35: =IFERROR(AVERAGE(G35,J35,M35,P35,S35,V35,Y35,AB35,AE35,AH35,AK35,AN35,AQ35,AT35,AW35,AZ35,BC35,BF35,BI35,BL35,BO35,BR35,BU35,BX35,CA35,CD35,CG35,CJ35,CM35,CP35,CS35), 0) | CW35: =CU35*CV35
A36: Papa amarilla | B36: Kg | H36: =IFERROR(F36*G36, 0) | I36: 1 | J36: 4000 | K36: 4000 | N36: =IFERROR(L36*M36, 0) | Q36: =IFERROR(O36*P36, 0) | T36: =IFERROR(R36*S36, 0) | U36: 2.075 | V36: 8800 | W36: 18260 | Z36: =IFERROR(X36*Y36, 0) | AC36: =IFERROR(AA36*AB36, 0) | AF36: =IFERROR(AD36*AE36, 0) | AI36: =IFERROR(AG36*AH36, 0) | AL36: =IFERROR(AJ36*AK36, 0) | AO36: =IFERROR(AM36*AN36, 0) | AP36: 4.3 | AQ36: 5500 | AR36: 23650 | AS36: 8 | AT36: 5800 | AU36: 45080 | AX36: =IFERROR(AV36*AW36, 0) | BA36: =IFERROR(AY36*AZ36, 0) | BD36: =IFERROR(BB36*BC36, 0) | BG36: =IFERROR(BE36*BF36, 0) | BJ36: =IFERROR(BH36*BI36, 0) | BM36: =IFERROR(BK36*BL36, 0) | BN36: 13.4 | BO36: 5500 | BP36: 74600 | BS36: =IFERROR(BQ36*BR36, 0) | BV36: =IFERROR(BT36*BU36, 0) | BY36: =IFERROR(BW36*BX36, 0) | CB36: =IFERROR(BZ36*CA36, 0) | CE36: =IFERROR(CC36*CD36, 0) | CH36: =IFERROR(CF36*CG36, 0) | CK36: =IFERROR(CI36*CJ36, 0) | CN36: =IFERROR(CL36*CM36, 0) | CQ36: =IFERROR(CO36*CP36, 0) | CT36: =IFERROR(CR36*CS36, 0) | CU36: =IFERROR(SUM(F36,I36,L36,O36,R36,U36,X36,AA36,AD36,AG36,AJ36,AM36,AP36,AS36,AV36,AY36,BB36,BE36,BH36,BK36,BN36,BQ36,BT36,BW36,BZ36,CC36,CF36,CI36,CL36,CO36,CR36), 0) | CV36: =IFERROR(AVERAGE(G36,J36,M36,P36,S36,V36,Y36,AB36,AE36,AH36,AK36,AN36,AQ36,AT36,AW36,AZ36,BC36,BF36,BI36,BL36,BO36,BR36,BU36,BX36,CA36,CD36,CG36,CJ36,CM36,CP36,CS36), 0) | CW36: =CU36*CV36
A37: Papa a la francesa paq 2.5 kl | B37: Kl | H37: =IFERROR(F37*G37, 0) | I37: 8 | J37: 15546.25 | K37: 124370 | N37: =IFERROR(L37*M37, 0) | O37: 8 | P37: 15546.25 | Q37: 124370 | T37: =IFERROR(R37*S37, 0) | W37: =IFERROR(U37*V37, 0) | X37: 8 | Y37: 15546.25 | Z37: 124370 | AC37: =IFERROR(AA37*AB37, 0) | AF37: =IFERROR(AD37*AE37, 0) | AG37: 8 | AH37: 15546.25 | AI37: 124370 | AL37: =IFERROR(AJ37*AK37, 0) | AO37: =IFERROR(AM37*AN37, 0) | AR37: =IFERROR(AP37*AQ37, 0) | AU37: =IFERROR(AS37*AT37, 0) | AV37: 12 | AW37: 16386.58 | AX37: 196639 | BA37: =IFERROR(AY37*AZ37, 0) | BB37: 12 | BC37: 16386.58 | BD37: 196639 | BG37: =IFERROR(BE37*BF37, 0) | BJ37: =IFERROR(BH37*BI37, 0) | BM37: =IFERROR(BK37*BL37, 0) | BP37: =IFERROR(BN37*BO37, 0) | BS37: =IFERROR(BQ37*BR37, 0) | BV37: =IFERROR(BT37*BU37, 0) | BY37: =IFERROR(BW37*BX37, 0) | CB37: =IFERROR(BZ37*CA37, 0) | CE37: =IFERROR(CC37*CD37, 0) | CH37: =IFERROR(CF37*CG37, 0) | CK37: =IFERROR(CI37*CJ37, 0) | CN37: =IFERROR(CL37*CM37, 0) | CQ37: =IFERROR(CO37*CP37, 0) | CT37: =IFERROR(CR37*CS37, 0) | CU37: =IFERROR(SUM(F37,I37,L37,O37,R37,U37,X37,AA37,AD37,AG37,AJ37,AM37,AP37,AS37,AV37,AY37,BB37,BE37,BH37,BK37,BN37,BQ37,BT37,BW37,BZ37,CC37,CF37,CI37,CL37,CO37,CR37), 0) | CV37: =IFERROR(AVERAGE(G37,J37,M37,P37,S37,V37,Y37,AB37,AE37,AH37,AK37,AN37,AQ37,AT37,AW37,AZ37,BC37,BF37,BI37,BL37,BO37,BR37,BU37,BX37,CA37,CD37,CG37,CJ37,CM37,CP37,CS37), 0) | CW37: =CU37*CV37
A38: Olluco | B38: Kg | H38: =IFERROR(F38*G38, 0) | K38: =IFERROR(I38*J38, 0) | N38: =IFERROR(L38*M38, 0) | Q38: =IFERROR(O38*P38, 0) | T38: =IFERROR(R38*S38, 0) | W38: =IFERROR(U38*V38, 0) | Z38: =IFERROR(X38*Y38, 0) | AC38: =IFERROR(AA38*AB38, 0) | AF38: =IFERROR(AD38*AE38, 0) | AI38: =IFERROR(AG38*AH38, 0) | AL38: =IFERROR(AJ38*AK38, 0) | AO38: =IFERROR(AM38*AN38, 0) | AR38: =IFERROR(AP38*AQ38, 0) | AU38: =IFERROR(AS38*AT38, 0) | AX38: =IFERROR(AV38*AW38, 0) | BA38: =IFERROR(AY38*AZ38, 0) | BD38: =IFERROR(BB38*BC38, 0) | BG38: =IFERROR(BE38*BF38, 0) | BJ38: =IFERROR(BH38*BI38, 0) | BM38: =IFERROR(BK38*BL38, 0) | BP38: =IFERROR(BN38*BO38, 0) | BS38: =IFERROR(BQ38*BR38, 0) | BV38: =IFERROR(BT38*BU38, 0) | BY38: =IFERROR(BW38*BX38, 0) | CB38: =IFERROR(BZ38*CA38, 0) | CE38: =IFERROR(CC38*CD38, 0) | CH38: =IFERROR(CF38*CG38, 0) | CK38: =IFERROR(CI38*CJ38, 0) | CN38: =IFERROR(CL38*CM38, 0) | CQ38: =IFERROR(CO38*CP38, 0) | CT38: =IFERROR(CR38*CS38, 0) | CU38: =IFERROR(SUM(F38,I38,L38,O38,R38,U38,X38,AA38,AD38,AG38,AJ38,AM38,AP38,AS38,AV38,AY38,BB38,BE38,BH38,BK38,BN38,BQ38,BT38,BW38,BZ38,CC38,CF38,CI38,CL38,CO38,CR38), 0) | CV38: =IFERROR(AVERAGE(G38,J38,M38,P38,S38,V38,Y38,AB38,AE38,AH38,AK38,AN38,AQ38,AT38,AW38,AZ38,BC38,BF38,BI38,BL38,BO38,BR38,BU38,BX38,CA38,CD38,CG38,CJ38,CM38,CP38,CS38), 0) | CW38: =CU38*CV38
A39: Melon | B39: Kg | H39: =IFERROR(F39*G39, 0) | K39: =IFERROR(I39*J39, 0) | N39: =IFERROR(L39*M39, 0) | Q39: =IFERROR(O39*P39, 0) | T39: =IFERROR(R39*S39, 0) | W39: =IFERROR(U39*V39, 0) | Z39: =IFERROR(X39*Y39, 0) | AC39: =IFERROR(AA39*AB39, 0) | AF39: =IFERROR(AD39*AE39, 0) | AI39: =IFERROR(AG39*AH39, 0) | AL39: =IFERROR(AJ39*AK39, 0) | AO39: =IFERROR(AM39*AN39, 0) | AR39: =IFERROR(AP39*AQ39, 0) | AU39: =IFERROR(AS39*AT39, 0) | AX39: =IFERROR(AV39*AW39, 0) | BA39: =IFERROR(AY39*AZ39, 0) | BD39: =IFERROR(BB39*BC39, 0) | BG39: =IFERROR(BE39*BF39, 0) | BJ39: =IFERROR(BH39*BI39, 0) | BM39: =IFERROR(BK39*BL39, 0) | BP39: =IFERROR(BN39*BO39, 0) | BS39: =IFERROR(BQ39*BR39, 0) | BV39: =IFERROR(BT39*BU39, 0) | BY39: =IFERROR(BW39*BX39, 0) | CB39: =IFERROR(BZ39*CA39, 0) | CE39: =IFERROR(CC39*CD39, 0) | CH39: =IFERROR(CF39*CG39, 0) | CK39: =IFERROR(CI39*CJ39, 0) | CN39: =IFERROR(CL39*CM39, 0) | CQ39: =IFERROR(CO39*CP39, 0) | CT39: =IFERROR(CR39*CS39, 0) | CU39: =IFERROR(SUM(F39,I39,L39,O39,R39,U39,X39,AA39,AD39,AG39,AJ39,AM39,AP39,AS39,AV39,AY39,BB39,BE39,BH39,BK39,BN39,BQ39,BT39,BW39,BZ39,CC39,CF39,CI39,CL39,CO39,CR39), 0) | CV39: =IFERROR(AVERAGE(G39,J39,M39,P39,S39,V39,Y39,AB39,AE39,AH39,AK39,AN39,AQ39,AT39,AW39,AZ39,BC39,BF39,BI39,BL39,BO39,BR39,BU39,BX39,CA39,CD39,CG39,CJ39,CM39,CP39,CS39), 0) | CW39: =CU39*CV39
A40: Mazorca Bulto | B40: Kg | H40: =IFERROR(F40*G40, 0) | K40: =IFERROR(I40*J40, 0) | N40: =IFERROR(L40*M40, 0) | Q40: =IFERROR(O40*P40, 0) | T40: =IFERROR(R40*S40, 0) | W40: =IFERROR(U40*V40, 0) | Z40: =IFERROR(X40*Y40, 0) | AC40: =IFERROR(AA40*AB40, 0) | AF40: =IFERROR(AD40*AE40, 0) | AI40: =IFERROR(AG40*AH40, 0) | AL40: =IFERROR(AJ40*AK40, 0) | AO40: =IFERROR(AM40*AN40, 0) | AR40: =IFERROR(AP40*AQ40, 0) | AU40: =IFERROR(AS40*AT40, 0) | AX40: =IFERROR(AV40*AW40, 0) | BA40: =IFERROR(AY40*AZ40, 0) | BD40: =IFERROR(BB40*BC40, 0) | BG40: =IFERROR(BE40*BF40, 0) | BJ40: =IFERROR(BH40*BI40, 0) | BM40: =IFERROR(BK40*BL40, 0) | BP40: =IFERROR(BN40*BO40, 0) | BS40: =IFERROR(BQ40*BR40, 0) | BV40: =IFERROR(BT40*BU40, 0) | BY40: =IFERROR(BW40*BX40, 0) | CB40: =IFERROR(BZ40*CA40, 0) | CE40: =IFERROR(CC40*CD40, 0) | CH40: =IFERROR(CF40*CG40, 0) | CK40: =IFERROR(CI40*CJ40, 0) | CN40: =IFERROR(CL40*CM40, 0) | CQ40: =IFERROR(CO40*CP40, 0) | CT40: =IFERROR(CR40*CS40, 0) | CU40: =IFERROR(SUM(F40,I40,L40,O40,R40,U40,X40,AA40,AD40,AG40,AJ40,AM40,AP40,AS40,AV40,AY40,BB40,BE40,BH40,BK40,BN40,BQ40,BT40,BW40,BZ40,CC40,CF40,CI40,CL40,CO40,CR40), 0) | CV40: =IFERROR(AVERAGE(G40,J40,M40,P40,S40,V40,Y40,AB40,AE40,AH40,AK40,AN40,AQ40,AT40,AW40,AZ40,BC40,BF40,BI40,BL40,BO40,BR40,BU40,BX40,CA40,CD40,CG40,CJ40,CM40,CP40,CS40), 0) | CW40: =CU40*CV40
A41: Mazorca | B41: Bulto | F41: 1 | G41: 15000 | H41: 15000 | K41: =IFERROR(I41*J41, 0) | N41: =IFERROR(L41*M41, 0) | Q41: =IFERROR(O41*P41, 0) | T41: =IFERROR(R41*S41, 0) | W41: =IFERROR(U41*V41, 0) | Z41: =IFERROR(X41*Y41, 0) | AC41: =IFERROR(AA41*AB41, 0) | AF41: =IFERROR(AD41*AE41, 0) | AI41: =IFERROR(AG41*AH41, 0) | AL41: =IFERROR(AJ41*AK41, 0) | AO41: =IFERROR(AM41*AN41, 0) | AP41: 30 | AQ41: 1000 | AR41: 30000 | AS41: 30 | AT41: 1000 | AU41: 30000 | AX41: =IFERROR(AV41*AW41, 0) | BA41: =IFERROR(AY41*AZ41, 0) | BD41: =IFERROR(BB41*BC41, 0) | BG41: =IFERROR(BE41*BF41, 0) | BJ41: =IFERROR(BH41*BI41, 0) | BM41: =IFERROR(BK41*BL41, 0) | BN41: 30 | BO41: 1000 | BP41: 30000 | BS41: =IFERROR(BQ41*BR41, 0) | BV41: =IFERROR(BT41*BU41, 0) | BY41: =IFERROR(BW41*BX41, 0) | CB41: =IFERROR(BZ41*CA41, 0) | CE41: =IFERROR(CC41*CD41, 0) | CH41: =IFERROR(CF41*CG41, 0) | CK41: =IFERROR(CI41*CJ41, 0) | CN41: =IFERROR(CL41*CM41, 0) | CQ41: =IFERROR(CO41*CP41, 0) | CT41: =IFERROR(CR41*CS41, 0) | CU41: =IFERROR(SUM(F41,I41,L41,O41,R41,U41,X41,AA41,AD41,AG41,AJ41,AM41,AP41,AS41,AV41,AY41,BB41,BE41,BH41,BK41,BN41,BQ41,BT41,BW41,BZ41,CC41,CF41,CI41,CL41,CO41,CR41), 0) | CV41: =IFERROR(AVERAGE(G41,J41,M41,P41,S41,V41,Y41,AB41,AE41,AH41,AK41,AN41,AQ41,AT41,AW41,AZ41,BC41,BF41,BI41,BL41,BO41,BR41,BU41,BX41,CA41,CD41,CG41,CJ41,CM41,CP41,CS41), 0) | CW41: =CU41*CV41
A42: Maza de tamal | B42: Kg | H42: =IFERROR(F42*G42, 0) | K42: =IFERROR(I42*J42, 0) | N42: =IFERROR(L42*M42, 0) | Q42: =IFERROR(O42*P42, 0) | T42: =IFERROR(R42*S42, 0) | W42: =IFERROR(U42*V42, 0) | Z42: =IFERROR(X42*Y42, 0) | AC42: =IFERROR(AA42*AB42, 0) | AF42: =IFERROR(AD42*AE42, 0) | AI42: =IFERROR(AG42*AH42, 0) | AL42: =IFERROR(AJ42*AK42, 0) | AO42: =IFERROR(AM42*AN42, 0) | AR42: =IFERROR(AP42*AQ42, 0) | AU42: =IFERROR(AS42*AT42, 0) | AX42: =IFERROR(AV42*AW42, 0) | BA42: =IFERROR(AY42*AZ42, 0) | BD42: =IFERROR(BB42*BC42, 0) | BG42: =IFERROR(BE42*BF42, 0) | BJ42: =IFERROR(BH42*BI42, 0) | BM42: =IFERROR(BK42*BL42, 0) | BP42: =IFERROR(BN42*BO42, 0) | BS42: =IFERROR(BQ42*BR42, 0) | BV42: =IFERROR(BT42*BU42, 0) | BY42: =IFERROR(BW42*BX42, 0) | CB42: =IFERROR(BZ42*CA42, 0) | CE42: =IFERROR(CC42*CD42, 0) | CH42: =IFERROR(CF42*CG42, 0) | CK42: =IFERROR(CI42*CJ42, 0) | CN42: =IFERROR(CL42*CM42, 0) | CQ42: =IFERROR(CO42*CP42, 0) | CT42: =IFERROR(CR42*CS42, 0) | CU42: =IFERROR(SUM(F42,I42,L42,O42,R42,U42,X42,AA42,AD42,AG42,AJ42,AM42,AP42,AS42,AV42,AY42,BB42,BE42,BH42,BK42,BN42,BQ42,BT42,BW42,BZ42,CC42,CF42,CI42,CL42,CO42,CR42), 0) | CV42: =IFERROR(AVERAGE(G42,J42,M42,P42,S42,V42,Y42,AB42,AE42,AH42,AK42,AN42,AQ42,AT42,AW42,AZ42,BC42,BF42,BI42,BL42,BO42,BR42,BU42,BX42,CA42,CD42,CG42,CJ42,CM42,CP42,CS42), 0) | CW42: =CU42*CV42
A43: Manzana | B43: Kg | H43: =IFERROR(F43*G43, 0) | K43: =IFERROR(I43*J43, 0) | N43: =IFERROR(L43*M43, 0) | Q43: =IFERROR(O43*P43, 0) | T43: =IFERROR(R43*S43, 0) | W43: =IFERROR(U43*V43, 0) | Z43: =IFERROR(X43*Y43, 0) | AC43: =IFERROR(AA43*AB43, 0) | AF43: =IFERROR(AD43*AE43, 0) | AI43: =IFERROR(AG43*AH43, 0) | AL43: =IFERROR(AJ43*AK43, 0) | AO43: =IFERROR(AM43*AN43, 0) | AR43: =IFERROR(AP43*AQ43, 0) | AU43: =IFERROR(AS43*AT43, 0) | AX43: =IFERROR(AV43*AW43, 0) | BA43: =IFERROR(AY43*AZ43, 0) | BD43: =IFERROR(BB43*BC43, 0) | BG43: =IFERROR(BE43*BF43, 0) | BJ43: =IFERROR(BH43*BI43, 0) | BM43: =IFERROR(BK43*BL43, 0) | BP43: =IFERROR(BN43*BO43, 0) | BS43: =IFERROR(BQ43*BR43, 0) | BV43: =IFERROR(BT43*BU43, 0) | BY43: =IFERROR(BW43*BX43, 0) | CB43: =IFERROR(BZ43*CA43, 0) | CE43: =IFERROR(CC43*CD43, 0) | CH43: =IFERROR(CF43*CG43, 0) | CK43: =IFERROR(CI43*CJ43, 0) | CN43: =IFERROR(CL43*CM43, 0) | CQ43: =IFERROR(CO43*CP43, 0) | CT43: =IFERROR(CR43*CS43, 0) | CU43: =IFERROR(SUM(F43,I43,L43,O43,R43,U43,X43,AA43,AD43,AG43,AJ43,AM43,AP43,AS43,AV43,AY43,BB43,BE43,BH43,BK43,BN43,BQ43,BT43,BW43,BZ43,CC43,CF43,CI43,CL43,CO43,CR43), 0) | CV43: =IFERROR(AVERAGE(G43,J43,M43,P43,S43,V43,Y43,AB43,AE43,AH43,AK43,AN43,AQ43,AT43,AW43,AZ43,BC43,BF43,BI43,BL43,BO43,BR43,BU43,BX43,CA43,CD43,CG43,CJ43,CM43,CP43,CS43), 0) | CW43: =CU43*CV43
A44: Mango tommy | B44: Kg | H44: =IFERROR(F44*G44, 0) | K44: =IFERROR(I44*J44, 0) | N44: =IFERROR(L44*M44, 0) | Q44: =IFERROR(O44*P44, 0) | T44: =IFERROR(R44*S44, 0) | W44: =IFERROR(U44*V44, 0) | Z44: =IFERROR(X44*Y44, 0) | AC44: =IFERROR(AA44*AB44, 0) | AF44: =IFERROR(AD44*AE44, 0) | AI44: =IFERROR(AG44*AH44, 0) | AL44: =IFERROR(AJ44*AK44, 0) | AO44: =IFERROR(AM44*AN44, 0) | AR44: =IFERROR(AP44*AQ44, 0) | AU44: =IFERROR(AS44*AT44, 0) | AV44: 18 | AW44: 1500 | AX44: 27000 | BA44: =IFERROR(AY44*AZ44, 0) | BD44: =IFERROR(BB44*BC44, 0) | BG44: =IFERROR(BE44*BF44, 0) | BJ44: =IFERROR(BH44*BI44, 0) | BM44: =IFERROR(BK44*BL44, 0) | BP44: =IFERROR(BN44*BO44, 0) | BS44: =IFERROR(BQ44*BR44, 0) | BV44: =IFERROR(BT44*BU44, 0) | BY44: =IFERROR(BW44*BX44, 0) | CB44: =IFERROR(BZ44*CA44, 0) | CE44: =IFERROR(CC44*CD44, 0) | CH44: =IFERROR(CF44*CG44, 0) | CK44: =IFERROR(CI44*CJ44, 0) | CN44: =IFERROR(CL44*CM44, 0) | CQ44: =IFERROR(CO44*CP44, 0) | CT44: =IFERROR(CR44*CS44, 0) | CU44: =IFERROR(SUM(F44,I44,L44,O44,R44,U44,X44,AA44,AD44,AG44,AJ44,AM44,AP44,AS44,AV44,AY44,BB44,BE44,BH44,BK44,BN44,BQ44,BT44,BW44,BZ44,CC44,CF44,CI44,CL44,CO44,CR44), 0) | CV44: =IFERROR(AVERAGE(G44,J44,M44,P44,S44,V44,Y44,AB44,AE44,AH44,AK44,AN44,AQ44,AT44,AW44,AZ44,BC44,BF44,BI44,BL44,BO44,BR44,BU44,BX44,CA44,CD44,CG44,CJ44,CM44,CP44,CS44), 0) | CW44: =CU44*CV44
A45: Limon tahiti | B45: Kg | H45: =IFERROR(F45*G45, 0) | K45: =IFERROR(I45*J45, 0) | N45: =IFERROR(L45*M45, 0) | Q45: =IFERROR(O45*P45, 0) | T45: =IFERROR(R45*S45, 0) | W45: =IFERROR(U45*V45, 0) | Z45: =IFERROR(X45*Y45, 0) | AC45: =IFERROR(AA45*AB45, 0) | AF45: =IFERROR(AD45*AE45, 0) | AI45: =IFERROR(AG45*AH45, 0) | AL45: =IFERROR(AJ45*AK45, 0) | AO45: =IFERROR(AM45*AN45, 0) | AR45: =IFERROR(AP45*AQ45, 0) | AU45: =IFERROR(AS45*AT45, 0) | AX45: =IFERROR(AV45*AW45, 0) | BA45: =IFERROR(AY45*AZ45, 0) | BD45: =IFERROR(BB45*BC45, 0) | BG45: =IFERROR(BE45*BF45, 0) | BJ45: =IFERROR(BH45*BI45, 0) | BM45: =IFERROR(BK45*BL45, 0) | BP45: =IFERROR(BN45*BO45, 0) | BS45: =IFERROR(BQ45*BR45, 0) | BV45: =IFERROR(BT45*BU45, 0) | BY45: =IFERROR(BW45*BX45, 0) | CB45: =IFERROR(BZ45*CA45, 0) | CE45: =IFERROR(CC45*CD45, 0) | CH45: =IFERROR(CF45*CG45, 0) | CK45: =IFERROR(CI45*CJ45, 0) | CN45: =IFERROR(CL45*CM45, 0) | CQ45: =IFERROR(CO45*CP45, 0) | CT45: =IFERROR(CR45*CS45, 0) | CU45: =IFERROR(SUM(F45,I45,L45,O45,R45,U45,X45,AA45,AD45,AG45,AJ45,AM45,AP45,AS45,AV45,AY45,BB45,BE45,BH45,BK45,BN45,BQ45,BT45,BW45,BZ45,CC45,CF45,CI45,CL45,CO45,CR45), 0) | CV45: =IFERROR(AVERAGE(G45,J45,M45,P45,S45,V45,Y45,AB45,AE45,AH45,AK45,AN45,AQ45,AT45,AW45,AZ45,BC45,BF45,BI45,BL45,BO45,BR45,BU45,BX45,CA45,CD45,CG45,CJ45,CM45,CP45,CS45), 0) | CW45: =CU45*CV45
A46: Limon tahiti | B46: Kg | H46: =IFERROR(F46*G46, 0) | K46: =IFERROR(I46*J46, 0) | N46: =IFERROR(L46*M46, 0) | Q46: =IFERROR(O46*P46, 0) | T46: =IFERROR(R46*S46, 0) | W46: =IFERROR(U46*V46, 0) | X46: 2.71 | Y46: 2765 | Z46: 7493 | AC46: =IFERROR(AA46*AB46, 0) | AF46: =IFERROR(AD46*AE46, 0) | AI46: =IFERROR(AG46*AH46, 0) | AL46: =IFERROR(AJ46*AK46, 0) | AO46: =IFERROR(AM46*AN46, 0) | AP46: 131 | AQ46: 2000 | AR46: 262000 | AS46: 68 | AT46: 2500 | AU46: 170000 | AX46: =IFERROR(AV46*AW46, 0) | BA46: =IFERROR(AY46*AZ46, 0) | BD46: =IFERROR(BB46*BC46, 0) | BG46: =IFERROR(BE46*BF46, 0) | BJ46: =IFERROR(BH46*BI46, 0) | BM46: =IFERROR(BK46*BL46, 0) | BN46: 118.3 | BO46: 2000 | BP46: 236600 | BS46: =IFERROR(BQ46*BR46, 0) | BV46: =IFERROR(BT46*BU46, 0) | BY46: =IFERROR(BW46*BX46, 0) | CB46: =IFERROR(BZ46*CA46, 0) | CE46: =IFERROR(CC46*CD46, 0) | CH46: =IFERROR(CF46*CG46, 0) | CK46: =IFERROR(CI46*CJ46, 0) | CN46: =IFERROR(CL46*CM46, 0) | CQ46: =IFERROR(CO46*CP46, 0) | CT46: =IFERROR(CR46*CS46, 0) | CU46: =IFERROR(SUM(F46,I46,L46,O46,R46,U46,X46,AA46,AD46,AG46,AJ46,AM46,AP46,AS46,AV46,AY46,BB46,BE46,BH46,BK46,BN46,BQ46,BT46,BW46,BZ46,CC46,CF46,CI46,CL46,CO46,CR46), 0) | CV46: =IFERROR(AVERAGE(G46,J46,M46,P46,S46,V46,Y46,AB46,AE46,AH46,AK46,AN46,AQ46,AT46,AW46,AZ46,BC46,BF46,BI46,BL46,BO46,BR46,BU46,BX46,CA46,CD46,CG46,CJ46,CM46,CP46,CS46), 0) | CW46: =CU46*CV46
A47: Lechuga batavia x Caja | B47: Kg | H47: =IFERROR(F47*G47, 0) | K47: =IFERROR(I47*J47, 0) | N47: =IFERROR(L47*M47, 0) | Q47: =IFERROR(O47*P47, 0) | T47: =IFERROR(R47*S47, 0) | W47: =IFERROR(U47*V47, 0) | Z47: =IFERROR(X47*Y47, 0) | AC47: =IFERROR(AA47*AB47, 0) | AF47: =IFERROR(AD47*AE47, 0) | AI47: =IFERROR(AG47*AH47, 0) | AL47: =IFERROR(AJ47*AK47, 0) | AO47: =IFERROR(AM47*AN47, 0) | AR47: =IFERROR(AP47*AQ47, 0) | AU47: =IFERROR(AS47*AT47, 0) | AX47: =IFERROR(AV47*AW47, 0) | BA47: =IFERROR(AY47*AZ47, 0) | BD47: =IFERROR(BB47*BC47, 0) | BG47: =IFERROR(BE47*BF47, 0) | BJ47: =IFERROR(BH47*BI47, 0) | BM47: =IFERROR(BK47*BL47, 0) | BP47: =IFERROR(BN47*BO47, 0) | BS47: =IFERROR(BQ47*BR47, 0) | BV47: =IFERROR(BT47*BU47, 0) | BY47: =IFERROR(BW47*BX47, 0) | CB47: =IFERROR(BZ47*CA47, 0) | CE47: =IFERROR(CC47*CD47, 0) | CH47: =IFERROR(CF47*CG47, 0) | CK47: =IFERROR(CI47*CJ47, 0) | CN47: =IFERROR(CL47*CM47, 0) | CQ47: =IFERROR(CO47*CP47, 0) | CT47: =IFERROR(CR47*CS47, 0) | CU47: =IFERROR(SUM(F47,I47,L47,O47,R47,U47,X47,AA47,AD47,AG47,AJ47,AM47,AP47,AS47,AV47,AY47,BB47,BE47,BH47,BK47,BN47,BQ47,BT47,BW47,BZ47,CC47,CF47,CI47,CL47,CO47,CR47), 0) | CV47: =IFERROR(AVERAGE(G47,J47,M47,P47,S47,V47,Y47,AB47,AE47,AH47,AK47,AN47,AQ47,AT47,AW47,AZ47,BC47,BF47,BI47,BL47,BO47,BR47,BU47,BX47,CA47,CD47,CG47,CJ47,CM47,CP47,CS47), 0) | CW47: =CU47*CV47
A48: Lechuga batavia | B48: Kg | H48: =IFERROR(F48*G48, 0) | K48: =IFERROR(I48*J48, 0) | N48: =IFERROR(L48*M48, 0) | Q48: =IFERROR(O48*P48, 0) | T48: =IFERROR(R48*S48, 0) | W48: =IFERROR(U48*V48, 0) | X48: 1.85 | Y48: 3800 | Z48: 7530 | AC48: =IFERROR(AA48*AB48, 0) | AF48: =IFERROR(AD48*AE48, 0) | AI48: =IFERROR(AG48*AH48, 0) | AL48: =IFERROR(AJ48*AK48, 0) | AO48: =IFERROR(AM48*AN48, 0) | AP48: 73 | AQ48: 2800 | AR48: 204400 | AS48: 47 | AT48: 2800 | AU48: 131600 | AX48: =IFERROR(AV48*AW48, 0) | BA48: =IFERROR(AY48*AZ48, 0) | BD48: =IFERROR(BB48*BC48, 0) | BG48: =IFERROR(BE48*BF48, 0) | BJ48: =IFERROR(BH48*BI48, 0) | BM48: =IFERROR(BK48*BL48, 0) | BN48: 1 | BO48: 30000 | BP48: 30000 | BS48: =IFERROR(BQ48*BR48, 0) | BV48: =IFERROR(BT48*BU48, 0) | BY48: =IFERROR(BW48*BX48, 0) | CB48: =IFERROR(BZ48*CA48, 0) | CE48: =IFERROR(CC48*CD48, 0) | CH48: =IFERROR(CF48*CG48, 0) | CK48: =IFERROR(CI48*CJ48, 0) | CN48: =IFERROR(CL48*CM48, 0) | CQ48: =IFERROR(CO48*CP48, 0) | CT48: =IFERROR(CR48*CS48, 0) | CU48: =IFERROR(SUM(F48,I48,L48,O48,R48,U48,X48,AA48,AD48,AG48,AJ48,AM48,AP48,AS48,AV48,AY48,BB48,BE48,BH48,BK48,BN48,BQ48,BT48,BW48,BZ48,CC48,CF48,CI48,CL48,CO48,CR48), 0) | CV48: =IFERROR(AVERAGE(G48,J48,M48,P48,S48,V48,Y48,AB48,AE48,AH48,AK48,AN48,AQ48,AT48,AW48,AZ48,BC48,BF48,BI48,BL48,BO48,BR48,BU48,BX48,CA48,CD48,CG48,CJ48,CM48,CP48,CS48), 0) | CW48: =CU48*CV48
A49: Laurel | B49: Kg | H49: =IFERROR(F49*G49, 0) | I49: 1 | J49: 25000 | K49: 25000 | N49: =IFERROR(L49*M49, 0) | Q49: =IFERROR(O49*P49, 0) | T49: =IFERROR(R49*S49, 0) | W49: =IFERROR(U49*V49, 0) | Z49: =IFERROR(X49*Y49, 0) | AC49: =IFERROR(AA49*AB49, 0) | AF49: =IFERROR(AD49*AE49, 0) | AI49: =IFERROR(AG49*AH49, 0) | AL49: =IFERROR(AJ49*AK49, 0) | AO49: =IFERROR(AM49*AN49, 0) | AR49: =IFERROR(AP49*AQ49, 0) | AU49: =IFERROR(AS49*AT49, 0) | AX49: =IFERROR(AV49*AW49, 0) | BA49: =IFERROR(AY49*AZ49, 0) | BD49: =IFERROR(BB49*BC49, 0) | BG49: =IFERROR(BE49*BF49, 0) | BJ49: =IFERROR(BH49*BI49, 0) | BM49: =IFERROR(BK49*BL49, 0) | BP49: =IFERROR(BN49*BO49, 0) | BS49: =IFERROR(BQ49*BR49, 0) | BV49: =IFERROR(BT49*BU49, 0) | BY49: =IFERROR(BW49*BX49, 0) | CB49: =IFERROR(BZ49*CA49, 0) | CE49: =IFERROR(CC49*CD49, 0) | CH49: =IFERROR(CF49*CG49, 0) | CK49: =IFERROR(CI49*CJ49, 0) | CN49: =IFERROR(CL49*CM49, 0) | CQ49: =IFERROR(CO49*CP49, 0) | CT49: =IFERROR(CR49*CS49, 0) | CU49: =IFERROR(SUM(F49,I49,L49,O49,R49,U49,X49,AA49,AD49,AG49,AJ49,AM49,AP49,AS49,AV49,AY49,BB49,BE49,BH49,BK49,BN49,BQ49,BT49,BW49,BZ49,CC49,CF49,CI49,CL49,CO49,CR49), 0) | CV49: =IFERROR(AVERAGE(G49,J49,M49,P49,S49,V49,Y49,AB49,AE49,AH49,AK49,AN49,AQ49,AT49,AW49,AZ49,BC49,BF49,BI49,BL49,BO49,BR49,BU49,BX49,CA49,CD49,CG49,CJ49,CM49,CP49,CS49), 0) | CW49: =CU49*CV49
A50: Hoja de tamal | B50: Kg | H50: =IFERROR(F50*G50, 0) | I50: 1 | J50: 100000 | K50: 100000 | N50: =IFERROR(L50*M50, 0) | Q50: =IFERROR(O50*P50, 0) | T50: =IFERROR(R50*S50, 0) | W50: =IFERROR(U50*V50, 0) | Z50: =IFERROR(X50*Y50, 0) | AC50: =IFERROR(AA50*AB50, 0) | AD50: 1 | AE50: 40000 | AF50: 40000 | AI50: =IFERROR(AG50*AH50, 0) | AL50: =IFERROR(AJ50*AK50, 0) | AO50: =IFERROR(AM50*AN50, 0) | AR50: =IFERROR(AP50*AQ50, 0) | AU50: =IFERROR(AS50*AT50, 0) | AX50: =IFERROR(AV50*AW50, 0) | BA50: =IFERROR(AY50*AZ50, 0) | BD50: =IFERROR(BB50*BC50, 0) | BG50: =IFERROR(BE50*BF50, 0) | BJ50: =IFERROR(BH50*BI50, 0) | BM50: =IFERROR(BK50*BL50, 0) | BP50: =IFERROR(BN50*BO50, 0) | BS50: =IFERROR(BQ50*BR50, 0) | BV50: =IFERROR(BT50*BU50, 0) | BY50: =IFERROR(BW50*BX50, 0) | CB50: =IFERROR(BZ50*CA50, 0) | CE50: =IFERROR(CC50*CD50, 0) | CH50: =IFERROR(CF50*CG50, 0) | CK50: =IFERROR(CI50*CJ50, 0) | CN50: =IFERROR(CL50*CM50, 0) | CQ50: =IFERROR(CO50*CP50, 0) | CT50: =IFERROR(CR50*CS50, 0) | CU50: =IFERROR(SUM(F50,I50,L50,O50,R50,U50,X50,AA50,AD50,AG50,AJ50,AM50,AP50,AS50,AV50,AY50,BB50,BE50,BH50,BK50,BN50,BQ50,BT50,BW50,BZ50,CC50,CF50,CI50,CL50,CO50,CR50), 0) | CV50: =IFERROR(AVERAGE(G50,J50,M50,P50,S50,V50,Y50,AB50,AE50,AH50,AK50,AN50,AQ50,AT50,AW50,AZ50,BC50,BF50,BI50,BL50,BO50,BR50,BU50,BX50,CA50,CD50,CG50,CJ50,CM50,CP50,CS50), 0) | CW50: =CU50*CV50
A51: Hiervas | B51: Kg | H51: =IFERROR(F51*G51, 0) | K51: =IFERROR(I51*J51, 0) | N51: =IFERROR(L51*M51, 0) | Q51: =IFERROR(O51*P51, 0) | T51: =IFERROR(R51*S51, 0) | W51: =IFERROR(U51*V51, 0) | Z51: =IFERROR(X51*Y51, 0) | AC51: =IFERROR(AA51*AB51, 0) | AF51: =IFERROR(AD51*AE51, 0) | AI51: =IFERROR(AG51*AH51, 0) | AL51: =IFERROR(AJ51*AK51, 0) | AO51: =IFERROR(AM51*AN51, 0) | AP51: 4 | AQ51: 2000 | AR51: 8000 | AS51: 3 | AT51: 2000 | AU51: 6000 | AX51: =IFERROR(AV51*AW51, 0) | BA51: =IFERROR(AY51*AZ51, 0) | BD51: =IFERROR(BB51*BC51, 0) | BG51: =IFERROR(BE51*BF51, 0) | BJ51: =IFERROR(BH51*BI51, 0) | BM51: =IFERROR(BK51*BL51, 0) | BN51: 1 | BO51: 2000 | BP51: 2000 | BS51: =IFERROR(BQ51*BR51, 0) | BV51: =IFERROR(BT51*BU51, 0) | BY51: =IFERROR(BW51*BX51, 0) | CB51: =IFERROR(BZ51*CA51, 0) | CE51: =IFERROR(CC51*CD51, 0) | CH51: =IFERROR(CF51*CG51, 0) | CK51: =IFERROR(CI51*CJ51, 0) | CN51: =IFERROR(CL51*CM51, 0) | CQ51: =IFERROR(CO51*CP51, 0) | CT51: =IFERROR(CR51*CS51, 0) | CU51: =IFERROR(SUM(F51,I51,L51,O51,R51,U51,X51,AA51,AD51,AG51,AJ51,AM51,AP51,AS51,AV51,AY51,BB51,BE51,BH51,BK51,BN51,BQ51,BT51,BW51,BZ51,CC51,CF51,CI51,CL51,CO51,CR51), 0) | CV51: =IFERROR(AVERAGE(G51,J51,M51,P51,S51,V51,Y51,AB51,AE51,AH51,AK51,AN51,AQ51,AT51,AW51,AZ51,BC51,BF51,BI51,BL51,BO51,BR51,BU51,BX51,CA51,CD51,CG51,CJ51,CM51,CP51,CS51), 0) | CW51: =CU51*CV51
A52: Habichuela | B52: Kg | H52: =IFERROR(F52*G52, 0) | K52: =IFERROR(I52*J52, 0) | N52: =IFERROR(L52*M52, 0) | Q52: =IFERROR(O52*P52, 0) | T52: =IFERROR(R52*S52, 0) | W52: =IFERROR(U52*V52, 0) | Z52: =IFERROR(X52*Y52, 0) | AC52: =IFERROR(AA52*AB52, 0) | AF52: =IFERROR(AD52*AE52, 0) | AI52: =IFERROR(AG52*AH52, 0) | AL52: =IFERROR(AJ52*AK52, 0) | AO52: =IFERROR(AM52*AN52, 0) | AP52: 6.1 | AQ52: 3000 | AR52: 20780 | AU52: =IFERROR(AS52*AT52, 0) | AX52: =IFERROR(AV52*AW52, 0) | BA52: =IFERROR(AY52*AZ52, 0) | BD52: =IFERROR(BB52*BC52, 0) | BG52: =IFERROR(BE52*BF52, 0) | BJ52: =IFERROR(BH52*BI52, 0) | BM52: =IFERROR(BK52*BL52, 0) | BN52: 3.1 | BO52: 4000 | BP52: 12400 | BS52: =IFERROR(BQ52*BR52, 0) | BV52: =IFERROR(BT52*BU52, 0) | BY52: =IFERROR(BW52*BX52, 0) | CB52: =IFERROR(BZ52*CA52, 0) | CE52: =IFERROR(CC52*CD52, 0) | CH52: =IFERROR(CF52*CG52, 0) | CK52: =IFERROR(CI52*CJ52, 0) | CN52: =IFERROR(CL52*CM52, 0) | CQ52: =IFERROR(CO52*CP52, 0) | CT52: =IFERROR(CR52*CS52, 0) | CU52: =IFERROR(SUM(F52,I52,L52,O52,R52,U52,X52,AA52,AD52,AG52,AJ52,AM52,AP52,AS52,AV52,AY52,BB52,BE52,BH52,BK52,BN52,BQ52,BT52,BW52,BZ52,CC52,CF52,CI52,CL52,CO52,CR52), 0) | CV52: =IFERROR(AVERAGE(G52,J52,M52,P52,S52,V52,Y52,AB52,AE52,AH52,AK52,AN52,AQ52,AT52,AW52,AZ52,BC52,BF52,BI52,BL52,BO52,BR52,BU52,BX52,CA52,CD52,CG52,CJ52,CM52,CP52,CS52), 0) | CW52: =CU52*CV52
A53: Guasca | B53: Lb | H53: =IFERROR(F53*G53, 0) | K53: =IFERROR(I53*J53, 0) | N53: =IFERROR(L53*M53, 0) | Q53: =IFERROR(O53*P53, 0) | T53: =IFERROR(R53*S53, 0) | W53: =IFERROR(U53*V53, 0) | Z53: =IFERROR(X53*Y53, 0) | AC53: =IFERROR(AA53*AB53, 0) | AD53: 1 | AE53: 10000 | AF53: 10000 | AI53: =IFERROR(AG53*AH53, 0) | AL53: =IFERROR(AJ53*AK53, 0) | AO53: =IFERROR(AM53*AN53, 0) | AR53: =IFERROR(AP53*AQ53, 0) | AU53: =IFERROR(AS53*AT53, 0) | AX53: =IFERROR(AV53*AW53, 0) | BA53: =IFERROR(AY53*AZ53, 0) | BD53: =IFERROR(BB53*BC53, 0) | BG53: =IFERROR(BE53*BF53, 0) | BJ53: =IFERROR(BH53*BI53, 0) | BM53: =IFERROR(BK53*BL53, 0) | BP53: =IFERROR(BN53*BO53, 0) | BS53: =IFERROR(BQ53*BR53, 0) | BV53: =IFERROR(BT53*BU53, 0) | BY53: =IFERROR(BW53*BX53, 0) | CB53: =IFERROR(BZ53*CA53, 0) | CE53: =IFERROR(CC53*CD53, 0) | CH53: =IFERROR(CF53*CG53, 0) | CK53: =IFERROR(CI53*CJ53, 0) | CN53: =IFERROR(CL53*CM53, 0) | CQ53: =IFERROR(CO53*CP53, 0) | CT53: =IFERROR(CR53*CS53, 0) | CU53: =IFERROR(SUM(F53,I53,L53,O53,R53,U53,X53,AA53,AD53,AG53,AJ53,AM53,AP53,AS53,AV53,AY53,BB53,BE53,BH53,BK53,BN53,BQ53,BT53,BW53,BZ53,CC53,CF53,CI53,CL53,CO53,CR53), 0) | CV53: =IFERROR(AVERAGE(G53,J53,M53,P53,S53,V53,Y53,AB53,AE53,AH53,AK53,AN53,AQ53,AT53,AW53,AZ53,BC53,BF53,BI53,BL53,BO53,BR53,BU53,BX53,CA53,CD53,CG53,CJ53,CM53,CP53,CS53), 0) | CW53: =CU53*CV53
A54: Frijol verdes | B54: Lb | H54: =IFERROR(F54*G54, 0) | K54: =IFERROR(I54*J54, 0) | N54: =IFERROR(L54*M54, 0) | Q54: =IFERROR(O54*P54, 0) | T54: =IFERROR(R54*S54, 0) | W54: =IFERROR(U54*V54, 0) | Z54: =IFERROR(X54*Y54, 0) | AC54: =IFERROR(AA54*AB54, 0) | AF54: =IFERROR(AD54*AE54, 0) | AI54: =IFERROR(AG54*AH54, 0) | AL54: =IFERROR(AJ54*AK54, 0) | AO54: =IFERROR(AM54*AN54, 0) | AR54: =IFERROR(AP54*AQ54, 0) | AU54: =IFERROR(AS54*AT54, 0) | AX54: =IFERROR(AV54*AW54, 0) | BA54: =IFERROR(AY54*AZ54, 0) | BD54: =IFERROR(BB54*BC54, 0) | BG54: =IFERROR(BE54*BF54, 0) | BJ54: =IFERROR(BH54*BI54, 0) | BM54: =IFERROR(BK54*BL54, 0) | BP54: =IFERROR(BN54*BO54, 0) | BS54: =IFERROR(BQ54*BR54, 0) | BV54: =IFERROR(BT54*BU54, 0) | BY54: =IFERROR(BW54*BX54, 0) | CB54: =IFERROR(BZ54*CA54, 0) | CE54: =IFERROR(CC54*CD54, 0) | CH54: =IFERROR(CF54*CG54, 0) | CK54: =IFERROR(CI54*CJ54, 0) | CN54: =IFERROR(CL54*CM54, 0) | CQ54: =IFERROR(CO54*CP54, 0) | CT54: =IFERROR(CR54*CS54, 0) | CU54: =IFERROR(SUM(F54,I54,L54,O54,R54,U54,X54,AA54,AD54,AG54,AJ54,AM54,AP54,AS54,AV54,AY54,BB54,BE54,BH54,BK54,BN54,BQ54,BT54,BW54,BZ54,CC54,CF54,CI54,CL54,CO54,CR54), 0) | CV54: =IFERROR(AVERAGE(G54,J54,M54,P54,S54,V54,Y54,AB54,AE54,AH54,AK54,AN54,AQ54,AT54,AW54,AZ54,BC54,BF54,BI54,BL54,BO54,BR54,BU54,BX54,CA54,CD54,CG54,CJ54,CM54,CP54,CS54), 0) | CW54: =CU54*CV54
A55: Fresa | B55: Kg | H55: =IFERROR(F55*G55, 0) | K55: =IFERROR(I55*J55, 0) | N55: =IFERROR(L55*M55, 0) | Q55: =IFERROR(O55*P55, 0) | T55: =IFERROR(R55*S55, 0) | W55: =IFERROR(U55*V55, 0) | Z55: =IFERROR(X55*Y55, 0) | AC55: =IFERROR(AA55*AB55, 0) | AF55: =IFERROR(AD55*AE55, 0) | AI55: =IFERROR(AG55*AH55, 0) | AL55: =IFERROR(AJ55*AK55, 0) | AO55: =IFERROR(AM55*AN55, 0) | AR55: =IFERROR(AP55*AQ55, 0) | AU55: =IFERROR(AS55*AT55, 0) | AX55: =IFERROR(AV55*AW55, 0) | BA55: =IFERROR(AY55*AZ55, 0) | BD55: =IFERROR(BB55*BC55, 0) | BG55: =IFERROR(BE55*BF55, 0) | BJ55: =IFERROR(BH55*BI55, 0) | BM55: =IFERROR(BK55*BL55, 0) | BP55: =IFERROR(BN55*BO55, 0) | BS55: =IFERROR(BQ55*BR55, 0) | BV55: =IFERROR(BT55*BU55, 0) | BY55: =IFERROR(BW55*BX55, 0) | CB55: =IFERROR(BZ55*CA55, 0) | CE55: =IFERROR(CC55*CD55, 0) | CH55: =IFERROR(CF55*CG55, 0) | CK55: =IFERROR(CI55*CJ55, 0) | CN55: =IFERROR(CL55*CM55, 0) | CQ55: =IFERROR(CO55*CP55, 0) | CT55: =IFERROR(CR55*CS55, 0) | CU55: =IFERROR(SUM(F55,I55,L55,O55,R55,U55,X55,AA55,AD55,AG55,AJ55,AM55,AP55,AS55,AV55,AY55,BB55,BE55,BH55,BK55,BN55,BQ55,BT55,BW55,BZ55,CC55,CF55,CI55,CL55,CO55,CR55), 0) | CV55: =IFERROR(AVERAGE(G55,J55,M55,P55,S55,V55,Y55,AB55,AE55,AH55,AK55,AN55,AQ55,AT55,AW55,AZ55,BC55,BF55,BI55,BL55,BO55,BR55,BU55,BX55,CA55,CD55,CG55,CJ55,CM55,CP55,CS55), 0) | CW55: =CU55*CV55
A56: Espinaca | B56: Lb | H56: =IFERROR(F56*G56, 0) | K56: =IFERROR(I56*J56, 0) | N56: =IFERROR(L56*M56, 0) | Q56: =IFERROR(O56*P56, 0) | T56: =IFERROR(R56*S56, 0) | W56: =IFERROR(U56*V56, 0) | Z56: =IFERROR(X56*Y56, 0) | AC56: =IFERROR(AA56*AB56, 0) | AF56: =IFERROR(AD56*AE56, 0) | AI56: =IFERROR(AG56*AH56, 0) | AL56: =IFERROR(AJ56*AK56, 0) | AO56: =IFERROR(AM56*AN56, 0) | AR56: =IFERROR(AP56*AQ56, 0) | AU56: =IFERROR(AS56*AT56, 0) | AX56: =IFERROR(AV56*AW56, 0) | BA56: =IFERROR(AY56*AZ56, 0) | BD56: =IFERROR(BB56*BC56, 0) | BG56: =IFERROR(BE56*BF56, 0) | BJ56: =IFERROR(BH56*BI56, 0) | BM56: =IFERROR(BK56*BL56, 0) | BP56: =IFERROR(BN56*BO56, 0) | BS56: =IFERROR(BQ56*BR56, 0) | BV56: =IFERROR(BT56*BU56, 0) | BY56: =IFERROR(BW56*BX56, 0) | CB56: =IFERROR(BZ56*CA56, 0) | CE56: =IFERROR(CC56*CD56, 0) | CH56: =IFERROR(CF56*CG56, 0) | CK56: =IFERROR(CI56*CJ56, 0) | CN56: =IFERROR(CL56*CM56, 0) | CQ56: =IFERROR(CO56*CP56, 0) | CT56: =IFERROR(CR56*CS56, 0) | CU56: =IFERROR(SUM(F56,I56,L56,O56,R56,U56,X56,AA56,AD56,AG56,AJ56,AM56,AP56,AS56,AV56,AY56,BB56,BE56,BH56,BK56,BN56,BQ56,BT56,BW56,BZ56,CC56,CF56,CI56,CL56,CO56,CR56), 0) | CV56: =IFERROR(AVERAGE(G56,J56,M56,P56,S56,V56,Y56,AB56,AE56,AH56,AK56,AN56,AQ56,AT56,AW56,AZ56,BC56,BF56,BI56,BL56,BO56,BR56,BU56,BX56,CA56,CD56,CG56,CJ56,CM56,CP56,CS56), 0) | CW56: =CU56*CV56
A57: Coliflor | B57: Kg | H57: =IFERROR(F57*G57, 0) | K57: =IFERROR(I57*J57, 0) | N57: =IFERROR(L57*M57, 0) | Q57: =IFERROR(O57*P57, 0) | T57: =IFERROR(R57*S57, 0) | W57: =IFERROR(U57*V57, 0) | Z57: =IFERROR(X57*Y57, 0) | AC57: =IFERROR(AA57*AB57, 0) | AF57: =IFERROR(AD57*AE57, 0) | AI57: =IFERROR(AG57*AH57, 0) | AL57: =IFERROR(AJ57*AK57, 0) | AO57: =IFERROR(AM57*AN57, 0) | AR57: =IFERROR(AP57*AQ57, 0) | AU57: =IFERROR(AS57*AT57, 0) | AX57: =IFERROR(AV57*AW57, 0) | BA57: =IFERROR(AY57*AZ57, 0) | BD57: =IFERROR(BB57*BC57, 0) | BG57: =IFERROR(BE57*BF57, 0) | BJ57: =IFERROR(BH57*BI57, 0) | BM57: =IFERROR(BK57*BL57, 0) | BP57: =IFERROR(BN57*BO57, 0) | BQ57: 1.19 | BR57: 7280 | BS57: 8664 | BV57: =IFERROR(BT57*BU57, 0) | BY57: =IFERROR(BW57*BX57, 0) | CB57: =IFERROR(BZ57*CA57, 0) | CE57: =IFERROR(CC57*CD57, 0) | CH57: =IFERROR(CF57*CG57, 0) | CK57: =IFERROR(CI57*CJ57, 0) | CN57: =IFERROR(CL57*CM57, 0) | CQ57: =IFERROR(CO57*CP57, 0) | CT57: =IFERROR(CR57*CS57, 0) | CU57: =IFERROR(SUM(F57,I57,L57,O57,R57,U57,X57,AA57,AD57,AG57,AJ57,AM57,AP57,AS57,AV57,AY57,BB57,BE57,BH57,BK57,BN57,BQ57,BT57,BW57,BZ57,CC57,CF57,CI57,CL57,CO57,CR57), 0) | CV57: =IFERROR(AVERAGE(G57,J57,M57,P57,S57,V57,Y57,AB57,AE57,AH57,AK57,AN57,AQ57,AT57,AW57,AZ57,BC57,BF57,BI57,BL57,BO57,BR57,BU57,BX57,CA57,CD57,CG57,CJ57,CM57,CP57,CS57), 0) | CW57: =CU57*CV57
A58: Coco unidad | B58: Kg | H58: =IFERROR(F58*G58, 0) | K58: =IFERROR(I58*J58, 0) | N58: =IFERROR(L58*M58, 0) | Q58: =IFERROR(O58*P58, 0) | T58: =IFERROR(R58*S58, 0) | W58: =IFERROR(U58*V58, 0) | Z58: =IFERROR(X58*Y58, 0) | AC58: =IFERROR(AA58*AB58, 0) | AF58: =IFERROR(AD58*AE58, 0) | AI58: =IFERROR(AG58*AH58, 0) | AL58: =IFERROR(AJ58*AK58, 0) | AO58: =IFERROR(AM58*AN58, 0) | AR58: =IFERROR(AP58*AQ58, 0) | AU58: =IFERROR(AS58*AT58, 0) | AX58: =IFERROR(AV58*AW58, 0) | BA58: =IFERROR(AY58*AZ58, 0) | BD58: =IFERROR(BB58*BC58, 0) | BG58: =IFERROR(BE58*BF58, 0) | BJ58: =IFERROR(BH58*BI58, 0) | BM58: =IFERROR(BK58*BL58, 0) | BP58: =IFERROR(BN58*BO58, 0) | BS58: =IFERROR(BQ58*BR58, 0) | BV58: =IFERROR(BT58*BU58, 0) | BY58: =IFERROR(BW58*BX58, 0) | CB58: =IFERROR(BZ58*CA58, 0) | CE58: =IFERROR(CC58*CD58, 0) | CH58: =IFERROR(CF58*CG58, 0) | CK58: =IFERROR(CI58*CJ58, 0) | CN58: =IFERROR(CL58*CM58, 0) | CQ58: =IFERROR(CO58*CP58, 0) | CT58: =IFERROR(CR58*CS58, 0) | CU58: =IFERROR(SUM(F58,I58,L58,O58,R58,U58,X58,AA58,AD58,AG58,AJ58,AM58,AP58,AS58,AV58,AY58,BB58,BE58,BH58,BK58,BN58,BQ58,BT58,BW58,BZ58,CC58,CF58,CI58,CL58,CO58,CR58), 0) | CV58: =IFERROR(AVERAGE(G58,J58,M58,P58,S58,V58,Y58,AB58,AE58,AH58,AK58,AN58,AQ58,AT58,AW58,AZ58,BC58,BF58,BI58,BL58,BO58,BR58,BU58,BX58,CA58,CD58,CG58,CJ58,CM58,CP58,CS58), 0) | CW58: =CU58*CV58
A59: Coco rallado | B59: Kg | H59: =IFERROR(F59*G59, 0) | K59: =IFERROR(I59*J59, 0) | N59: =IFERROR(L59*M59, 0) | Q59: =IFERROR(O59*P59, 0) | T59: =IFERROR(R59*S59, 0) | W59: =IFERROR(U59*V59, 0) | Z59: =IFERROR(X59*Y59, 0) | AC59: =IFERROR(AA59*AB59, 0) | AF59: =IFERROR(AD59*AE59, 0) | AI59: =IFERROR(AG59*AH59, 0) | AL59: =IFERROR(AJ59*AK59, 0) | AO59: =IFERROR(AM59*AN59, 0) | AR59: =IFERROR(AP59*AQ59, 0) | AU59: =IFERROR(AS59*AT59, 0) | AX59: =IFERROR(AV59*AW59, 0) | BA59: =IFERROR(AY59*AZ59, 0) | BD59: =IFERROR(BB59*BC59, 0) | BG59: =IFERROR(BE59*BF59, 0) | BJ59: =IFERROR(BH59*BI59, 0) | BM59: =IFERROR(BK59*BL59, 0) | BP59: =IFERROR(BN59*BO59, 0) | BS59: =IFERROR(BQ59*BR59, 0) | BV59: =IFERROR(BT59*BU59, 0) | BY59: =IFERROR(BW59*BX59, 0) | CB59: =IFERROR(BZ59*CA59, 0) | CE59: =IFERROR(CC59*CD59, 0) | CH59: =IFERROR(CF59*CG59, 0) | CK59: =IFERROR(CI59*CJ59, 0) | CN59: =IFERROR(CL59*CM59, 0) | CQ59: =IFERROR(CO59*CP59, 0) | CT59: =IFERROR(CR59*CS59, 0) | CU59: =IFERROR(SUM(F59,I59,L59,O59,R59,U59,X59,AA59,AD59,AG59,AJ59,AM59,AP59,AS59,AV59,AY59,BB59,BE59,BH59,BK59,BN59,BQ59,BT59,BW59,BZ59,CC59,CF59,CI59,CL59,CO59,CR59), 0) | CV59: =IFERROR(AVERAGE(G59,J59,M59,P59,S59,V59,Y59,AB59,AE59,AH59,AK59,AN59,AQ59,AT59,AW59,AZ59,BC59,BF59,BI59,BL59,BO59,BR59,BU59,BX59,CA59,CD59,CG59,CJ59,CM59,CP59,CS59), 0) | CW59: =CU59*CV59
A60: Cimarron | B60: Atado | H60: =IFERROR(F60*G60, 0) | K60: =IFERROR(I60*J60, 0) | N60: =IFERROR(L60*M60, 0) | Q60: =IFERROR(O60*P60, 0) | T60: =IFERROR(R60*S60, 0) | W60: =IFERROR(U60*V60, 0) | Z60: =IFERROR(X60*Y60, 0) | AC60: =IFERROR(AA60*AB60, 0) | AF60: =IFERROR(AD60*AE60, 0) | AI60: =IFERROR(AG60*AH60, 0) | AL60: =IFERROR(AJ60*AK60, 0) | AO60: =IFERROR(AM60*AN60, 0) | AR60: =IFERROR(AP60*AQ60, 0) | AU60: =IFERROR(AS60*AT60, 0) | AX60: =IFERROR(AV60*AW60, 0) | BA60: =IFERROR(AY60*AZ60, 0) | BD60: =IFERROR(BB60*BC60, 0) | BG60: =IFERROR(BE60*BF60, 0) | BJ60: =IFERROR(BH60*BI60, 0) | BM60: =IFERROR(BK60*BL60, 0) | BP60: =IFERROR(BN60*BO60, 0) | BS60: =IFERROR(BQ60*BR60, 0) | BV60: =IFERROR(BT60*BU60, 0) | BY60: =IFERROR(BW60*BX60, 0) | CB60: =IFERROR(BZ60*CA60, 0) | CE60: =IFERROR(CC60*CD60, 0) | CH60: =IFERROR(CF60*CG60, 0) | CK60: =IFERROR(CI60*CJ60, 0) | CN60: =IFERROR(CL60*CM60, 0) | CQ60: =IFERROR(CO60*CP60, 0) | CT60: =IFERROR(CR60*CS60, 0) | CU60: =IFERROR(SUM(F60,I60,L60,O60,R60,U60,X60,AA60,AD60,AG60,AJ60,AM60,AP60,AS60,AV60,AY60,BB60,BE60,BH60,BK60,BN60,BQ60,BT60,BW60,BZ60,CC60,CF60,CI60,CL60,CO60,CR60), 0) | CV60: =IFERROR(AVERAGE(G60,J60,M60,P60,S60,V60,Y60,AB60,AE60,AH60,AK60,AN60,AQ60,AT60,AW60,AZ60,BC60,BF60,BI60,BL60,BO60,BR60,BU60,BX60,CA60,CD60,CG60,CJ60,CM60,CP60,CS60), 0) | CW60: =CU60*CV60
A61: Cilantro | B61: Atado | H61: =IFERROR(F61*G61, 0) | K61: =IFERROR(I61*J61, 0) | N61: =IFERROR(L61*M61, 0) | Q61: =IFERROR(O61*P61, 0) | T61: =IFERROR(R61*S61, 0) | W61: =IFERROR(U61*V61, 0) | Z61: =IFERROR(X61*Y61, 0) | AC61: =IFERROR(AA61*AB61, 0) | AF61: =IFERROR(AD61*AE61, 0) | AI61: =IFERROR(AG61*AH61, 0) | AL61: =IFERROR(AJ61*AK61, 0) | AO61: =IFERROR(AM61*AN61, 0) | AP61: 4 | AQ61: 8000 | AR61: 31000 | AS61: 6 | AT61: 8000 | AU61: 42000 | AX61: =IFERROR(AV61*AW61, 0) | BA61: =IFERROR(AY61*AZ61, 0) | BD61: =IFERROR(BB61*BC61, 0) | BG61: =IFERROR(BE61*BF61, 0) | BJ61: =IFERROR(BH61*BI61, 0) | BM61: =IFERROR(BK61*BL61, 0) | BN61: 2 | BO61: 8000 | BP61: 16000 | BS61: =IFERROR(BQ61*BR61, 0) | BV61: =IFERROR(BT61*BU61, 0) | BY61: =IFERROR(BW61*BX61, 0) | CB61: =IFERROR(BZ61*CA61, 0) | CE61: =IFERROR(CC61*CD61, 0) | CH61: =IFERROR(CF61*CG61, 0) | CK61: =IFERROR(CI61*CJ61, 0) | CN61: =IFERROR(CL61*CM61, 0) | CQ61: =IFERROR(CO61*CP61, 0) | CT61: =IFERROR(CR61*CS61, 0) | CU61: =IFERROR(SUM(F61,I61,L61,O61,R61,U61,X61,AA61,AD61,AG61,AJ61,AM61,AP61,AS61,AV61,AY61,BB61,BE61,BH61,BK61,BN61,BQ61,BT61,BW61,BZ61,CC61,CF61,CI61,CL61,CO61,CR61), 0) | CV61: =IFERROR(AVERAGE(G61,J61,M61,P61,S61,V61,Y61,AB61,AE61,AH61,AK61,AN61,AQ61,AT61,AW61,AZ61,BC61,BF61,BI61,BL61,BO61,BR61,BU61,BX61,CA61,CD61,CG61,CJ61,CM61,CP61,CS61), 0) | CW61: =CU61*CV61
A62: Champiñon | B62: Kl | H62: =IFERROR(F62*G62, 0) | K62: =IFERROR(I62*J62, 0) | N62: =IFERROR(L62*M62, 0) | Q62: =IFERROR(O62*P62, 0) | T62: =IFERROR(R62*S62, 0) | W62: =IFERROR(U62*V62, 0) | Z62: =IFERROR(X62*Y62, 0) | AC62: =IFERROR(AA62*AB62, 0) | AF62: =IFERROR(AD62*AE62, 0) | AI62: =IFERROR(AG62*AH62, 0) | AL62: =IFERROR(AJ62*AK62, 0) | AO62: =IFERROR(AM62*AN62, 0) | AR62: =IFERROR(AP62*AQ62, 0) | AU62: =IFERROR(AS62*AT62, 0) | AX62: =IFERROR(AV62*AW62, 0) | BA62: =IFERROR(AY62*AZ62, 0) | BD62: =IFERROR(BB62*BC62, 0) | BG62: =IFERROR(BE62*BF62, 0) | BJ62: =IFERROR(BH62*BI62, 0) | BM62: =IFERROR(BK62*BL62, 0) | BP62: =IFERROR(BN62*BO62, 0) | BS62: =IFERROR(BQ62*BR62, 0) | BV62: =IFERROR(BT62*BU62, 0) | BY62: =IFERROR(BW62*BX62, 0) | CB62: =IFERROR(BZ62*CA62, 0) | CE62: =IFERROR(CC62*CD62, 0) | CH62: =IFERROR(CF62*CG62, 0) | CK62: =IFERROR(CI62*CJ62, 0) | CN62: =IFERROR(CL62*CM62, 0) | CQ62: =IFERROR(CO62*CP62, 0) | CT62: =IFERROR(CR62*CS62, 0) | CU62: =IFERROR(SUM(F62,I62,L62,O62,R62,U62,X62,AA62,AD62,AG62,AJ62,AM62,AP62,AS62,AV62,AY62,BB62,BE62,BH62,BK62,BN62,BQ62,BT62,BW62,BZ62,CC62,CF62,CI62,CL62,CO62,CR62), 0) | CV62: =IFERROR(AVERAGE(G62,J62,M62,P62,S62,V62,Y62,AB62,AE62,AH62,AK62,AN62,AQ62,AT62,AW62,AZ62,BC62,BF62,BI62,BL62,BO62,BR62,BU62,BX62,CA62,CD62,CG62,CJ62,CM62,CP62,CS62), 0) | CW62: =CU62*CV62
A63: Champinon*250g tajado setas | B63: Kl | H63: =IFERROR(F63*G63, 0) | K63: =IFERROR(I63*J63, 0) | N63: =IFERROR(L63*M63, 0) | Q63: =IFERROR(O63*P63, 0) | T63: =IFERROR(R63*S63, 0) | W63: =IFERROR(U63*V63, 0) | Z63: =IFERROR(X63*Y63, 0) | AC63: =IFERROR(AA63*AB63, 0) | AF63: =IFERROR(AD63*AE63, 0) | AI63: =IFERROR(AG63*AH63, 0) | AL63: =IFERROR(AJ63*AK63, 0) | AO63: =IFERROR(AM63*AN63, 0) | AR63: =IFERROR(AP63*AQ63, 0) | AU63: =IFERROR(AS63*AT63, 0) | AX63: =IFERROR(AV63*AW63, 0) | BA63: =IFERROR(AY63*AZ63, 0) | BD63: =IFERROR(BB63*BC63, 0) | BG63: =IFERROR(BE63*BF63, 0) | BJ63: =IFERROR(BH63*BI63, 0) | BM63: =IFERROR(BK63*BL63, 0) | BP63: =IFERROR(BN63*BO63, 0) | BS63: =IFERROR(BQ63*BR63, 0) | BV63: =IFERROR(BT63*BU63, 0) | BY63: =IFERROR(BW63*BX63, 0) | CB63: =IFERROR(BZ63*CA63, 0) | CE63: =IFERROR(CC63*CD63, 0) | CH63: =IFERROR(CF63*CG63, 0) | CK63: =IFERROR(CI63*CJ63, 0) | CN63: =IFERROR(CL63*CM63, 0) | CQ63: =IFERROR(CO63*CP63, 0) | CT63: =IFERROR(CR63*CS63, 0) | CU63: =IFERROR(SUM(F63,I63,L63,O63,R63,U63,X63,AA63,AD63,AG63,AJ63,AM63,AP63,AS63,AV63,AY63,BB63,BE63,BH63,BK63,BN63,BQ63,BT63,BW63,BZ63,CC63,CF63,CI63,CL63,CO63,CR63), 0) | CV63: =IFERROR(AVERAGE(G63,J63,M63,P63,S63,V63,Y63,AB63,AE63,AH63,AK63,AN63,AQ63,AT63,AW63,AZ63,BC63,BF63,BI63,BL63,BO63,BR63,BU63,BX63,CA63,CD63,CG63,CJ63,CM63,CP63,CS63), 0) | CW63: =CU63*CV63
A64: Cebolla larga | B64: Atados | H64: =IFERROR(F64*G64, 0) | K64: =IFERROR(I64*J64, 0) | N64: =IFERROR(L64*M64, 0) | Q64: =IFERROR(O64*P64, 0) | T64: =IFERROR(R64*S64, 0) | W64: =IFERROR(U64*V64, 0) | Z64: =IFERROR(X64*Y64, 0) | AC64: =IFERROR(AA64*AB64, 0) | AF64: =IFERROR(AD64*AE64, 0) | AI64: =IFERROR(AG64*AH64, 0) | AL64: =IFERROR(AJ64*AK64, 0) | AO64: =IFERROR(AM64*AN64, 0) | AR64: =IFERROR(AP64*AQ64, 0) | AU64: =IFERROR(AS64*AT64, 0) | AX64: =IFERROR(AV64*AW64, 0) | BA64: =IFERROR(AY64*AZ64, 0) | BD64: =IFERROR(BB64*BC64, 0) | BG64: =IFERROR(BE64*BF64, 0) | BJ64: =IFERROR(BH64*BI64, 0) | BM64: =IFERROR(BK64*BL64, 0) | BP64: =IFERROR(BN64*BO64, 0) | BS64: =IFERROR(BQ64*BR64, 0) | BV64: =IFERROR(BT64*BU64, 0) | BY64: =IFERROR(BW64*BX64, 0) | CB64: =IFERROR(BZ64*CA64, 0) | CE64: =IFERROR(CC64*CD64, 0) | CH64: =IFERROR(CF64*CG64, 0) | CK64: =IFERROR(CI64*CJ64, 0) | CN64: =IFERROR(CL64*CM64, 0) | CQ64: =IFERROR(CO64*CP64, 0) | CT64: =IFERROR(CR64*CS64, 0) | CU64: =IFERROR(SUM(F64,I64,L64,O64,R64,U64,X64,AA64,AD64,AG64,AJ64,AM64,AP64,AS64,AV64,AY64,BB64,BE64,BH64,BK64,BN64,BQ64,BT64,BW64,BZ64,CC64,CF64,CI64,CL64,CO64,CR64), 0) | CV64: =IFERROR(AVERAGE(G64,J64,M64,P64,S64,V64,Y64,AB64,AE64,AH64,AK64,AN64,AQ64,AT64,AW64,AZ64,BC64,BF64,BI64,BL64,BO64,BR64,BU64,BX64,CA64,CD64,CG64,CJ64,CM64,CP64,CS64), 0) | CW64: =CU64*CV64
A65: Cebolla cabezona | B65: Kg | H65: =IFERROR(F65*G65, 0) | K65: =IFERROR(I65*J65, 0) | N65: =IFERROR(L65*M65, 0) | Q65: =IFERROR(O65*P65, 0) | T65: =IFERROR(R65*S65, 0) | W65: =IFERROR(U65*V65, 0) | X65: 1.72 | Y65: 6880 | Z65: 11834 | AC65: =IFERROR(AA65*AB65, 0) | AF65: =IFERROR(AD65*AE65, 0) | AI65: =IFERROR(AG65*AH65, 0) | AL65: =IFERROR(AJ65*AK65, 0) | AO65: =IFERROR(AM65*AN65, 0) | AP65: 15.2 | AQ65: 3500 | AR65: 53200 | AS65: 13.7 | AT65: 3800 | AU65: 52060 | AX65: =IFERROR(AV65*AW65, 0) | BA65: =IFERROR(AY65*AZ65, 0) | BD65: =IFERROR(BB65*BC65, 0) | BG65: =IFERROR(BE65*BF65, 0) | BJ65: =IFERROR(BH65*BI65, 0) | BM65: =IFERROR(BK65*BL65, 0) | BN65: 12.8 | BO65: 3800 | BP65: 47280 | BS65: =IFERROR(BQ65*BR65, 0) | BV65: =IFERROR(BT65*BU65, 0) | BY65: =IFERROR(BW65*BX65, 0) | CB65: =IFERROR(BZ65*CA65, 0) | CE65: =IFERROR(CC65*CD65, 0) | CH65: =IFERROR(CF65*CG65, 0) | CK65: =IFERROR(CI65*CJ65, 0) | CN65: =IFERROR(CL65*CM65, 0) | CQ65: =IFERROR(CO65*CP65, 0) | CT65: =IFERROR(CR65*CS65, 0) | CU65: =IFERROR(SUM(F65,I65,L65,O65,R65,U65,X65,AA65,AD65,AG65,AJ65,AM65,AP65,AS65,AV65,AY65,BB65,BE65,BH65,BK65,BN65,BQ65,BT65,BW65,BZ65,CC65,CF65,CI65,CL65,CO65,CR65), 0) | CV65: =IFERROR(AVERAGE(G65,J65,M65,P65,S65,V65,Y65,AB65,AE65,AH65,AK65,AN65,AQ65,AT65,AW65,AZ65,BC65,BF65,BI65,BL65,BO65,BR65,BU65,BX65,CA65,CD65,CG65,CJ65,CM65,CP65,CS65), 0) | CW65: =CU65*CV65
A66: Carbon | B66: Bulto | H66: =IFERROR(F66*G66, 0) | K66: =IFERROR(I66*J66, 0) | N66: =IFERROR(L66*M66, 0) | Q66: =IFERROR(O66*P66, 0) | T66: =IFERROR(R66*S66, 0) | W66: =IFERROR(U66*V66, 0) | Z66: =IFERROR(X66*Y66, 0) | AC66: =IFERROR(AA66*AB66, 0) | AF66: =IFERROR(AD66*AE66, 0) | AI66: =IFERROR(AG66*AH66, 0) | AL66: =IFERROR(AJ66*AK66, 0) | AO66: =IFERROR(AM66*AN66, 0) | AR66: =IFERROR(AP66*AQ66, 0) | AU66: =IFERROR(AS66*AT66, 0) | AX66: =IFERROR(AV66*AW66, 0) | BA66: =IFERROR(AY66*AZ66, 0) | BD66: =IFERROR(BB66*BC66, 0) | BG66: =IFERROR(BE66*BF66, 0) | BJ66: =IFERROR(BH66*BI66, 0) | BM66: =IFERROR(BK66*BL66, 0) | BP66: =IFERROR(BN66*BO66, 0) | BS66: =IFERROR(BQ66*BR66, 0) | BV66: =IFERROR(BT66*BU66, 0) | BY66: =IFERROR(BW66*BX66, 0) | CB66: =IFERROR(BZ66*CA66, 0) | CE66: =IFERROR(CC66*CD66, 0) | CH66: =IFERROR(CF66*CG66, 0) | CK66: =IFERROR(CI66*CJ66, 0) | CN66: =IFERROR(CL66*CM66, 0) | CQ66: =IFERROR(CO66*CP66, 0) | CT66: =IFERROR(CR66*CS66, 0) | CU66: =IFERROR(SUM(F66,I66,L66,O66,R66,U66,X66,AA66,AD66,AG66,AJ66,AM66,AP66,AS66,AV66,AY66,BB66,BE66,BH66,BK66,BN66,BQ66,BT66,BW66,BZ66,CC66,CF66,CI66,CL66,CO66,CR66), 0) | CV66: =IFERROR(AVERAGE(G66,J66,M66,P66,S66,V66,Y66,AB66,AE66,AH66,AK66,AN66,AQ66,AT66,AW66,AZ66,BC66,BF66,BI66,BL66,BO66,BR66,BU66,BX66,CA66,CD66,CG66,CJ66,CM66,CP66,CS66), 0) | CW66: =CU66*CV66
A67: Brocoly | B67: Kg | H67: =IFERROR(F67*G67, 0) | K67: =IFERROR(I67*J67, 0) | N67: =IFERROR(L67*M67, 0) | Q67: =IFERROR(O67*P67, 0) | T67: =IFERROR(R67*S67, 0) | W67: =IFERROR(U67*V67, 0) | Z67: =IFERROR(X67*Y67, 0) | AC67: =IFERROR(AA67*AB67, 0) | AF67: =IFERROR(AD67*AE67, 0) | AI67: =IFERROR(AG67*AH67, 0) | AL67: =IFERROR(AJ67*AK67, 0) | AO67: =IFERROR(AM67*AN67, 0) | AR67: =IFERROR(AP67*AQ67, 0) | AU67: =IFERROR(AS67*AT67, 0) | AX67: =IFERROR(AV67*AW67, 0) | BA67: =IFERROR(AY67*AZ67, 0) | BD67: =IFERROR(BB67*BC67, 0) | BG67: =IFERROR(BE67*BF67, 0) | BJ67: =IFERROR(BH67*BI67, 0) | BM67: =IFERROR(BK67*BL67, 0) | BP67: =IFERROR(BN67*BO67, 0) | BQ67: 0.695 | BR67: 7280 | BS67: 5060 | BV67: =IFERROR(BT67*BU67, 0) | BY67: =IFERROR(BW67*BX67, 0) | CB67: =IFERROR(BZ67*CA67, 0) | CE67: =IFERROR(CC67*CD67, 0) | CH67: =IFERROR(CF67*CG67, 0) | CK67: =IFERROR(CI67*CJ67, 0) | CN67: =IFERROR(CL67*CM67, 0) | CQ67: =IFERROR(CO67*CP67, 0) | CT67: =IFERROR(CR67*CS67, 0) | CU67: =IFERROR(SUM(F67,I67,L67,O67,R67,U67,X67,AA67,AD67,AG67,AJ67,AM67,AP67,AS67,AV67,AY67,BB67,BE67,BH67,BK67,BN67,BQ67,BT67,BW67,BZ67,CC67,CF67,CI67,CL67,CO67,CR67), 0) | CV67: =IFERROR(AVERAGE(G67,J67,M67,P67,S67,V67,Y67,AB67,AE67,AH67,AK67,AN67,AQ67,AT67,AW67,AZ67,BC67,BF67,BI67,BL67,BO67,BR67,BU67,BX67,CA67,CD67,CG67,CJ67,CM67,CP67,CS67), 0) | CW67: =CU67*CV67
A68: Banano | B68: Kg | H68: =IFERROR(F68*G68, 0) | K68: =IFERROR(I68*J68, 0) | N68: =IFERROR(L68*M68, 0) | Q68: =IFERROR(O68*P68, 0) | T68: =IFERROR(R68*S68, 0) | W68: =IFERROR(U68*V68, 0) | X68: 2.22 | Y68: 4500 | Z68: 9989 | AC68: =IFERROR(AA68*AB68, 0) | AF68: =IFERROR(AD68*AE68, 0) | AI68: =IFERROR(AG68*AH68, 0) | AL68: =IFERROR(AJ68*AK68, 0) | AO68: =IFERROR(AM68*AN68, 0) | AR68: =IFERROR(AP68*AQ68, 0) | AU68: =IFERROR(AS68*AT68, 0) | AX68: =IFERROR(AV68*AW68, 0) | BA68: =IFERROR(AY68*AZ68, 0) | BD68: =IFERROR(BB68*BC68, 0) | BG68: =IFERROR(BE68*BF68, 0) | BJ68: =IFERROR(BH68*BI68, 0) | BM68: =IFERROR(BK68*BL68, 0) | BP68: =IFERROR(BN68*BO68, 0) | BS68: =IFERROR(BQ68*BR68, 0) | BV68: =IFERROR(BT68*BU68, 0) | BY68: =IFERROR(BW68*BX68, 0) | CB68: =IFERROR(BZ68*CA68, 0) | CE68: =IFERROR(CC68*CD68, 0) | CH68: =IFERROR(CF68*CG68, 0) | CK68: =IFERROR(CI68*CJ68, 0) | CN68: =IFERROR(CL68*CM68, 0) | CQ68: =IFERROR(CO68*CP68, 0) | CT68: =IFERROR(CR68*CS68, 0) | CU68: =IFERROR(SUM(F68,I68,L68,O68,R68,U68,X68,AA68,AD68,AG68,AJ68,AM68,AP68,AS68,AV68,AY68,BB68,BE68,BH68,BK68,BN68,BQ68,BT68,BW68,BZ68,CC68,CF68,CI68,CL68,CO68,CR68), 0) | CV68: =IFERROR(AVERAGE(G68,J68,M68,P68,S68,V68,Y68,AB68,AE68,AH68,AK68,AN68,AQ68,AT68,AW68,AZ68,BC68,BF68,BI68,BL68,BO68,BR68,BU68,BX68,CA68,CD68,CG68,CJ68,CM68,CP68,CS68), 0) | CW68: =CU68*CV68
A69: Arracacha | B69: Kg | H69: =IFERROR(F69*G69, 0) | K69: =IFERROR(I69*J69, 0) | N69: =IFERROR(L69*M69, 0) | Q69: =IFERROR(O69*P69, 0) | T69: =IFERROR(R69*S69, 0) | W69: =IFERROR(U69*V69, 0) | Z69: =IFERROR(X69*Y69, 0) | AC69: =IFERROR(AA69*AB69, 0) | AF69: =IFERROR(AD69*AE69, 0) | AI69: =IFERROR(AG69*AH69, 0) | AL69: =IFERROR(AJ69*AK69, 0) | AO69: =IFERROR(AM69*AN69, 0) | AR69: =IFERROR(AP69*AQ69, 0) | AU69: =IFERROR(AS69*AT69, 0) | AX69: =IFERROR(AV69*AW69, 0) | BA69: =IFERROR(AY69*AZ69, 0) | BD69: =IFERROR(BB69*BC69, 0) | BG69: =IFERROR(BE69*BF69, 0) | BJ69: =IFERROR(BH69*BI69, 0) | BM69: =IFERROR(BK69*BL69, 0) | BN69: 3.1 | BO69: 6500 | BP69: 20150 | BS69: =IFERROR(BQ69*BR69, 0) | BV69: =IFERROR(BT69*BU69, 0) | BY69: =IFERROR(BW69*BX69, 0) | CB69: =IFERROR(BZ69*CA69, 0) | CE69: =IFERROR(CC69*CD69, 0) | CH69: =IFERROR(CF69*CG69, 0) | CK69: =IFERROR(CI69*CJ69, 0) | CN69: =IFERROR(CL69*CM69, 0) | CQ69: =IFERROR(CO69*CP69, 0) | CT69: =IFERROR(CR69*CS69, 0) | CU69: =IFERROR(SUM(F69,I69,L69,O69,R69,U69,X69,AA69,AD69,AG69,AJ69,AM69,AP69,AS69,AV69,AY69,BB69,BE69,BH69,BK69,BN69,BQ69,BT69,BW69,BZ69,CC69,CF69,CI69,CL69,CO69,CR69), 0) | CV69: =IFERROR(AVERAGE(G69,J69,M69,P69,S69,V69,Y69,AB69,AE69,AH69,AK69,AN69,AQ69,AT69,AW69,AZ69,BC69,BF69,BI69,BL69,BO69,BR69,BU69,BX69,CA69,CD69,CG69,CJ69,CM69,CP69,CS69), 0) | CW69: =CU69*CV69
A70: Archuchas | B70: Kg | H70: =IFERROR(F70*G70, 0) | K70: =IFERROR(I70*J70, 0) | N70: =IFERROR(L70*M70, 0) | Q70: =IFERROR(O70*P70, 0) | T70: =IFERROR(R70*S70, 0) | W70: =IFERROR(U70*V70, 0) | Z70: =IFERROR(X70*Y70, 0) | AC70: =IFERROR(AA70*AB70, 0) | AF70: =IFERROR(AD70*AE70, 0) | AI70: =IFERROR(AG70*AH70, 0) | AL70: =IFERROR(AJ70*AK70, 0) | AO70: =IFERROR(AM70*AN70, 0) | AR70: =IFERROR(AP70*AQ70, 0) | AU70: =IFERROR(AS70*AT70, 0) | AX70: =IFERROR(AV70*AW70, 0) | BA70: =IFERROR(AY70*AZ70, 0) | BD70: =IFERROR(BB70*BC70, 0) | BG70: =IFERROR(BE70*BF70, 0) | BJ70: =IFERROR(BH70*BI70, 0) | BM70: =IFERROR(BK70*BL70, 0) | BP70: =IFERROR(BN70*BO70, 0) | BS70: =IFERROR(BQ70*BR70, 0) | BV70: =IFERROR(BT70*BU70, 0) | BY70: =IFERROR(BW70*BX70, 0) | CB70: =IFERROR(BZ70*CA70, 0) | CE70: =IFERROR(CC70*CD70, 0) | CH70: =IFERROR(CF70*CG70, 0) | CK70: =IFERROR(CI70*CJ70, 0) | CN70: =IFERROR(CL70*CM70, 0) | CQ70: =IFERROR(CO70*CP70, 0) | CT70: =IFERROR(CR70*CS70, 0) | CU70: =IFERROR(SUM(F70,I70,L70,O70,R70,U70,X70,AA70,AD70,AG70,AJ70,AM70,AP70,AS70,AV70,AY70,BB70,BE70,BH70,BK70,BN70,BQ70,BT70,BW70,BZ70,CC70,CF70,CI70,CL70,CO70,CR70), 0) | CV70: =IFERROR(AVERAGE(G70,J70,M70,P70,S70,V70,Y70,AB70,AE70,AH70,AK70,AN70,AQ70,AT70,AW70,AZ70,BC70,BF70,BI70,BL70,BO70,BR70,BU70,BX70,CA70,CD70,CG70,CJ70,CM70,CP70,CS70), 0) | CW70: =CU70*CV70
A71: Apio | B71: Kg | H71: =IFERROR(F71*G71, 0) | K71: =IFERROR(I71*J71, 0) | N71: =IFERROR(L71*M71, 0) | Q71: =IFERROR(O71*P71, 0) | T71: =IFERROR(R71*S71, 0) | W71: =IFERROR(U71*V71, 0) | Z71: =IFERROR(X71*Y71, 0) | AC71: =IFERROR(AA71*AB71, 0) | AF71: =IFERROR(AD71*AE71, 0) | AI71: =IFERROR(AG71*AH71, 0) | AL71: =IFERROR(AJ71*AK71, 0) | AO71: =IFERROR(AM71*AN71, 0) | AP71: 1.4 | AQ71: 2500 | AR71: 3500 | AS71: 4.2 | AT71: 2500 | AU71: 10500 | AX71: =IFERROR(AV71*AW71, 0) | BA71: =IFERROR(AY71*AZ71, 0) | BD71: =IFERROR(BB71*BC71, 0) | BG71: =IFERROR(BE71*BF71, 0) | BJ71: =IFERROR(BH71*BI71, 0) | BM71: =IFERROR(BK71*BL71, 0) | BP71: =IFERROR(BN71*BO71, 0) | BS71: =IFERROR(BQ71*BR71, 0) | BV71: =IFERROR(BT71*BU71, 0) | BY71: =IFERROR(BW71*BX71, 0) | CB71: =IFERROR(BZ71*CA71, 0) | CE71: =IFERROR(CC71*CD71, 0) | CH71: =IFERROR(CF71*CG71, 0) | CK71: =IFERROR(CI71*CJ71, 0) | CN71: =IFERROR(CL71*CM71, 0) | CQ71: =IFERROR(CO71*CP71, 0) | CT71: =IFERROR(CR71*CS71, 0) | CU71: =IFERROR(SUM(F71,I71,L71,O71,R71,U71,X71,AA71,AD71,AG71,AJ71,AM71,AP71,AS71,AV71,AY71,BB71,BE71,BH71,BK71,BN71,BQ71,BT71,BW71,BZ71,CC71,CF71,CI71,CL71,CO71,CR71), 0) | CV71: =IFERROR(AVERAGE(G71,J71,M71,P71,S71,V71,Y71,AB71,AE71,AH71,AK71,AN71,AQ71,AT71,AW71,AZ71,BC71,BF71,BI71,BL71,BO71,BR71,BU71,BX71,CA71,CD71,CG71,CJ71,CM71,CP71,CS71), 0) | CW71: =CU71*CV71
A72: Alverjas verdes | B72: Kg | H72: =IFERROR(F72*G72, 0) | K72: =IFERROR(I72*J72, 0) | N72: =IFERROR(L72*M72, 0) | Q72: =IFERROR(O72*P72, 0) | T72: =IFERROR(R72*S72, 0) | W72: =IFERROR(U72*V72, 0) | Z72: =IFERROR(X72*Y72, 0) | AC72: =IFERROR(AA72*AB72, 0) | AF72: =IFERROR(AD72*AE72, 0) | AI72: =IFERROR(AG72*AH72, 0) | AL72: =IFERROR(AJ72*AK72, 0) | AO72: =IFERROR(AM72*AN72, 0) | AR72: =IFERROR(AP72*AQ72, 0) | AU72: =IFERROR(AS72*AT72, 0) | AX72: =IFERROR(AV72*AW72, 0) | BA72: =IFERROR(AY72*AZ72, 0) | BD72: =IFERROR(BB72*BC72, 0) | BG72: =IFERROR(BE72*BF72, 0) | BJ72: =IFERROR(BH72*BI72, 0) | BM72: =IFERROR(BK72*BL72, 0) | BP72: =IFERROR(BN72*BO72, 0) | BS72: =IFERROR(BQ72*BR72, 0) | BV72: =IFERROR(BT72*BU72, 0) | BY72: =IFERROR(BW72*BX72, 0) | CB72: =IFERROR(BZ72*CA72, 0) | CE72: =IFERROR(CC72*CD72, 0) | CH72: =IFERROR(CF72*CG72, 0) | CK72: =IFERROR(CI72*CJ72, 0) | CN72: =IFERROR(CL72*CM72, 0) | CQ72: =IFERROR(CO72*CP72, 0) | CT72: =IFERROR(CR72*CS72, 0) | CU72: =IFERROR(SUM(F72,I72,L72,O72,R72,U72,X72,AA72,AD72,AG72,AJ72,AM72,AP72,AS72,AV72,AY72,BB72,BE72,BH72,BK72,BN72,BQ72,BT72,BW72,BZ72,CC72,CF72,CI72,CL72,CO72,CR72), 0) | CV72: =IFERROR(AVERAGE(G72,J72,M72,P72,S72,V72,Y72,AB72,AE72,AH72,AK72,AN72,AQ72,AT72,AW72,AZ72,BC72,BF72,BI72,BL72,BO72,BR72,BU72,BX72,CA72,CD72,CG72,CJ72,CM72,CP72,CS72), 0) | CW72: =CU72*CV72
A73: Ajo pelado | B73: Kl | H73: =IFERROR(F73*G73, 0) | K73: =IFERROR(I73*J73, 0) | N73: =IFERROR(L73*M73, 0) | Q73: =IFERROR(O73*P73, 0) | T73: =IFERROR(R73*S73, 0) | W73: =IFERROR(U73*V73, 0) | Z73: =IFERROR(X73*Y73, 0) | AC73: =IFERROR(AA73*AB73, 0) | AF73: =IFERROR(AD73*AE73, 0) | AI73: =IFERROR(AG73*AH73, 0) | AL73: =IFERROR(AJ73*AK73, 0) | AO73: =IFERROR(AM73*AN73, 0) | AR73: =IFERROR(AP73*AQ73, 0) | AU73: =IFERROR(AS73*AT73, 0) | AV73: 10 | AW73: 11900 | AX73: 119000 | BA73: =IFERROR(AY73*AZ73, 0) | BD73: =IFERROR(BB73*BC73, 0) | BG73: =IFERROR(BE73*BF73, 0) | BJ73: =IFERROR(BH73*BI73, 0) | BM73: =IFERROR(BK73*BL73, 0) | BP73: =IFERROR(BN73*BO73, 0) | BS73: =IFERROR(BQ73*BR73, 0) | BV73: =IFERROR(BT73*BU73, 0) | BY73: =IFERROR(BW73*BX73, 0) | CB73: =IFERROR(BZ73*CA73, 0) | CE73: =IFERROR(CC73*CD73, 0) | CH73: =IFERROR(CF73*CG73, 0) | CK73: =IFERROR(CI73*CJ73, 0) | CN73: =IFERROR(CL73*CM73, 0) | CQ73: =IFERROR(CO73*CP73, 0) | CT73: =IFERROR(CR73*CS73, 0) | CU73: =IFERROR(SUM(F73,I73,L73,O73,R73,U73,X73,AA73,AD73,AG73,AJ73,AM73,AP73,AS73,AV73,AY73,BB73,BE73,BH73,BK73,BN73,BQ73,BT73,BW73,BZ73,CC73,CF73,CI73,CL73,CO73,CR73), 0) | CV73: =IFERROR(AVERAGE(G73,J73,M73,P73,S73,V73,Y73,AB73,AE73,AH73,AK73,AN73,AQ73,AT73,AW73,AZ73,BC73,BF73,BI73,BL73,BO73,BR73,BU73,BX73,CA73,CD73,CG73,CJ73,CM73,CP73,CS73), 0) | CW73: =CU73*CV73
A74: Aguacate | B74: Kg | H74: =IFERROR(F74*G74, 0) | K74: =IFERROR(I74*J74, 0) | N74: =IFERROR(L74*M74, 0) | Q74: =IFERROR(O74*P74, 0) | T74: =IFERROR(R74*S74, 0) | W74: =IFERROR(U74*V74, 0) | Z74: =Y74*X74 | AC74: =IFERROR(AA74*AB74, 0) | AF74: =IFERROR(AD74*AE74, 0) | AI74: =IFERROR(AG74*AH74, 0) | AL74: =IFERROR(AJ74*AK74, 0) | AO74: =IFERROR(AM74*AN74, 0) | AR74: =IFERROR(AP74*AQ74, 0) | AU74: =IFERROR(AS74*AT74, 0) | AX74: =IFERROR(AV74*AW74, 0) | BA74: =IFERROR(AY74*AZ74, 0) | BD74: =IFERROR(BB74*BC74, 0) | BG74: =IFERROR(BE74*BF74, 0) | BJ74: =IFERROR(BH74*BI74, 0) | BM74: =IFERROR(BK74*BL74, 0) | BP74: =IFERROR(BN74*BO74, 0) | BS74: =IFERROR(BQ74*BR74, 0) | BV74: =IFERROR(BT74*BU74, 0) | BY74: =IFERROR(BW74*BX74, 0) | CB74: =IFERROR(BZ74*CA74, 0) | CE74: =IFERROR(CC74*CD74, 0) | CH74: =IFERROR(CF74*CG74, 0) | CK74: =IFERROR(CI74*CJ74, 0) | CN74: =IFERROR(CL74*CM74, 0) | CQ74: =IFERROR(CO74*CP74, 0) | CT74: =IFERROR(CR74*CS74, 0) | CU74: =IFERROR(SUM(F74,I74,L74,O74,R74,U74,X74,AA74,AD74,AG74,AJ74,AM74,AP74,AS74,AV74,AY74,BB74,BE74,BH74,BK74,BN74,BQ74,BT74,BW74,BZ74,CC74,CF74,CI74,CL74,CO74,CR74), 0) | CV74: =IFERROR(AVERAGE(G74,J74,M74,P74,S74,V74,Y74,AB74,AE74,AH74,AK74,AN74,AQ74,AT74,AW74,AZ74,BC74,BF74,BI74,BL74,BO74,BR74,BU74,BX74,CA74,CD74,CG74,CJ74,CM74,CP74,CS74), 0) | CW74: =CU74*CV74
A75: Oregano | B75: Kl | H75: =IFERROR(F75*G75, 0) | K75: =IFERROR(I75*J75, 0) | N75: =IFERROR(L75*M75, 0) | Q75: =IFERROR(O75*P75, 0) | T75: =IFERROR(R75*S75, 0) | W75: =IFERROR(U75*V75, 0) | Z75: =IFERROR(X75*Y75, 0) | AC75: =IFERROR(AA75*AB75, 0) | AF75: =IFERROR(AD75*AE75, 0) | AI75: =IFERROR(AG75*AH75, 0) | AL75: =IFERROR(AJ75*AK75, 0) | AO75: =IFERROR(AM75*AN75, 0) | AR75: =IFERROR(AP75*AQ75, 0) | AU75: =IFERROR(AS75*AT75, 0) | AX75: =IFERROR(AV75*AW75, 0) | BA75: =IFERROR(AY75*AZ75, 0) | BD75: =IFERROR(BB75*BC75, 0) | BG75: =IFERROR(BE75*BF75, 0) | BJ75: =IFERROR(BH75*BI75, 0) | BK75: 1 | BL75: 2311 | BM75: 2311 | BP75: =IFERROR(BN75*BO75, 0) | BS75: =IFERROR(BQ75*BR75, 0) | BV75: =IFERROR(BT75*BU75, 0) | BY75: =IFERROR(BW75*BX75, 0) | CB75: =IFERROR(BZ75*CA75, 0) | CE75: =IFERROR(CC75*CD75, 0) | CH75: =IFERROR(CF75*CG75, 0) | CK75: =IFERROR(CI75*CJ75, 0) | CN75: =IFERROR(CL75*CM75, 0) | CQ75: =IFERROR(CO75*CP75, 0) | CT75: =IFERROR(CR75*CS75, 0) | CU75: =IFERROR(SUM(F75,I75,L75,O75,R75,U75,X75,AA75,AD75,AG75,AJ75,AM75,AP75,AS75,AV75,AY75,BB75,BE75,BH75,BK75,BN75,BQ75,BT75,BW75,BZ75,CC75,CF75,CI75,CL75,CO75,CR75), 0) | CV75: =IFERROR(AVERAGE(G75,J75,M75,P75,S75,V75,Y75,AB75,AE75,AH75,AK75,AN75,AQ75,AT75,AW75,AZ75,BC75,BF75,BI75,BL75,BO75,BR75,BU75,BX75,CA75,CD75,CG75,CJ75,CM75,CP75,CS75), 0) | CW75: =CU75*CV75
A76: Cebolla Larga Atado | B76: Kg | H76: =IFERROR(F76*G76, 0) | K76: =IFERROR(I76*J76, 0) | N76: =IFERROR(L76*M76, 0) | Q76: =IFERROR(O76*P76, 0) | T76: =IFERROR(R76*S76, 0) | W76: =IFERROR(U76*V76, 0) | Z76: =IFERROR(X76*Y76, 0) | AC76: =IFERROR(AA76*AB76, 0) | AF76: =IFERROR(AD76*AE76, 0) | AI76: =IFERROR(AG76*AH76, 0) | AL76: =IFERROR(AJ76*AK76, 0) | AO76: =IFERROR(AM76*AN76, 0) | AP76: 2 | AQ76: 100000 | AR76: 190000 | AS76: 1 | AT76: 90000 | AU76: 90000 | AX76: =IFERROR(AV76*AW76, 0) | BA76: =IFERROR(AY76*AZ76, 0) | BD76: =IFERROR(BB76*BC76, 0) | BG76: =IFERROR(BE76*BF76, 0) | BJ76: =IFERROR(BH76*BI76, 0) | BM76: =IFERROR(BK76*BL76, 0) | BN76: 1.5 | BO76: 90000 | BP76: 105000 | BS76: =IFERROR(BQ76*BR76, 0) | BV76: =IFERROR(BT76*BU76, 0) | BY76: =IFERROR(BW76*BX76, 0) | CB76: =IFERROR(BZ76*CA76, 0) | CE76: =IFERROR(CC76*CD76, 0) | CH76: =IFERROR(CF76*CG76, 0) | CK76: =IFERROR(CI76*CJ76, 0) | CN76: =IFERROR(CL76*CM76, 0) | CQ76: =IFERROR(CO76*CP76, 0) | CT76: =IFERROR(CR76*CS76, 0) | CU76: =IFERROR(SUM(F76,I76,L76,O76,R76,U76,X76,AA76,AD76,AG76,AJ76,AM76,AP76,AS76,AV76,AY76,BB76,BE76,BH76,BK76,BN76,BQ76,BT76,BW76,BZ76,CC76,CF76,CI76,CL76,CO76,CR76), 0) | CV76: =IFERROR(AVERAGE(G76,J76,M76,P76,S76,V76,Y76,AB76,AE76,AH76,AK76,AN76,AQ76,AT76,AW76,AZ76,BC76,BF76,BI76,BL76,BO76,BR76,BU76,BX76,CA76,CD76,CG76,CJ76,CM76,CP76,CS76), 0) | CW76: =CU76*CV76
